Workbook
Name SegmentaçãodeDados_Mês: #N/A

Sheet Planilha8
D1: nova | G1: old | I1: vr.
B2: 1000000 | E2: 1000000
B3: 46143 | E3: 46143
C4: Adj. Ebitda After Capex | F4: Adj. Ebitda After Capex
C9: Actual | F9: Actual
B11: Consolidado nstech | C11: 21.963357 | E11: Consolidado nstech | F11: 22.053523 | H11: =F11-C11 -> 0.09016632 | I11: =H11*10^6 -> 90166.32 | J11: =H11/C11 -> 0.0041053069 | L11: Fechamento Mai26 - Mapeamento de alterações
B13: Consolidado PSL | C13: 19.283281 | E13: Consolidado PSL | F13: 19.359549 | H13: =F13-C13 -> 0.07626753 | I13: =H13*10^6 -> 76267.53 | L13: Total Resultado | N13: =SUM(N20,N27) -> -90.164 | O13: 0.0041053069
B14: Torre TMS | C14: 9.0247915 | E14: Torre TMS | F14: 9.1010591 | H14: =F14-C14 -> 0.07626753 | I14: =H14*10^6 -> 76267.53
B15: Torre ICP Pequeno e Micro | C15: 7.1296428 | E15: Torre ICP Pequeno e Micro | F15: 7.1296428 | H15: =F15-C15 -> 0 | I15: =H15*10^6 -> 0 | M15: Empresa | N15: Valor | O15: Motivo
B16: Bsoft | C16: 5.3466884 | E16: Bsoft | F16: 5.3466884 | H16: =F16-C16 -> 0 | I16: =H16*10^6 -> 0 | L16: ATSLog
B17: Datamex | C17: 0.46905115 | E17: Datamex | F17: 0.46905115 | H17: =F17-C17 -> 0 | I17: =H17*10^6 -> 0 | M17: Outros | N17: -31.41 | O17: Conta de despesa, não veio no BI
B18: Hivecloud | C18: 1.2579829 | E18: Hivecloud | F18: 1.2579829 | H18: =F18-C18 -> 0 | I18: =H18*10^6 -> 0 | M18: Jornada | N18: -44.857 | O18: Conta de despesa, não veio no BI
B19: Otimizy | C19: 0.055920294 | E19: Otimizy | F19: 0.055920294 | H19: =F19-C19 -> 0 | I19: =H19*10^6 -> 0
B20: Torre ICP Médio e Grande | C20: 1.160067 | E20: Torre ICP Médio e Grande | F20: 1.2363345 | H20: =F20-C20 -> 0.07626753 | I20: =H20*10^6 -> 76267.53 | L20: Total PSL | N20: =SUM(N17:N18) -> -76.267
B21: TMS MG | C21: -1.7567802 | E21: TMS MG | F21: -1.7253702 | H21: =F21-C21 -> 0.03141001 | I21: =H21*10^6 -> 31410.01
B22: KMM MG | C22: -2.0497984 | E22: KMM MG | F22: -2.0497984 | H22: =F22-C22 -> 0 | I22: =H22*10^6 -> 0
B23: ATSLog Outros | C23: 0.19805047 | E23: ATSLog Outros | F23: 0.22946048 | H23: =F23-C23 -> 0.03141001 | I23: =H23*10^6 -> 31410.01 | L23: BRK | N23: -5.242 | O23: Conta duplicada em "Others Income and Expenses"
B24: Praxio - Avacorp | C24: -0.080853175 | E24: Praxio - Avacorp | F24: -0.080853175 | H24: =F24-C24 -> 0 | I24: =H24*10^6 -> 0 | L24: Onisys | N24: -8.655 | O24: Conta duplicada em "Others Income and Expenses"
B25: Praxio - Globus | C25: 0.1758209 | E25: Praxio - Globus | F25: 0.1758209 | H25: =F25-C25 -> 0 | I25: =H25*10^6 -> 0
B26: Atua | C26: 2.3656454 | E26: Atua | F26: 2.3656454 | H26: =F26-C26 -> 0 | I26: =H26*10^6 -> 0 | L26: Total BU Embarcador
B27: ATSLog Jornada | C27: 0.40740325 | E27: ATSLog Jornada | F27: 0.45226077 | H27: =F27-C27 -> 0.04485752 | I27: =H27*10^6 -> 44857.52 | N27: =SUM(N23:N24) -> -13.897
B28: NSKote | C28: 0.14379849 | E28: NSKote | F28: 0.14379849 | H28: =F28-C28 -> 0 | I28: =H28*10^6 -> 0
B29: Signa | C29: 0.73508178 | E29: Signa | F29: 0.73508178 | H29: =F29-C29 -> 0 | I29: =H29*10^6 -> 0
B30: Fintech | C30: 2.9369959 | E30: Fintech | F30: 2.9369959 | H30: =F30-C30 -> 0 | I30: =H30*10^6 -> 0
B31: e-frete | C31: 1.3080537 | E31: e-frete | F31: 1.3080537 | H31: =F31-C31 -> 0 | I31: =H31*10^6 -> 0
B32: e-frete Meio Pagamento | C32: 1.3721186 | E32: e-frete Meio Pagamento | F32: 1.3721186 | H32: =F32-C32 -> 0 | I32: =H32*10^6 -> 0
B33: e-frete nsflow | C33: -0.06667544 | E33: e-frete nsflow | F33: -0.06667544 | H33: =F33-C33 -> 0 | I33: =H33*10^6 -> 0
B34: Torre Fintech - PSL | C34: 0.00261056 | E34: Torre Fintech - PSL | F34: 0.00261056 | H34: =F34-C34 -> 0 | I34: =H34*10^6 -> 0
B35: Gasola | C35: 0.54752537 | E35: Gasola | F35: 0.54752537 | H35: =F35-C35 -> 0 | I35: =H35*10^6 -> 0
B36: Pedágio | C36: 1.0814168 | E36: Pedágio | F36: 1.0814168 | H36: =F36-C36 -> 0 | I36: =H36*10^6 -> 0
B37: Digitalcomm | C37: 0.6036868 | E37: Digitalcomm | F37: 0.6036868 | H37: =F37-C37 -> 0 | I37: =H37*10^6 -> 0
B38: e-frete Pedágio | C38: 0.14197763 | E38: e-frete Pedágio | F38: 0.14197763 | H38: =F38-C38 -> 0 | I38: =H38*10^6 -> 0
B39: Qualp | C39: 0.33575241 | E39: Qualp | F39: 0.33575241 | H39: =F39-C39 -> 0 | I39: =H39*10^6 -> 0
... B49: BU PSL CS | C49: -0.1215734 | E49: BU PSL CS | F49: -0.1215734 | H49: =F49-C49 -> 0 | I49: =H49*10^6 -> 0
I50: =H50*10^6 -> 0
B51: Consolidado Embarcador | C51: 12.757321 | E51: Consolidado Embarcador | F51: 12.77122 | H51: =F51-C51 -> 0.01389879 | I51: =H51*10^6 -> 13898.79
B52: Torre VGR | C52: 13.582673 | E52: Torre VGR | F52: 13.596572 | H52: =F52-C52 -> 0.01389879 | I52: =H52*10^6 -> 13898.79
B53: Opentech | C53: 4.6633703 | E53: Opentech | F53: 4.6633703 | H53: =F53-C53 -> 0 | I53: =H53*10^6 -> 0
B54: BRK | C54: 6.256908 | E54: BRK | F54: 6.262151 | H54: =F54-C54 -> 0.00524299 | I54: =H54*10^6 -> 5242.99
B55: LogRisk | C55: 1.3676425 | E55: LogRisk | F55: 1.3676425 | H55: =F55-C55 -> 0 | I55: =H55*10^6 -> 0
B56: Onisys | C56: 0.87821268 | E56: Onisys | F56: 0.88686848 | H56: =F56-C56 -> 0.0086558 | I56: =H56*10^6 -> 8655.8
B57: Trafegus | C57: 0.41653966 | E57: Trafegus | F57: 0.41653966 | H57: =F57-C57 -> 0 | I57: =H57*10^6 -> 0
B58: BU V&RM | C58: 0 | E58: BU V&RM | F58: 0 | H58: =F58-C58 -> 0 | I58: =H58*10^6 -> 0
B59: Torre SW Embarcador | C59: -1.5528942 | E59: Torre SW Embarcador | F59: -1.5528942 | H59: =F59-C59 -> 0
B60: YMS/WMS | C60: 0.16588238 | E60: YMS/WMS | F60: 0.16588238 | H60: =F60-C60 -> 0
B61: GBM | C61: 0.76255616 | E61: GBM | F61: 0.76255616 | H61: =F61-C61 -> 0
B62: KMM YMS | C62: 1.0016422 | E62: KMM YMS | F62: 1.0016422 | H62: =F62-C62 -> 0
B63: KMM WMS | C63: -0.026297191 | E63: KMM WMS | F63: -0.026297191 | H63: =F63-C63 -> 0
B64: Trizy YMS | C64: -1.6490124 | E64: Trizy YMS | F64: -1.6490124 | H64: =F64-C64 -> 0
B65: LogOne | C65: 0.13546175 | E65: LogOne | F65: 0.13546175 | H65: =F65-C65 -> 0
B66: TNS Booking | C66: 0 | E66: TNS Booking | F66: 0 | H66: =F66-C66 -> 0
B67: TNS Match | C67: -0.05846807 | E67: TNS Match | F67: -0.05846807 | H67: =F67-C67 -> 0
B68: Last Mile | C68: 1.0396648 | E68: Last Mile | F68: 1.0396648 | H68: =F68-C68 -> 0
B69: Fusion | C69: 0.6613494 | E69: Fusion | F69: 0.6613494 | H69: =F69-C69 -> 0
B70: Routeasy | C70: -0.0069784878 | E70: Routeasy | F70: -0.0069784878 | H70: =F70-C70 -> 0
... B83: BU EMBARCADOR | C83: -1.719501 | E83: BU EMBARCADOR | F83: -1.719501 | H83: =F83-C83 -> 0
B85: G&A | C85: -3.8116515 | E85: G&A | F85: -3.8116515 | H85: 0
B86: S&M | C86: -2.3933161 | E86: S&M | F86: -2.3933161 | H86: 0
B87: R&D | C87: -3.8722777 | E87: R&D | F87: -3.8722777 | H87: 0
B88: Corporate | C88: -10.077245 | E88: Corporate | F88: -10.077245 | H88: 0
C90: -2.8421709e-14

Sheet Empillhado
F6: Jan | G6: Feb | H6: Mar | I6: Apr | J6: May | K6: YTD | L6: Jun | M6: Jul | N6: Aug | O6: Set | P6: Oct | Q6: Nov | R6: Dec | S6: Full Year | U6: 1Q | V6: 2Q | W6: 3Q | X6: 4Q | Y6: Full Year
C10: Net Revenue Contábil
D11: Actual | E11: 2024 | F11: 69974.548 | G11: 69844.884 | H11: 72994.185 | I11: 75032.306 | J11: 77044.186 | K11: =SUM(F11:J11) -> 364890.11 | L11: 79737.524 | M11: 82235.21 | N11: 82395.173 | O11: 82409.301 | P11: 90317.968 | Q11: 84507.935 | R11: 85975.636 | S11: =SUM(K11:R11) -> 952468.86 | U11: =SUM(F11:G11,H11) -> 212813.62 | V11: =SUM(I11,J11,L11) -> 231814.02 | W11: =SUM(M11:O11) -> 247039.68 | X11: =SUM(P11:R11) -> 260801.54 | Y11: =SUM(U11:X11) -> 952468.86
D12: Actual | E12: 2025 | F12: 91352.84 | G12: 90612.467 | H12: 91858.182 | I12: 92547.036 | J12: 95185.544 | K12: =SUM(F12:J12) -> 461556.07 | L12: 90717.613 | M12: 90078.395 | N12: 98389.379 | O12: 101231.72 | P12: 109542.93 | Q12: 103163.04 | R12: 101055.22 | S12: =SUM(K12:R12) -> 1155734.4 | U12: =SUM(F12:G12,H12) -> 273823.49 | V12: =SUM(I12,J12,L12) -> 278450.19 | W12: =SUM(M12:O12) -> 289699.5 | X12: =SUM(P12:R12) -> 313761.19 | Y12: =SUM(U12:X12) -> 1155734.4
D13: Budget | E13: 2026 | F13: 104452.96 | G13: 104590.28 | H13: 108978.13 | I13: 110603.63 | J13: 113070.77 | K13: =SUM(F13:J13) -> 541695.77 | L13: 118169.73 | M13: 120040.07 | N13: 121218.11 | O13: 135105.5 | P13: 125420.36 | Q13: 126008.46 | R13: 126627.93 | S13: =SUM(K13:R13) -> 1414285.9 | U13: =SUM(F13:G13,H13) -> 318021.37 | V13: =SUM(I13,J13,L13) -> 341844.13 | W13: =SUM(M13:O13) -> 376363.68 | X13: =SUM(P13:R13) -> 378056.75 | Y13: =SUM(U13:X13) -> 1414285.9
D14: Forecast | E14: 2026 | F14: 106599.38 | G14: 104831.3 | H14: 107263.69 | I14: 111037.74 | J14: 111619.43 | K14: =SUM(F14:J14) -> 541351.54 | L14: 115609.78 | M14: 117485.01 | N14: 119733.09 | O14: 133736.62 | P14: 124435.7 | Q14: 125402.45 | R14: 126468.54 | S14: =SUM(K14:R14) -> 1404222.7 | U14: =SUM(F14:G14,H14) -> 318694.37 | V14: =SUM(I14,J14,L14) -> 338266.94 | W14: =SUM(M14:O14) -> 370954.72 | X14: =SUM(P14:R14) -> 376306.7 | Y14: =SUM(U14:X14) -> 1404222.7
D15: Actual | E15: 2026 | F15: 106599.38 | G15: 104831.3 | H15: 107263.69 | I15: 111037.74 | J15: 113734.67 | K15: =SUM(F15:J15) -> 543466.78 | L15: =L14 -> 115609.78 | M15: =M14 -> 117485.01 | N15: =N14 -> 119733.09 | O15: =O14 -> 133736.62 | P15: =P14 -> 124435.7 | Q15: =Q14 -> 125402.45 | R15: =R14 -> 126468.54 | S15: =SUM(K15:R15) -> 1406338 | U15: =SUM(F15:G15,H15) -> 318694.37 | V15: =SUM(I15,J15,L15) -> 340382.19 | W15: =SUM(M15:O15) -> 370954.72 | X15: =SUM(P15:R15) -> 376306.7 | Y15: =SUM(U15:X15) -> 1406338
D16: % 25 (Act) x 24 (Act) | F16: =F12/F11-1 -> 0.30551525 | G16: =G12/G11-1 -> 0.29733865 | H16: =H12/H11-1 -> 0.25843149 | I16: =I12/I11-1 -> 0.23342918 | J16: =J12/J11-1 -> 0.23546692 | K16: =K12/K11-1 -> 0.264918 | L16: =L12/L11-1 -> 0.13770291 | M16: =M12/M11-1 -> 0.095375015 | ... S16: =S12/S11-1 -> 0.21340908 | U16: =U12/U11-1 -> 0.28668218 | V16: =V12/V11-1 -> 0.20117928 | W16: =W12/W11-1 -> 0.17268404 | X16: =X12/X11-1 -> 0.20306493 | Y16: =Y12/Y11-1 -> 0.21340908
D17: % 26 (Act) x 25 (Act) | F17: =F15/F12-1 -> 0.16689731 | G17: =G15/G12-1 -> 0.15691912 | H17: =H15/H12-1 -> 0.16770972 | I17: =I15/I12-1 -> 0.1997979 | J17: =J15/J12-1 -> 0.19487333 | K17: =K15/K12-1 -> 0.17746643 | L17: =L15/L12-1 -> 0.27439174 | M17: =M15/M12-1 -> 0.30425293 | ... S17: =S15/S12-1 -> 0.21683496 | U17: =U15/U12-1 -> 0.16386791 | V17: =V15/V12-1 -> 0.22241677 | W17: =W15/W12-1 -> 0.28048108 | X17: =X15/X12-1 -> 0.19934113 | Y17: =Y15/Y12-1 -> 0.21683496
D18: % 26 (Act) x 26 (Bgt) | F18: =F15/F13-1 -> 0.020549171 | G18: =G15/G13-1 -> 0.0023043876 | H18: =H15/H13-1 -> -0.015731968 | I18: =I15/I13-1 -> 0.0039249233 | J18: =J15/J13-1 -> 0.0058715277 | K18: =K15/K13-1 -> 0.0032693752 | L18: =L15/L13-1 -> -0.021663336 | M18: =M15/M13-1 -> -0.021285069 | ... S18: =S15/S13-1 -> -0.0056197594 | U18: =U15/U13-1 -> 0.0021162031 | V18: =V15/V13-1 -> -0.0042766321 | W18: =W15/W13-1 -> -0.014371608 | X18: =X15/X13-1 -> -0.004629071 | Y18: =Y15/Y13-1 -> -0.0056197594
D19: % 26 (Act) x 26 (Rfc) | F19: =F15/F14-1 -> 0 | G19: =G15/G14-1 -> 0 | H19: =H15/H14-1 -> 0 | I19: =I15/I14-1 -> 0 | J19: =J15/J14-1 -> 0.018950473 | K19: =K15/K14-1 -> 0.0039073333 | L19: =L15/L14-1 -> 0 | M19: =M15/M14-1 -> 0 | ... S19: =S15/S14-1 -> 0.0015063429 | U19: =U15/U14-1 -> 0 | V19: =V15/V14-1 -> 0.0062531706 | W19: =W15/W14-1 -> 0 | X19: =X15/X14-1 -> 0 | Y19: =Y15/Y14-1 -> 0.0015063429
C21: Net Revenue - Contábil Ajustado 1) Ajustando provisão de receita na competência de origem 2) Considera eliminação intercompany de 2024 (contabilmente não existe)
D22: Actual | E22: 2024 | F22: 69593.317 | G22: 69370.873 | H22: 72615.298 | I22: 74529.2 | J22: 76509.687 | K22: =SUM(F22:J22) -> 362618.38 | L22: 79207.305 | M22: 81672.212 | N22: 81694.305 | O22: 81468.623 | P22: 89419.544 | Q22: 83320.997 | R22: 82432.92 | S22: =SUM(K22:R22) -> 941834.28 | U22: =SUM(F22:G22,H22) -> 211579.49 | V22: =SUM(I22,J22,L22) -> 230246.19 | W22: =SUM(M22:O22) -> 244835.14 | X22: =SUM(P22:R22) -> 255173.46 | Y22: =SUM(U22:X22) -> 941834.28
D23: Actual | E23: 2025 | F23: 91352.84 | G23: 90612.467 | H23: 91858.182 | I23: 92547.036 | J23: 95185.544 | K23: =SUM(F23:J23) -> 461556.07 | L23: 93052.097 | M23: 91360.204 | N23: 98389.379 | O23: 101231.72 | P23: 109542.93 | Q23: 103264.41 | R23: 101319.27 | S23: =SUM(K23:R23) -> 1159716.1 | U23: =SUM(F23:G23,H23) -> 273823.49 | V23: =SUM(I23,J23,L23) -> 280784.68 | W23: =SUM(M23:O23) -> 290981.31 | X23: =SUM(P23:R23) -> 314126.62 | Y23: =SUM(U23:X23) -> 1159716.1
D24: Budget | E24: 2026 | F24: =F13 -> 104452.96 | G24: =G13 -> 104590.28 | H24: =H13 -> 108978.13 | I24: =I13 -> 110603.63 | J24: =J13 -> 113070.77 | K24: =SUM(F24:J24) -> 541695.77 | L24: =L13 -> 118169.73 | M24: =M13 -> 120040.07 | N24: =N13 -> 121218.11 | O24: =O13 -> 135105.5 | P24: =P13 -> 125420.36 | Q24: =Q13 -> 126008.46 | R24: =R13 -> 126627.93 | S24: =SUM(K24:R24) -> 1414285.9 | U24: =SUM(F24:G24,H24) -> 318021.37 | V24: =SUM(I24,J24,L24) -> 341844.13 | W24: =SUM(M24:O24) -> 376363.68 | X24: =SUM(P24:R24) -> 378056.75 | Y24: =SUM(U24:X24) -> 1414285.9
D25: Forecast | E25: 2026 | F25: 106599.38 | G25: 104831.3 | H25: 107263.69 | I25: 111037.74 | J25: 111619.43 | K25: =SUM(F25:J25) -> 541351.54 | L25: 115609.78 | M25: 117485.01 | N25: 119733.09 | O25: 133736.62 | P25: 124435.7 | Q25: 125402.45 | R25: 126468.54 | S25: =SUM(K25:R25) -> 1404222.7 | U25: =SUM(F25:G25,H25) -> 318694.37 | V25: =SUM(I25,J25,L25) -> 338266.94 | W25: =SUM(M25:O25) -> 370954.72 | X25: =SUM(P25:R25) -> 376306.7 | Y25: =SUM(U25:X25) -> 1404222.7
D26: Actual | E26: 2026 | F26: =F15 -> 106599.38 | G26: =G15 -> 104831.3 | H26: =H15 -> 107263.69 | I26: 111037.74 | J26: 113734.67 | K26: =SUM(F26:J26) -> 543466.78 | L26: =L25 -> 115609.78 | M26: =M25 -> 117485.01 | N26: =N25 -> 119733.09 | O26: =O25 -> 133736.62 | P26: =P25 -> 124435.7 | Q26: =Q25 -> 125402.45 | R26: =R25 -> 126468.54 | S26: =SUM(K26:R26) -> 1406338 | U26: =SUM(F26:G26,H26) -> 318694.37 | V26: =SUM(I26,J26,L26) -> 340382.19 | W26: =SUM(M26:O26) -> 370954.72 | X26: =SUM(P26:R26) -> 376306.7 | Y26: =SUM(U26:X26) -> 1406338
D27: % 25 (Act) x 24 (Act) | F27: =F23/F22-1 -> 0.31266684 | G27: =G23/G22-1 -> 0.30620336 | H27: =H23/H22-1 -> 0.26499765 | I27: =I23/I22-1 -> 0.24175539 | J27: =J23/J22-1 -> 0.24409794 | K27: =K23/K22-1 -> 0.27284247 | L27: =L23/L22-1 -> 0.17479185 | M27: =M23/M22-1 -> 0.11862043 | ... S27: =S23/S22-1 -> 0.23133773 | U27: =U23/U22-1 -> 0.29418731 | V27: =V23/V22-1 -> 0.21949759 | W27: =W23/W22-1 -> 0.18847852 | X27: =X23/X22-1 -> 0.23103168 | Y27: =Y23/Y22-1 -> 0.23133773
D28: % 26 (Act) x 25 (Act) | F28: =F26/F23-1 -> 0.16689731 | G28: =G26/G23-1 -> 0.15691912 | H28: =H26/H23-1 -> 0.16770972 | I28: =I26/I23-1 -> 0.1997979 | J28: =J26/J23-1 -> 0.19487333 | K28: =K26/K23-1 -> 0.17746643 | L28: =L26/L23-1 -> 0.24241991 | M28: =M26/M23-1 -> 0.28595389 | ... S28: =S26/S23-1 -> 0.21265713 | U28: =U26/U23-1 -> 0.16386791 | V28: =V26/V23-1 -> 0.21225342 | W28: =W26/W23-1 -> 0.2748404 | X28: =X26/X23-1 -> 0.19794592 | Y28: =Y26/Y23-1 -> 0.21265713
D29: % 26 (Act) x 26 (Bgt) | F29: =F26/F24-1 -> 0.020549171 | G29: =G26/G24-1 -> 0.0023043876 | H29: =H26/H24-1 -> -0.015731968 | I29: =I26/I24-1 -> 0.0039249233 | J29: =J26/J24-1 -> 0.0058715277 | K29: =K26/K24-1 -> 0.0032693752 | L29: =L26/L24-1 -> -0.021663336 | M29: =M26/M24-1 -> -0.021285069 | ... S29: =S26/S24-1 -> -0.0056197594 | U29: =U26/U24-1 -> 0.0021162031 | V29: =V26/V24-1 -> -0.0042766321 | W29: =W26/W24-1 -> -0.014371608 | X29: =X26/X24-1 -> -0.004629071 | Y29: =Y26/Y24-1 -> -0.0056197594
D30: % 26 (Act) x 26 (Rfc) | F30: =F26/F25-1 -> 0 | G30: =G26/G25-1 -> 0 | H30: =H26/H25-1 -> 0 | I30: =I26/I25-1 -> 0 | J30: =J26/J25-1 -> 0.018950473 | K30: =K26/K25-1 -> 0.0039073333 | L30: =L26/L25-1 -> 0 | M30: =M26/M25-1 -> 0 | ... S30: =S26/S25-1 -> 0.0015063429 | U30: =U26/U25-1 -> 0 | V30: =V26/V25-1 -> 0.0062531706 | W30: =W26/W25-1 -> 0 | X30: =X26/X25-1 -> 0 | Y30: =Y26/Y25-1 -> 0.0015063429
C32: Net Revenue - Orgânico Ajustado
D33: Actual | E33: 2024 | F33: 74899.301 | G33: 74515.061 | H33: 78804.55 | I33: 80191.125 | J33: 81204.579 | K33: =SUM(F33:J33) -> 389614.61 | L33: 83717.445 | M33: 86214.598 | N33: 86675.377 | O33: 87309.391 | P33: 94903.091 | Q33: 89241.924 | R33: 84295.323 | S33: =SUM(K33:R33) -> 1001971.8 | U33: =SUM(F33:G33,H33) -> 228218.91 | V33: =SUM(I33,J33,L33) -> 245113.15 | W33: =SUM(M33:O33) -> 260199.37 | X33: =SUM(P33:R33) -> 268440.34 | Y33: =SUM(U33:X33) -> 1001971.8
D34: Actual | E34: 2025 | F34: =92754.4230211031 -> 92754.423 | G34: 91911.149 | H34: 93355.651 | I34: 94307.257 | J34: 96658.286 | K34: =SUM(F34:J34) -> 468986.77 | L34: 95038.412 | M34: 92539.742 | N34: 99290.606 | O34: 102168.91 | P34: 110453.8 | Q34: 103264.41 | R34: 101319.27 | S34: =SUM(K34:R34) -> 1173061.9 | U34: =SUM(F34:G34,H34) -> 278021.22 | V34: =SUM(I34,J34,L34) -> 286003.96 | W34: =SUM(M34:O34) -> 293999.26 | X34: =SUM(P34:R34) -> 315037.48 | Y34: =SUM(U34:X34) -> 1173061.9
D35: Budget | E35: 2026 | F35: =F24 -> 104452.96 | G35: =G24 -> 104590.28 | H35: =H24 -> 108978.13 | I35: =I24 -> 110603.63 | J35: =J24 -> 113070.77 | K35: =SUM(F35:J35) -> 541695.77 | L35: =L24 -> 118169.73 | M35: =M24 -> 120040.07 | N35: =N24 -> 121218.11 | O35: =O24 -> 135105.5 | P35: =P24 -> 125420.36 | Q35: =Q24 -> 126008.46 | R35: =R24 -> 126627.93 | S35: =SUM(K35:R35) -> 1414285.9 | U35: =SUM(F35:G35,H35) -> 318021.37 | V35: =SUM(I35,J35,L35) -> 341844.13 | W35: =SUM(M35:O35) -> 376363.68 | X35: =SUM(P35:R35) -> 378056.75 | Y35: =SUM(U35:X35) -> 1414285.9
D36: Forecast | E36: 2026 | F36: 106599.38 | G36: 104831.3 | H36: 107263.69 | I36: 111037.74 | J36: 111619.43 | K36: =SUM(F36:J36) -> 541351.54 | L36: 115609.78 | M36: 117485.01 | N36: 119733.09 | O36: 133736.62 | P36: 124435.7 | Q36: 125402.45 | R36: 126468.54 | S36: =SUM(K36:R36) -> 1404222.7 | U36: =SUM(F36:G36,H36) -> 318694.37 | V36: =SUM(I36,J36,L36) -> 338266.94 | W36: =SUM(M36:O36) -> 370954.72 | X36: =SUM(P36:R36) -> 376306.7 | Y36: =SUM(U36:X36) -> 1404222.7
D37: Actual | E37: 2026 | F37: =F15 -> 106599.38 | G37: =G26 -> 104831.3 | H37: =H26 -> 107263.69 | I37: =I26 -> 111037.74 | J37: =J26 -> 113734.67 | K37: =SUM(F37:J37) -> 543466.78 | L37: =L36 -> 115609.78 | M37: =M36 -> 117485.01 | N37: =N36 -> 119733.09 | O37: =O36 -> 133736.62 | P37: =P36 -> 124435.7 | Q37: =Q36 -> 125402.45 | R37: =R36 -> 126468.54 | S37: =SUM(K37:R37) -> 1406338 | U37: =SUM(F37:G37,H37) -> 318694.37 | V37: =SUM(I37,J37,L37) -> 340382.19 | W37: =SUM(M37:O37) -> 370954.72 | X37: =SUM(P37:R37) -> 376306.7 | Y37: =SUM(U37:X37) -> 1406338
D38: % 25 (Act) x 24 (Act) | F38: =F34/F33-1 -> 0.23838837 | G38: =G34/G33-1 -> 0.23345735 | H38: =H34/H33-1 -> 0.18464798 | I38: =I34/I33-1 -> 0.17603111 | J38: =J34/J33-1 -> 0.19030586 | K38: =K34/K33-1 -> 0.20371965 | L38: =L34/L33-1 -> 0.13522829 | M38: =M34/M33-1 -> 0.073365118 | ... S38: =S34/S33-1 -> 0.17075347 | U38: =U34/U33-1 -> 0.21822167 | V38: =V34/V33-1 -> 0.16682421 | W38: =W34/W33-1 -> 0.12989999 | X38: =X34/X33-1 -> 0.17358473 | Y38: =Y34/Y33-1 -> 0.17075347
D39: % 26 (Act) x 25 (Act) | F39: =F37/F34-1 -> 0.14926469 | G39: =G37/G34-1 -> 0.14057213 | H39: =H37/H34-1 -> 0.1489791 | I39: =I37/I34-1 -> 0.17740397 | J39: =J37/J34-1 -> 0.17666754 | K39: =K37/K34-1 -> 0.15881048 | L39: =L37/L34-1 -> 0.21645317 | M39: =M37/M34-1 -> 0.26956275 | ... S39: =S37/S34-1 -> 0.19886082 | U39: =U37/U34-1 -> 0.14629512 | V39: =V37/V34-1 -> 0.19013104 | W39: =W37/W34-1 -> 0.26175394 | X39: =X37/X34-1 -> 0.19448231 | Y39: =Y37/Y34-1 -> 0.19886082
D40: % 26 (Act) x 26 (Bgt) | F40: =F37/F35-1 -> 0.020549171 | G40: =G37/G35-1 -> 0.0023043876 | H40: =H37/H35-1 -> -0.015731968 | I40: =I37/I35-1 -> 0.0039249233 | J40: =J37/J35-1 -> 0.0058715277 | K40: =K37/K35-1 -> 0.0032693752 | L40: =L37/L35-1 -> -0.021663336 | M40: =M37/M35-1 -> -0.021285069 | ... S40: =S37/S35-1 -> -0.0056197594 | U40: =U37/U35-1 -> 0.0021162031 | V40: =V37/V35-1 -> -0.0042766321 | W40: =W37/W35-1 -> -0.014371608 | X40: =X37/X35-1 -> -0.004629071 | Y40: =Y37/Y35-1 -> -0.0056197594
D41: % 26 (Act) x 26 (Rfc) | F41: =F37/F36-1 -> 0 | G41: =G37/G36-1 -> 0 | H41: =H37/H36-1 -> 0 | I41: =I37/I36-1 -> 0 | J41: =J37/J36-1 -> 0.018950473 | K41: =K37/K36-1 -> 0.0039073333 | L41: =L37/L36-1 -> 0 | M41: =M37/M36-1 -> 0 | ... S41: =S37/S36-1 -> 0.0015063429 | U41: =U37/U36-1 -> 0 | V41: =V37/V36-1 -> 0.0062531706 | W41: =W37/W36-1 -> 0 | X41: =X37/X36-1 -> 0 | Y41: =Y37/Y36-1 -> 0.0015063429
C43: Adjusted EBITDA
D44: Actual | E44: 2024 | F44: 16979.872 | G44: 12830.786 | H44: 15086.515 | I44: 14900.988 | J44: 16517.669 | K44: =SUM(F44:J44) -> 76315.83 | L44: 21271.893 | M44: 19772.247 | N44: 19885.52 | O44: 23989.438 | P44: 22055.599 | Q44: 16363.687 | R44: 11006.227 | S44: =SUM(K44:R44) -> 210660.44 | U44: =SUM(F44:G44,H44) -> 44897.173 | V44: =SUM(I44,J44,L44) -> 52690.55 | W44: =SUM(M44:O44) -> 63647.205 | X44: =SUM(P44:R44) -> 49425.513 | Y44: =SUM(U44:X44) -> 210660.44
D45: Actual | E45: 2025 | F45: 19364.982 | G45: 17234.531 | H45: 18910.161 | I45: 20957.21 | J45: 22718.949 | K45: =SUM(F45:J45) -> 99185.833 | L45: 18698.385 | M45: 11439.798 | N45: 19030.364 | O45: 23163.767 | P45: 33582.398 | Q45: 34781.384 | R45: =24592.3715281149-1576.205 -> 23016.167 | S45: =SUM(K45:R45) -> 262898.1 | U45: =SUM(F45:G45,H45) -> 55509.674 | V45: =SUM(I45,J45,L45) -> 62374.545 | W45: =SUM(M45:O45) -> 53633.929 | X45: =SUM(P45:R45) -> 91379.948 | Y45: =SUM(U45:X45) -> 262898.1
D46: Budget | E46: 2026 | F46: =F64-[1]Empillhado!F154 -> 16586.961 | G46: =G64-[1]Empillhado!G154 -> 15577.279 | H46: =H64-[1]Empillhado!H154 -> 15298.111 | I46: =I64-[1]Empillhado!I154 -> 15977.409 | J46: =J64-[1]Empillhado!J154 -> 17160.363 | K46: =SUM(F46:J46) -> 80600.123 | L46: =L64-[1]Empillhado!L154 -> 17877.244 | M46: =M64-[1]Empillhado!M154 -> 21613.485 | N46: =N64-[1]Empillhado!N154 -> 21353.103 | O46: =O64-[1]Empillhado!O154 -> 28960.706 | P46: =P64-[1]Empillhado!P154 -> 26936.868 | Q46: =Q64-[1]Empillhado!Q154 -> 27232.027 | R46: =R64-[1]Empillhado!R154 -> 25064.366 | S46: =SUM(K46:R46) -> 249637.92 | U46: =SUM(F46:G46,H46) -> 47462.352 | V46: =SUM(I46,J46,L46) -> 51015.015 | W46: =SUM(M46:O46) -> 71927.294 | X46: =SUM(P46:R46) -> 79233.261 | Y46: =SUM(U46:X46) -> 249637.92
D47: Forecast | E47: 2026 | F47: =F48 -> 22496.568 | G47: =G48 -> 21677.649 | H47: =H48 -> 21418.495 | I47: =I48 -> 28184.804 | J47: =J65-[1]Empillhado!J155 -> 17728.989 | K47: =SUM(F47:J47) -> 111506.5 | L47: =L65-[1]Empillhado!L155 -> 17099.983 | M47: =M65-[1]Empillhado!M155 -> 19481.631 | N47: =N65-[1]Empillhado!N155 -> 20150.334 | O47: =O65-[1]Empillhado!O155 -> 27841.228 | P47: =P65-[1]Empillhado!P155 -> 26828.845 | Q47: =Q65-[1]Empillhado!Q155 -> 27132.086 | R47: =R65-[1]Empillhado!R155 -> 27181.863 | S47: =SUM(K47:R47) -> 277222.48 | U47: =SUM(F47:G47,H47) -> 65592.712 | V47: =SUM(I47,J47,L47) -> 63013.776 | W47: =SUM(M47:O47) -> 67473.193 | X47: =SUM(P47:R47) -> 81142.795 | Y47: =SUM(U47:X47) -> 277222.48
D48: Actual | E48: 2026 | F48: 22496.568 | G48: 21677.649 | H48: 21418.495 | I48: 28184.804 | J48: 34075.192 | K48: =SUM(F48:J48) -> 127852.71 | L48: =L47 -> 17099.983 | M48: =M47 -> 19481.631 | N48: =N47 -> 20150.334 | O48: =O47 -> 27841.228 | P48: =P47 -> 26828.845 | Q48: =Q47 -> 27132.086 | R48: =R47 -> 27181.863 | S48: =SUM(K48:R48) -> 293568.68 | U48: =SUM(F48:G48,H48) -> 65592.712 | V48: =SUM(I48,J48,L48) -> 79359.979 | W48: =SUM(M48:O48) -> 67473.193 | X48: =SUM(P48:R48) -> 81142.795 | Y48: =SUM(U48:X48) -> 293568.68
D49: % 25 (Act) x 24 (Act) | F49: =F45/F44-1 -> 0.14046687 | G49: =G45/G44-1 -> 0.34321715 | H49: =H45/H44-1 -> 0.25344791 | I49: =I45/I44-1 -> 0.40643088 | J49: =J45/J44-1 -> 0.37543315 | K49: =K45/K44-1 -> 0.29967574 | L49: =L45/L44-1 -> -0.12098159 | M49: =M45/M44-1 -> -0.42142147 | ... S49: =S45/S44-1 -> 0.24797088 | U49: =U45/U44-1 -> 0.23637347 | V49: =V45/V44-1 -> 0.18378997 | W49: =W45/W44-1 -> -0.15732468 | X49: =X45/X44-1 -> 0.84884168 | Y49: =Y45/Y44-1 -> 0.24797088
D50: % 26 (Act) x 25 (Act) | F50: =F48/F45-1 -> 0.16171389 | G50: =G48/G45-1 -> 0.25780324 | H50: =H48/H45-1 -> 0.13264475 | I50: =I48/I45-1 -> 0.34487383 | J50: =J48/J45-1 -> 0.49985776 | K50: =K48/K45-1 -> 0.28902187 | L50: =L48/L45-1 -> -0.085483424 | M50: =M48/M45-1 -> 0.7029699 | ... S50: =S48/S45-1 -> 0.11666339 | U50: =U48/U45-1 -> 0.1816447 | V50: =V48/V45-1 -> 0.27231356 | W50: =W48/W45-1 -> 0.25803187 | X50: =X48/X45-1 -> -0.11202845 | Y50: =Y48/Y45-1 -> 0.11666339
D51: % 26 (Act) x 26 (Bgt) | F51: =F48/F46-1 -> 0.35628025 | G51: =G48/G46-1 -> 0.39161974 | H51: =H48/H46-1 -> 0.40007445 | I51: =I48/I46-1 -> 0.76404096 | J51: =J48/J46-1 -> 0.98569184 | K51: =K48/K46-1 -> 0.58625946 | L51: =L48/L46-1 -> -0.043477658 | M51: =M48/M46-1 -> -0.098635381 | ... S51: =S48/S46-1 -> 0.17597789 | U51: =U48/U46-1 -> 0.38199456 | V51: =V48/V46-1 -> 0.55562001 | W51: =W48/W46-1 -> -0.06192505 | X51: =X48/X46-1 -> 0.024100146 | Y51: =Y48/Y46-1 -> 0.17597789
D52: % 26 (Act) x 26 (Rfc) | F52: =F48/F47-1 -> 0 | G52: =G48/G47-1 -> 0 | H52: =H48/H47-1 -> 0 | I52: =I48/I47-1 -> 0 | J52: =J48/J47-1 -> 0.9220042 | K52: =K48/K47-1 -> 0.14659416 | L52: =L48/L47-1 -> 0 | M52: =M48/M47-1 -> 0 | ... S52: =S48/S47-1 -> 0.058964204 | U52: =U48/U47-1 -> 0 | V52: =V48/V47-1 -> 0.25940681 | W52: =W48/W47-1 -> 0 | X52: =X48/X47-1 -> 0 | Y52: =Y48/Y47-1 -> 0.058964204
D54: %Ebitda / Net Revenue
D55: Actual | E55: 2024 | F55: =IFERROR(F44/F$22,0) -> 0.24398711 | G55: =IFERROR(G44/G$22,0) -> 0.18495926 | H55: =IFERROR(H44/H$22,0) -> 0.20775946 | I55: =IFERROR(I44/I$22,0) -> 0.1999349 | J55: =IFERROR(J44/J$22,0) -> 0.2158899 | K55: =IFERROR(K44/K$22,0) -> 0.2104577 | L55: =IFERROR(L44/L$22,0) -> 0.26855973 | M55: =IFERROR(M44/M$22,0) -> 0.24209271 | ... S55: =IFERROR(S44/S$22,0) -> 0.22367039 | U55: =IFERROR(U44/U$22,0) -> 0.21220003 | V55: =IFERROR(V44/V$22,0) -> 0.22884439 | W55: =IFERROR(W44/W$22,0) -> 0.25995944 | X55: =IFERROR(X44/X$22,0) -> 0.19369378 | Y55: =IFERROR(Y44/Y$22,0) -> 0.22367039
D56: Actual | E56: 2025 | F56: =IFERROR(F45/F$23,0) -> 0.21198007 | G56: =IFERROR(G45/G$23,0) -> 0.19020044 | H56: =IFERROR(H45/H$23,0) -> 0.20586257 | I56: =IFERROR(I45/I$23,0) -> 0.22644929 | J56: =IFERROR(J45/J$23,0) -> 0.23868066 | K56: =IFERROR(K45/K$23,0) -> 0.21489444 | L56: =IFERROR(L45/L$23,0) -> 0.20094534 | M56: =IFERROR(M45/M$23,0) -> 0.12521642 | ... S56: =IFERROR(S45/S$23,0) -> 0.22669177 | U56: =IFERROR(U45/U$23,0) -> 0.20272064 | V56: =IFERROR(V45/V$23,0) -> 0.22214369 | W56: =IFERROR(W45/W$23,0) -> 0.18432088 | X56: =IFERROR(X45/X$23,0) -> 0.29090164 | Y56: =IFERROR(Y45/Y$23,0) -> 0.22669177
D57: Budget | E57: 2026 | F57: =IFERROR(F46/F$24,0) -> 0.15879838 | G57: =IFERROR(G46/G$24,0) -> 0.1489362 | H57: =IFERROR(H46/H$24,0) -> 0.14037781 | I57: =IFERROR(I46/I$24,0) -> 0.14445646 | J57: =IFERROR(J46/J$24,0) -> 0.15176657 | K57: =IFERROR(K46/K$24,0) -> 0.14879223 | L57: =IFERROR(L46/L$24,0) -> 0.15128446 | M57: =IFERROR(M46/M$24,0) -> 0.18005225 | ... S57: =IFERROR(S46/S$24,0) -> 0.17651164 | U57: =IFERROR(U46/U$24,0) -> 0.14924265 | V57: =IFERROR(V46/V$24,0) -> 0.14923473 | W57: =IFERROR(W46/W$24,0) -> 0.19111115 | X57: =IFERROR(X46/X$24,0) -> 0.20958034 | Y57: =IFERROR(Y46/Y$24,0) -> 0.17651164
D58: Forecast | E58: 2026 | F58: =IFERROR(F47/F$25,0) -> 0.21103845 | G58: =IFERROR(G47/G$25,0) -> 0.20678605 | H58: =IFERROR(H47/H$25,0) -> 0.19968075 | I58: =IFERROR(I47/I$25,0) -> 0.25383085 | J58: =IFERROR(J47/J$25,0) -> 0.15883426 | K58: =IFERROR(K47/K$25,0) -> 0.205978 | L58: =IFERROR(L47/L$25,0) -> 0.14791122 | M58: =IFERROR(M47/M$25,0) -> 0.16582227 | ... S58: =IFERROR(S47/S$25,0) -> 0.19742059 | U58: =IFERROR(U47/U$25,0) -> 0.20581698 | V58: =IFERROR(V47/V$25,0) -> 0.18628417 | W58: =IFERROR(W47/W$25,0) -> 0.18189064 | X58: =IFERROR(X47/X$25,0) -> 0.21562942 | Y58: =IFERROR(Y47/Y$25,0) -> 0.19742059
D59: Actual | E59: 2026 | F59: =IFERROR(F48/F$26,0) -> 0.21103845 | G59: =IFERROR(G48/G$26,0) -> 0.20678605 | H59: =IFERROR(H48/H$26,0) -> 0.19968075 | I59: =IFERROR(I48/I$26,0) -> 0.25383085 | J59: =IFERROR(J48/J$26,0) -> 0.29960251 | K59: =IFERROR(K48/K$26,0) -> 0.23525395 | L59: =IFERROR(L48/L$26,0) -> 0.14791122 | M59: =IFERROR(M48/M$26,0) -> 0.16582227 | ... S59: =IFERROR(S48/S$26,0) -> 0.20874689 | U59: =IFERROR(U48/U$26,0) -> 0.20581698 | V59: =IFERROR(V48/V$26,0) -> 0.23314963 | W59: =IFERROR(W48/W$26,0) -> 0.18189064 | X59: =IFERROR(X48/X$26,0) -> 0.21562942 | Y59: =IFERROR(Y48/Y$26,0) -> 0.20874689
C61: Adjusted EBITDA after Capex
D62: Actual | E62: 2024 | F62: 14873.358 | G62: 10059.657 | H62: 12196.17 | I62: 10477.53 | J62: 13108.645 | K62: =SUM(F62:J62) -> 60715.361 | L62: 18379.596 | M62: 16625.99 | N62: 16877.611 | O62: 20735.244 | P62: 19140.357 | Q62: 13201.365 | R62: 7654.8482 | S62: =SUM(K62:R62) -> 173330.37 | U62: =SUM(F62:G62,H62) -> 37129.186 | V62: =SUM(I62,J62,L62) -> 41965.771 | W62: =SUM(M62:O62) -> 54238.844 | X62: =SUM(P62:R62) -> 39996.57 | Y62: =SUM(U62:X62) -> 173330.37
D63: Actual | E63: 2025 | F63: 17804.925 | G63: 15078.438 | H63: 14147.205 | I63: 16358.879 | J63: 18904.14 | K63: =SUM(F63:J63) -> 82293.587 | L63: 15234.017 | M63: 7439.0613 | N63: 14496.154 | O63: 18249.049 | P63: 18390.785 | Q63: 18619.926 | R63: =15425.6850281149-1576.205 -> 13849.48 | S63: =SUM(K63:R63) -> 188572.06 | U63: =SUM(F63:G63,H63) -> 47030.568 | V63: =SUM(I63,J63,L63) -> 50497.036 | W63: =SUM(M63:O63) -> 40184.265 | X63: =SUM(P63:R63) -> 50860.192 | Y63: =SUM(U63:X63) -> 188572.06
D64: Budget | E64: 2026 | F64: 16586.961 | G64: 15577.279 | H64: 15298.111 | I64: 15977.409 | J64: 17160.363 | K64: =SUM(F64:J64) -> 80600.123 | L64: 17877.244 | M64: 21613.485 | N64: 21353.103 | O64: 28960.706 | P64: 26936.868 | Q64: 27232.027 | R64: 25064.366 | S64: =SUM(K64:R64) -> 249637.92 | U64: =SUM(F64:G64,H64) -> 47462.352 | V64: =SUM(I64,J64,L64) -> 51015.015 | W64: =SUM(M64:O64) -> 71927.294 | X64: =SUM(P64:R64) -> 79233.261 | Y64: =SUM(U64:X64) -> 249637.92
D65: Forecast | E65: 2026 | F65: 19604.25 | G65: 18810.377 | H65: 16239.961 | I65: 19207.3 | J65: 17729.103 | K65: =SUM(F65:J65) -> 91590.991 | L65: 17100.112 | M65: 19481.75 | N65: 20150.506 | O65: 27841.405 | P65: 26829.025 | Q65: 27132.159 | R65: 27181.9 | S65: =SUM(K65:R65) -> 257307.85 | U65: =SUM(F65:G65,H65) -> 54654.588 | V65: =SUM(I65,J65,L65) -> 54036.515 | W65: =SUM(M65:O65) -> 67473.661 | X65: =SUM(P65:R65) -> 81143.084 | Y65: =SUM(U65:X65) -> 257307.85
D66: Actual | E66: 2026 | F66: 19604.25 | G66: 18810.377 | H66: 16239.961 | I66: 19207.3 | J66: 21963.356 | K66: =SUM(F66:J66) -> 95825.244 | L66: =L65 -> 17100.112 | M66: =M65 -> 19481.75 | N66: =N65 -> 20150.506 | O66: =O65 -> 27841.405 | P66: =P65 -> 26829.025 | Q66: =Q65 -> 27132.159 | R66: =R65 -> 27181.9 | S66: =SUM(K66:R66) -> 261542.1 | U66: =SUM(F66:G66,H66) -> 54654.588 | V66: =SUM(I66,J66,L66) -> 58270.768 | W66: =SUM(M66:O66) -> 67473.661 | X66: =SUM(P66:R66) -> 81143.084 | Y66: =SUM(U66:X66) -> 261542.1
D67: % 25 (Act) x 24 (Act) | F67: =F63/F62-1 -> 0.19710188 | G67: =G63/G62-1 -> 0.49890171 | H67: =H63/H62-1 -> 0.15997116 | I67: =I63/I62-1 -> 0.56132975 | J67: =J63/J62-1 -> 0.44211239 | K67: =K63/K62-1 -> 0.35539979 | L67: =L63/L62-1 -> -0.17114517 | M67: =M63/M62-1 -> -0.55256431 | ... S67: =S63/S62-1 -> 0.087934327 | U67: =U63/U62-1 -> 0.26667384 | V67: =V63/V62-1 -> 0.20329102 | W67: =W63/W62-1 -> -0.25912388 | X67: =X63/X62-1 -> 0.27161384 | Y67: =Y63/Y62-1 -> 0.087934327
D68: % 26 (Act) x 25 (Act) | F68: =F66/F63-1 -> 0.1010577 | G68: =G66/G63-1 -> 0.24750173 | H68: =H66/H63-1 -> 0.14792715 | I68: =I66/I63-1 -> 0.17412078 | J68: =J66/J63-1 -> 0.16182785 | K68: =K66/K63-1 -> 0.16443149 | L68: =L66/L63-1 -> 0.12249529 | M68: =M66/M63-1 -> 1.6188452 | ... S68: =S66/S63-1 -> 0.38696104 | U68: =U66/U63-1 -> 0.16210776 | V68: =V66/V63-1 -> 0.15394433 | W68: =W66/W63-1 -> 0.67910652 | X68: =X66/X63-1 -> 0.59541443 | Y68: =Y66/Y63-1 -> 0.38696104
D69: % 26 (Act) x 26 (Bgt) | F69: =F66/F64-1 -> 0.18190726 | G69: =G66/G64-1 -> 0.20755215 | H69: =H66/H64-1 -> 0.061566422 | I69: =I66/I64-1 -> 0.20215361 | J69: =J66/J64-1 -> 0.27988884 | K69: =K66/K64-1 -> 0.188897 | L69: =L66/L64-1 -> -0.043470463 | M69: =M66/M64-1 -> -0.098629886 | ... S69: =S66/S64-1 -> 0.047685779 | U69: =U66/U64-1 -> 0.15153561 | V69: =V66/V64-1 -> 0.14222779 | W69: =W66/W64-1 -> -0.061918539 | X69: =X66/X64-1 -> 0.024103798 | Y69: =Y66/Y64-1 -> 0.047685779
D70: % 26 (Act) x 26 (Bgt) | F70: =F66/F65-1 -> 0 | G70: =G66/G65-1 -> 0 | H70: =H66/H65-1 -> 0 | I70: =I66/I65-1 -> 0 | J70: =J66/J65-1 -> 0.23883067 | K70: =K66/K65-1 -> 0.046230023 | L70: =L66/L65-1 -> 0 | M70: =M66/M65-1 -> 0 | ... S70: =S66/S65-1 -> 0.016455983 | U70: =U66/U65-1 -> 0 | V70: =V66/V65-1 -> 0.078359117 | W70: =W66/W65-1 -> 0 | X70: =X66/X65-1 -> 0 | Y70: =Y66/Y65-1 -> 0.016455983
D72: %Ebitda / Net Revenue
D73: Actual | E73: 2024 | F73: =IFERROR(F62/F$22,0) -> 0.2137182 | G73: =IFERROR(G62/G$22,0) -> 0.1450127 | H73: =IFERROR(H62/H$22,0) -> 0.16795593 | I73: =IFERROR(I62/I$22,0) -> 0.14058288 | J73: =IFERROR(J62/J$22,0) -> 0.17133315 | K73: =IFERROR(K62/K$22,0) -> 0.16743597 | L73: =IFERROR(L62/L$22,0) -> 0.2320442 | M73: =IFERROR(M62/M$22,0) -> 0.20356973 | ... S73: =IFERROR(S62/S$22,0) -> 0.18403489 | U73: =IFERROR(U62/U$22,0) -> 0.17548575 | V73: =IFERROR(V62/V$22,0) -> 0.18226478 | W73: =IFERROR(W62/W$22,0) -> 0.22153211 | X73: =IFERROR(X62/X$22,0) -> 0.15674267 | Y73: =IFERROR(Y62/Y$22,0) -> 0.18403489
D74: Actual | E74: 2025 | F74: =IFERROR(F63/F$23,0) -> 0.19490281 | G74: =IFERROR(G63/G$23,0) -> 0.16640577 | H74: =IFERROR(H63/H$23,0) -> 0.15401138 | I74: =IFERROR(I63/I$23,0) -> 0.17676286 | J74: =IFERROR(J63/J$23,0) -> 0.19860306 | K74: =IFERROR(K63/K$23,0) -> 0.17829597 | L74: =IFERROR(L63/L$23,0) -> 0.16371492 | M74: =IFERROR(M63/M$23,0) -> 0.08142562 | ... S74: =IFERROR(S63/S$23,0) -> 0.16260192 | U74: =IFERROR(U63/U$23,0) -> 0.17175505 | V74: =IFERROR(V63/V$23,0) -> 0.17984256 | W74: =IFERROR(W63/W$23,0) -> 0.13809913 | X74: =IFERROR(X63/X$23,0) -> 0.16190985 | Y74: =IFERROR(Y63/Y$23,0) -> 0.16260192
D75: Budget | E75: 2026 | F75: =IFERROR(F64/F$24,0) -> 0.15879838 | G75: =IFERROR(G64/G$24,0) -> 0.1489362 | H75: =IFERROR(H64/H$24,0) -> 0.14037781 | I75: =IFERROR(I64/I$24,0) -> 0.14445646 | J75: =IFERROR(J64/J$24,0) -> 0.15176657 | K75: =IFERROR(K64/K$24,0) -> 0.14879223 | L75: =IFERROR(L64/L$24,0) -> 0.15128446 | M75: =IFERROR(M64/M$24,0) -> 0.18005225 | ... S75: =IFERROR(S64/S$24,0) -> 0.17651164 | U75: =IFERROR(U64/U$24,0) -> 0.14924265 | V75: =IFERROR(V64/V$24,0) -> 0.14923473 | W75: =IFERROR(W64/W$24,0) -> 0.19111115 | X75: =IFERROR(X64/X$24,0) -> 0.20958034 | Y75: =IFERROR(Y64/Y$24,0) -> 0.17651164
D76: Forecast | E76: 2026 | F76: =IFERROR(F65/F$25,0) -> 0.18390585 | G76: =IFERROR(G65/G$25,0) -> 0.17943475 | H76: =IFERROR(H65/H$25,0) -> 0.15140222 | I76: =IFERROR(I65/I$25,0) -> 0.17297992 | J76: =IFERROR(J65/J$25,0) -> 0.15883528 | K76: =IFERROR(K65/K$25,0) -> 0.16918949 | L76: =IFERROR(L65/L$25,0) -> 0.14791233 | M76: =IFERROR(M65/M$25,0) -> 0.16582328 | ... S76: =IFERROR(S65/S$25,0) -> 0.18323863 | U76: =IFERROR(U65/U$25,0) -> 0.1714953 | V76: =IFERROR(V65/V$25,0) -> 0.15974518 | W76: =IFERROR(W65/W$25,0) -> 0.1818919 | X76: =IFERROR(X65/X$25,0) -> 0.21563019 | Y76: =IFERROR(Y65/Y$25,0) -> 0.18323863
D77: Actual | E77: 2026 | F77: =IFERROR(F66/F$26,0) -> 0.18390585 | G77: =IFERROR(G66/G$26,0) -> 0.17943475 | H77: =IFERROR(H66/H$26,0) -> 0.15140222 | I77: =IFERROR(I66/I$26,0) -> 0.17297992 | J77: =IFERROR(J66/J$26,0) -> 0.19311048 | K77: =IFERROR(K66/K$26,0) -> 0.17632217 | L77: =IFERROR(L66/L$26,0) -> 0.14791233 | M77: =IFERROR(M66/M$26,0) -> 0.16582328 | ... S77: =IFERROR(S66/S$26,0) -> 0.18597386 | U77: =IFERROR(U66/U$26,0) -> 0.1714953 | V77: =IFERROR(V66/V$26,0) -> 0.17119218 | W77: =IFERROR(W66/W$26,0) -> 0.1818919 | X77: =IFERROR(X66/X$26,0) -> 0.21563019 | Y77: =IFERROR(Y66/Y$26,0) -> 0.18597386
C79: Cash Flow
D80: Actual | E80: 2024 | F80: 3162.661 | G80: 6328.1766 | H80: -1535.2097 | I80: 8695.2872 | J80: 9824.7813 | K80: =SUM(F80:J80) -> 26475.696 | L80: 11506.328 | M80: 14980.554 | N80: 12312.84 | O80: 20217.853 | P80: 18128.644 | Q80: -935.17022 | R80: 5797.7556 | S80: =SUM(K80:R80) -> 108484.5 | U80: =SUM(F80:G80,H80) -> 7955.6279 | V80: =SUM(I80,J80,L80) -> 30026.397 | W80: =SUM(M80:O80) -> 47511.247 | X80: =SUM(P80:R80) -> 22991.229 | Y80: =SUM(U80:X80) -> 108484.5
D81: Actual | E81: 2025 | F81: 14366.121 | G81: 5805.9192 | H81: 7376.6237 | I81: 3460.6935 | J81: 16937.229 | K81: =SUM(F81:J81) -> 47946.586 | L81: 13442.739 | M81: 9559.5878 | N81: 19138.199 | O81: 18614.144 | P81: 19941.734 | Q81: 2644.9386 | R81: 1557.3802 | S81: =SUM(K81:R81) -> 132845.31 | U81: =SUM(F81:G81,H81) -> 27548.663 | V81: =SUM(I81,J81,L81) -> 33840.661 | W81: =SUM(M81:O81) -> 47311.931 | X81: =SUM(P81:R81) -> 24144.053 | Y81: =SUM(U81:X81) -> 132845.31
D82: Budget | E82: 2026 | F82: 3336.378 | G82: 5783.1198 | H82: 4946.1592 | I82: 7645.2314 | J82: 16156.894 | K82: =SUM(F82:J82) -> 37867.783 | L82: 18284.681 | M82: 16882.809 | N82: 24483.953 | O82: 25196.506 | P82: 25638.162 | Q82: 10308.448 | R82: 5188.9162 | S82: =SUM(K82:R82) -> 163851.26 | U82: =SUM(F82:G82,H82) -> 14065.657 | V82: =SUM(I82,J82,L82) -> 42086.807 | W82: =SUM(M82:O82) -> 66563.268 | X82: =SUM(P82:R82) -> 41135.526 | Y82: =SUM(U82:X82) -> 163851.26
D83: Actual | E83: 2026 | F83: 2313 | G83: 5640 | H83: -944.86355 | I83: 9737.1957 | J83: 26676.709 | K83: =SUM(F83:J83) -> 43422.041 | L83: =L82 -> 18284.681 | M83: =M82 -> 16882.809 | N83: =N82 -> 24483.953 | O83: =O82 -> 25196.506 | P83: =P82 -> 25638.162 | Q83: =Q82 -> 10308.448 | R83: =R82 -> 5188.9162 | S83: =SUM(K83:R83) -> 169405.52 | U83: =SUM(F83:G83,H83) -> 7008.1365 | V83: =SUM(I83,J83,L83) -> 54698.585 | W83: =SUM(M83:O83) -> 66563.268 | X83: =SUM(P83:R83) -> 41135.526 | Y83: =SUM(U83:X83) -> 169405.52
D84: % 25 (Act) x 24 (Act) | F84: =F81/F80-1 -> 3.5424156 | G84: =G81/G80-1 -> -0.082528895 | H84: =H81/H80-1 -> -5.8049615 | I84: =I81/I80-1 -> -0.60200354 | J84: =J81/J80-1 -> 0.72392935 | K84: =K81/K80-1 -> 0.81096599 | L84: =L81/L80-1 -> 0.16829091 | M84: =M81/M80-1 -> -0.36186686 | ... S84: =S81/S80-1 -> 0.22455565 | U84: =U81/U80-1 -> 2.4627894 | V84: =V81/V80-1 -> 0.12703037 | W84: =W81/W80-1 -> -0.004195144 | X84: =X81/X80-1 -> 0.050141899 | Y84: =Y81/Y80-1 -> 0.22455565
D85: % 26 (Act) x 25 (Act) | F85: =F83/F81-1 -> -0.8389962 | G85: =G83/G81-1 -> -0.028577589 | H85: =H83/H81-1 -> -1.1280889 | I85: =I83/I81-1 -> 1.8136545 | J85: =J83/J81-1 -> 0.57503386 | K85: =K83/K81-1 -> -0.094366358 | L85: =L83/L81-1 -> 0.36019012 | M85: =M83/M81-1 -> 0.76606034 | ... S85: =S83/S81-1 -> 0.27520887 | U85: =U83/U81-1 -> -0.74560884 | V85: =V83/V81-1 -> 0.61635687 | W85: =W83/W81-1 -> 0.40690238 | X85: =X83/X81-1 -> 0.70375398 | Y85: =Y83/Y81-1 -> 0.27520887
D86: % 26 (Act) x 26 (Bgt) | F86: =F83/F82-1 -> -0.30673324 | G86: =G83/G82-1 -> -0.024747852 | H86: =H83/H82-1 -> -1.1910297 | I86: =I83/I82-1 -> 0.27362996 | J86: =J83/J82-1 -> 0.65110375 | K86: =K83/K82-1 -> 0.14667503 | L86: =L83/L82-1 -> 0 | M86: =M83/M82-1 -> 0 | ... S86: =S83/S82-1 -> 0.033898173 | U86: =U83/U82-1 -> -0.50175549 | V86: =V83/V82-1 -> 0.2996611 | W86: =W83/W82-1 -> 0 | X86: =X83/X82-1 -> 0 | Y86: =Y83/Y82-1 -> 0.033898173
D88: %Cashflow / Ebitda af. Capex
D89: Actual | E89: 2024 | F89: =IFERROR(F80/F62,0) -> 0.21263933 | G89: =IFERROR(G80/G62,0) -> 0.62906482 | H89: =IFERROR(H80/H62,0) -> -0.12587638 | I89: =IFERROR(I80/I62,0) -> 0.82989859 | J89: =IFERROR(J80/J62,0) -> 0.74948867 | K89: =IFERROR(K80/K62,0) -> 0.43606257 | L89: =IFERROR(L80/L62,0) -> 0.62603817 | M89: =IFERROR(M80/M62,0) -> 0.90103229 | ... S89: =IFERROR(S80/S62,0) -> 0.62588282 | U89: =IFERROR(U80/U62,0) -> 0.21426885 | V89: =IFERROR(V80/V62,0) -> 0.71549732 | W89: =IFERROR(W80/W62,0) -> 0.87596348 | X89: =IFERROR(X80/X62,0) -> 0.57483002 | Y89: =IFERROR(Y80/Y62,0) -> 0.62588282
D90: Actual | E90: 2025 | F90: =IFERROR(F81/F63,0) -> 0.80686216 | G90: =IFERROR(G81/G63,0) -> 0.3850478 | H90: =IFERROR(H81/H63,0) -> 0.52141915 | I90: =IFERROR(I81/I63,0) -> 0.21154833 | J90: =IFERROR(J81/J63,0) -> 0.89595342 | K90: =IFERROR(K81/K63,0) -> 0.58262846 | L90: =IFERROR(L81/L63,0) -> 0.88241593 | M90: =IFERROR(M81/M63,0) -> 1.285053 | ... S90: =IFERROR(S81/S63,0) -> 0.70448033 | U90: =IFERROR(U81/U63,0) -> 0.5857608 | V90: =IFERROR(V81/V63,0) -> 0.67015144 | W90: =IFERROR(W81/W63,0) -> 1.1773746 | X90: =IFERROR(X81/X63,0) -> 0.47471415 | Y90: =IFERROR(Y81/Y63,0) -> 0.70448033
D91: Budget | E91: 2026 | F91: =IFERROR(F82/F64,0) -> 0.20114462 | G91: =IFERROR(G82/G64,0) -> 0.37125353 | H91: =IFERROR(H82/H64,0) -> 0.3233183 | I91: =IFERROR(I82/I64,0) -> 0.47850258 | J91: =IFERROR(J82/J64,0) -> 0.94152407 | K91: =IFERROR(K82/K64,0) -> 0.46982289 | L91: =IFERROR(L82/L64,0) -> 1.0227908 | M91: =IFERROR(M82/M64,0) -> 0.78112386 | ... S91: =IFERROR(S82/S64,0) -> 0.65635564 | U91: =IFERROR(U82/U64,0) -> 0.29635399 | V91: =IFERROR(V82/V64,0) -> 0.82498861 | W91: =IFERROR(W82/W64,0) -> 0.92542434 | X91: =IFERROR(X82/X64,0) -> 0.51916992 | Y91: =IFERROR(Y82/Y64,0) -> 0.65635564
D92: Actual | E92: 2026 | F92: =IFERROR(F83/F66,0) -> 0.11798462 | G92: =IFERROR(G83/G66,0) -> 0.2998345 | H92: =IFERROR(H83/H66,0) -> -0.058181393 | I92: =IFERROR(I83/I66,0) -> 0.50695287 | J92: =IFERROR(J83/J66,0) -> 1.2146007 | K92: =IFERROR(K83/K66,0) -> 0.45313781 | L92: =IFERROR(L83/L66,0) -> 1.0692726 | M92: =IFERROR(M83/M66,0) -> 0.86659613 | ... S92: =IFERROR(S83/S66,0) -> 0.64771796 | U92: =IFERROR(U83/U66,0) -> 0.12822595 | V92: =IFERROR(V83/V66,0) -> 0.93869683 | W92: =IFERROR(W83/W66,0) -> 0.98650743 | X92: =IFERROR(X83/X66,0) -> 0.50695049 | Y92: =IFERROR(Y83/Y66,0) -> 0.64771796
C94: Adjusted EBITDA - Orgânico
D95: Actual | E95: 2024 | F95: 18412.284 | G95: 13425.105 | H95: 17137.982 | I95: 16163.728 | J95: 17931.609 | K95: =SUM(F95:J95) -> 83070.708 | L95: 22177.245 | M95: 20786.914 | N95: 20800.318 | O95: 26093.038 | P95: 23348.863 | Q95: 18624.538 | R95: 10533.289 | S95: =SUM(K95:R95) -> 225434.91 | U95: =SUM(F95:G95,H95) -> 48975.371 | V95: =SUM(I95,J95,L95) -> 56272.582 | W95: =SUM(M95:O95) -> 67680.269 | X95: =SUM(P95:R95) -> 52506.69 | Y95: =SUM(U95:X95) -> 225434.91
D96: Actual | E96: 2025 | F96: 19580.56 | G96: 17479.308 | H96: 19159.014 | I96: 21578.866 | J96: 22972.809 | K96: =SUM(F96:J96) -> 100770.56 | L96: 19295.223 | M96: 11837.151 | N96: 19145.986 | O96: 23310.816 | P96: 33732.87 | Q96: 34781.758 | R96: =24592.3715281149-1576.205 -> 23016.167 | S96: =SUM(K96:R96) -> 265890.53 | U96: =SUM(F96:G96,H96) -> 56218.882 | V96: =SUM(I96,J96,L96) -> 63846.898 | W96: =SUM(M96:O96) -> 54293.954 | X96: =SUM(P96:R96) -> 91530.795 | Y96: =SUM(U96:X96) -> 265890.53
D97: Budget | E97: 2026 | F97: =F46 -> 16586.961 | G97: =G46 -> 15577.279 | H97: =H46 -> 15298.111 | I97: =I46 -> 15977.409 | J97: =J46 -> 17160.363 | K97: =SUM(F97:J97) -> 80600.123 | L97: =L46 -> 17877.244 | M97: =M46 -> 21613.485 | N97: =N46 -> 21353.103 | O97: =O46 -> 28960.706 | P97: =P46 -> 26936.868 | Q97: =Q46 -> 27232.027 | R97: =R46 -> 25064.366 | S97: =SUM(K97:R97) -> 249637.92 | U97: =SUM(F97:G97,H97) -> 47462.352 | V97: =SUM(I97,J97,L97) -> 51015.015 | W97: =SUM(M97:O97) -> 71927.294 | X97: =SUM(P97:R97) -> 79233.261 | Y97: =SUM(U97:X97) -> 249637.92
D98: Forecast | E98: 2026 | F98: =F47 -> 22496.568 | G98: =G47 -> 21677.649 | H98: =H47 -> 21418.495 | I98: =I47 -> 28184.804 | J98: =J47 -> 17728.989 | K98: =SUM(F98:J98) -> 111506.5 | L98: =L47 -> 17099.983 | M98: =M47 -> 19481.631 | N98: =N47 -> 20150.334 | O98: =O47 -> 27841.228 | P98: =P47 -> 26828.845 | Q98: =Q47 -> 27132.086 | R98: =R47 -> 27181.863 | S98: =SUM(K98:R98) -> 277222.48 | U98: =SUM(F98:G98,H98) -> 65592.712 | V98: =SUM(I98,J98,L98) -> 63013.776 | W98: =SUM(M98:O98) -> 67473.193 | X98: =SUM(P98:R98) -> 81142.795 | Y98: =SUM(U98:X98) -> 277222.48
D99: Actual | E99: 2026 | F99: =F48 -> 22496.568 | G99: =G48 -> 21677.649 | H99: =H48 -> 21418.495 | I99: =I48 -> 28184.804 | J99: =J48 -> 34075.192 | K99: =SUM(F99:J99) -> 127852.71 | L99: =L98 -> 17099.983 | M99: =M98 -> 19481.631 | N99: =N98 -> 20150.334 | O99: =O98 -> 27841.228 | P99: =P98 -> 26828.845 | Q99: =Q98 -> 27132.086 | R99: =R98 -> 27181.863 | S99: =SUM(K99:R99) -> 293568.68 | U99: =SUM(F99:G99,H99) -> 65592.712 | V99: =SUM(I99,J99,L99) -> 79359.979 | W99: =SUM(M99:O99) -> 67473.193 | X99: =SUM(P99:R99) -> 81142.795 | Y99: =SUM(U99:X99) -> 293568.68
D100: % 25 (Act) x 24 (Act) | F100: =F96/F95-1 -> 0.063450901 | G100: =G96/G95-1 -> 0.30198669 | H100: =H96/H95-1 -> 0.1179271 | I100: =I96/I95-1 -> 0.3350179 | J100: =J96/J95-1 -> 0.28113481 | K100: =K96/K95-1 -> 0.21306968 | L100: =L96/L95-1 -> -0.12995402 | M100: =M96/M95-1 -> -0.43054793 | ... S100: =S96/S95-1 -> 0.17945586 | U100: =U96/U95-1 -> 0.14790111 | V100: =V96/V95-1 -> 0.13460046 | W100: =W96/W95-1 -> -0.19778756 | X100: =X96/X95-1 -> 0.74322157 | Y100: =Y96/Y95-1 -> 0.17945586
D101: % 26 (Act) x 25 (Act) | F101: =F99/F96-1 -> 0.14892363 | G101: =G99/G96-1 -> 0.2401892 | H101: =H99/H96-1 -> 0.11793301 | I101: =I99/I96-1 -> 0.30612996 | J101: =J99/J96-1 -> 0.48328366 | K101: =K99/K96-1 -> 0.26875062 | L101: =L99/L96-1 -> -0.11377113 | M101: =M99/M96-1 -> 0.64580401 | ... S101: =S99/S96-1 -> 0.10409603 | U101: =U99/U96-1 -> 0.1667381 | V101: =V99/V96-1 -> 0.24297314 | W101: =W99/W96-1 -> 0.24273861 | X101: =X99/X96-1 -> -0.11349186 | Y101: =Y99/Y96-1 -> 0.10409603
D102: % 26 (Act) x 26 (Bgt) | F102: =F99/F97-1 -> 0.35628025 | G102: =G99/G97-1 -> 0.39161974 | H102: =H99/H97-1 -> 0.40007445 | I102: =I99/I97-1 -> 0.76404096 | J102: =J99/J97-1 -> 0.98569184 | K102: =K99/K97-1 -> 0.58625946 | L102: =L99/L97-1 -> -0.043477658 | M102: =M99/M97-1 -> -0.098635381 | ... S102: =S99/S97-1 -> 0.17597789 | U102: =U99/U97-1 -> 0.38199456 | V102: =V99/V97-1 -> 0.55562001 | W102: =W99/W97-1 -> -0.06192505 | X102: =X99/X97-1 -> 0.024100146 | Y102: =Y99/Y97-1 -> 0.17597789
D103: % 26 (Act) x 26 (Rfc) | F103: =F99/F98-1 -> 0 | G103: =G99/G98-1 -> 0 | H103: =H99/H98-1 -> 0 | I103: =I99/I98-1 -> 0 | J103: =J99/J98-1 -> 0.9220042 | K103: =K99/K98-1 -> 0.14659416 | L103: =L99/L98-1 -> 0 | M103: =M99/M98-1 -> 0 | ... S103: =S99/S98-1 -> 0.058964204 | U103: =U99/U98-1 -> 0 | V103: =V99/V98-1 -> 0.25940681 | W103: =W99/W98-1 -> 0 | X103: =X99/X98-1 -> 0 | Y103: =Y99/Y98-1 -> 0.058964204
D105: %Ebitda / NetSales
D106: Actual | E106: 2024 | F106: =IFERROR(F95/F33,0) -> 0.24582718 | G106: =IFERROR(G95/G33,0) -> 0.18016633 | H106: =IFERROR(H95/H33,0) -> 0.21747452 | I106: =IFERROR(I95/I33,0) -> 0.20156505 | J106: =IFERROR(J95/J33,0) -> 0.22082017 | K106: =IFERROR(K95/K33,0) -> 0.21321251 | L106: =IFERROR(L95/L33,0) -> 0.2649059 | M106: =IFERROR(M95/M33,0) -> 0.24110666 | ... S106: =IFERROR(S95/S33,0) -> 0.22499128 | U106: =IFERROR(U95/U33,0) -> 0.21459821 | V106: =IFERROR(V95/V33,0) -> 0.22957798 | W106: =IFERROR(W95/W33,0) -> 0.26010928 | X106: =IFERROR(X95/X33,0) -> 0.19559911 | Y106: =IFERROR(Y95/Y33,0) -> 0.22499128
D107: Actual | E107: 2025 | F107: =IFERROR(F96/F34,0) -> 0.21110109 | G107: =IFERROR(G96/G34,0) -> 0.19017615 | H107: =IFERROR(H96/H34,0) -> 0.20522608 | I107: =IFERROR(I96/I34,0) -> 0.22881448 | J107: =IFERROR(J96/J34,0) -> 0.23767035 | K107: =IFERROR(K96/K34,0) -> 0.21486866 | L107: =IFERROR(L96/L34,0) -> 0.20302552 | M107: =IFERROR(M96/M34,0) -> 0.12791424 | ... S107: =IFERROR(S96/S34,0) -> 0.22666368 | U107: =IFERROR(U96/U34,0) -> 0.20221076 | V107: =IFERROR(V96/V34,0) -> 0.22323781 | W107: =IFERROR(W96/W34,0) -> 0.18467378 | X107: =IFERROR(X96/X34,0) -> 0.29053938 | Y107: =IFERROR(Y96/Y34,0) -> 0.22666368
D108: Budget | E108: 2026 | F108: =IFERROR(F97/F35,0) -> 0.15879838 | G108: =IFERROR(G97/G35,0) -> 0.1489362 | H108: =IFERROR(H97/H35,0) -> 0.14037781 | I108: =IFERROR(I97/I35,0) -> 0.14445646 | J108: =IFERROR(J97/J35,0) -> 0.15176657 | K108: =IFERROR(K97/K35,0) -> 0.14879223 | L108: =IFERROR(L97/L35,0) -> 0.15128446 | M108: =IFERROR(M97/M35,0) -> 0.18005225 | ... S108: =IFERROR(S97/S35,0) -> 0.17651164 | U108: =IFERROR(U97/U35,0) -> 0.14924265 | V108: =IFERROR(V97/V35,0) -> 0.14923473 | W108: =IFERROR(W97/W35,0) -> 0.19111115 | X108: =IFERROR(X97/X35,0) -> 0.20958034 | Y108: =IFERROR(Y97/Y35,0) -> 0.17651164
D109: Forecast | E109: 2026 | F109: =IFERROR(F98/F36,0) -> 0.21103845 | G109: =IFERROR(G98/G36,0) -> 0.20678605 | H109: =IFERROR(H98/H36,0) -> 0.19968075 | I109: =IFERROR(I98/I36,0) -> 0.25383085 | J109: =IFERROR(J98/J36,0) -> 0.15883426 | K109: =IFERROR(K98/K36,0) -> 0.205978 | L109: =IFERROR(L98/L36,0) -> 0.14791122 | M109: =IFERROR(M98/M36,0) -> 0.16582227 | ... S109: =IFERROR(S98/S36,0) -> 0.19742059 | U109: =IFERROR(U98/U36,0) -> 0.20581698 | V109: =IFERROR(V98/V36,0) -> 0.18628417 | W109: =IFERROR(W98/W36,0) -> 0.18189064 | X109: =IFERROR(X98/X36,0) -> 0.21562942 | Y109: =IFERROR(Y98/Y36,0) -> 0.19742059
D110: Actual | E110: 2026 | F110: =IFERROR(F99/F37,0) -> 0.21103845 | G110: =IFERROR(G99/G37,0) -> 0.20678605 | H110: =IFERROR(H99/H37,0) -> 0.19968075 | I110: =IFERROR(I99/I37,0) -> 0.25383085 | J110: =IFERROR(J99/J37,0) -> 0.29960251 | K110: =IFERROR(K99/K37,0) -> 0.23525395 | L110: =IFERROR(L99/L37,0) -> 0.14791122 | M110: =IFERROR(M99/M37,0) -> 0.16582227 | ... S110: =IFERROR(S99/S37,0) -> 0.20874689 | U110: =IFERROR(U99/U37,0) -> 0.20581698 | V110: =IFERROR(V99/V37,0) -> 0.23314963 | W110: =IFERROR(W99/W37,0) -> 0.18189064 | X110: =IFERROR(X99/X37,0) -> 0.21562942 | Y110: =IFERROR(Y99/Y37,0) -> 0.20874689
C112: Adjusted EBITDA after Capex - Organico
D113: Actual | E113: 2024 | F113: 16305.77 | G113: 10653.977 | H113: 14247.636 | I113: 11740.269 | J113: 14522.586 | K113: =SUM(F113:J113) -> 67470.239 | L113: 19284.948 | M113: 17640.657 | N113: 17792.408 | O113: 22838.843 | P113: 20433.62 | Q113: 15462.216 | R113: 7181.9105 | S113: =SUM(K113:R113) -> 188104.84 | U113: =SUM(F113:G113,H113) -> 41207.383 | V113: =SUM(I113,J113,L113) -> 45547.804 | W113: =SUM(M113:O113) -> 58271.908 | X113: =SUM(P113:R113) -> 43077.747 | Y113: =SUM(U113:X113) -> 188104.84
D114: Actual | E114: 2025 | F114: 18020.504 | G114: 15323.215 | H114: 14396.059 | I114: 16980.535 | J114: 19158 | K114: =SUM(F114:J114) -> 83878.312 | L114: 15830.854 | M114: 7836.4149 | N114: 14611.776 | O114: 18396.099 | P114: 18540.955 | Q114: 18620.3 | R114: =15425.6850281149-1576.205 -> 13849.48 | S114: =SUM(K114:R114) -> 191564.19 | U114: =SUM(F114:G114,H114) -> 47739.777 | V114: =SUM(I114,J114,L114) -> 51969.389 | W114: =SUM(M114:O114) -> 40844.289 | X114: =SUM(P114:R114) -> 51010.735 | Y114: =SUM(U114:X114) -> 191564.19
D115: Budget | E115: 2026 | F115: =F64 -> 16586.961 | G115: =G64 -> 15577.279 | H115: =H64 -> 15298.111 | I115: =I64 -> 15977.409 | J115: =J64 -> 17160.363 | K115: =SUM(F115:J115) -> 80600.123 | L115: =L64 -> 17877.244 | M115: =M64 -> 21613.485 | N115: =N64 -> 21353.103 | O115: =O64 -> 28960.706 | P115: =P64 -> 26936.868 | Q115: =Q64 -> 27232.027 | R115: =R64 -> 25064.366 | S115: =SUM(K115:R115) -> 249637.92 | U115: =SUM(F115:G115,H115) -> 47462.352 | V115: =SUM(I115,J115,L115) -> 51015.015 | W115: =SUM(M115:O115) -> 71927.294 | X115: =SUM(P115:R115) -> 79233.261 | Y115: =SUM(U115:X115) -> 249637.92
D116: Forecast | E116: 2026 | F116: =F65 -> 19604.25 | G116: =G65 -> 18810.377 | H116: =H65 -> 16239.961 | I116: =I65 -> 19207.3 | J116: =J65 -> 17729.103 | K116: =SUM(F116:J116) -> 91590.991 | L116: =L65 -> 17100.112 | M116: =M65 -> 19481.75 | N116: =N65 -> 20150.506 | O116: =O65 -> 27841.405 | P116: =P65 -> 26829.025 | Q116: =Q65 -> 27132.159 | R116: =R65 -> 27181.9 | S116: =SUM(K116:R116) -> 257307.85 | U116: =SUM(F116:G116,H116) -> 54654.588 | V116: =SUM(I116,J116,L116) -> 54036.515 | W116: =SUM(M116:O116) -> 67473.661 | X116: =SUM(P116:R116) -> 81143.084 | Y116: =SUM(U116:X116) -> 257307.85
D117: Actual | E117: 2026 | F117: =F66 -> 19604.25 | G117: =G66 -> 18810.377 | H117: =H66 -> 16239.961 | I117: =I66 -> 19207.3 | J117: =J66 -> 21963.356 | K117: =SUM(F117:J117) -> 95825.244 | L117: =L116 -> 17100.112 | M117: =M116 -> 19481.75 | N117: =N116 -> 20150.506 | O117: =O116 -> 27841.405 | P117: =P116 -> 26829.025 | Q117: =Q116 -> 27132.159 | R117: =R116 -> 27181.9 | S117: =SUM(K117:R117) -> 261542.1 | U117: =SUM(F117:G117,H117) -> 54654.588 | V117: =SUM(I117,J117,L117) -> 58270.768 | W117: =SUM(M117:O117) -> 67473.661 | X117: =SUM(P117:R117) -> 81143.084 | Y117: =SUM(U117:X117) -> 261542.1
D118: % 25 (Act) x 24 (Act) | F118: =F114/F113-1 -> 0.10516115 | G118: =G114/G113-1 -> 0.43826241 | H118: =H114/H113-1 -> 0.010417319 | I118: =I114/I113-1 -> 0.44634968 | J118: =J114/J113-1 -> 0.31918652 | K118: =K114/K113-1 -> 0.24318978 | L118: =L114/L113-1 -> -0.17910828 | M118: =M114/M113-1 -> -0.55577533 | ... S118: =S114/S113-1 -> 0.01839053 | U118: =U114/U113-1 -> 0.15852483 | V118: =V114/V113-1 -> 0.14098562 | W118: =W114/W113-1 -> -0.29907411 | X118: =X114/X113-1 -> 0.18415514 | Y118: =Y114/Y113-1 -> 0.01839053
D119: % 26 (Act) x 25 (Act) | F119: =F117/F114-1 -> 0.0878858 | G119: =G117/G114-1 -> 0.22757382 | H119: =H117/H114-1 -> 0.12808384 | I119: =I117/I114-1 -> 0.13113632 | J119: =J117/J114-1 -> 0.14643265 | K119: =K117/K114-1 -> 0.14243173 | L119: =L117/L114-1 -> 0.080176209 | M119: =M117/M114-1 -> 1.4860539 | ... S119: =S117/S114-1 -> 0.36529746 | U119: =U117/U114-1 -> 0.14484381 | V119: =V117/V114-1 -> 0.12125175 | W119: =W117/W114-1 -> 0.65197295 | X119: =X117/X114-1 -> 0.59070603 | Y119: =Y117/Y114-1 -> 0.36529746
...

Sheet P&L Contábil
C2: 1000000 | E2: Actual | F2: Actual | G2: Actual | I2: Actual | J2: Actual | T2: Actual | U2: Actual | V2: Actual | W2: Actual | X2: Actual | Z2: Actual | AA2: Actual | AI2: Actual | AJ2: Actual | AK2: Actual | AM2: Actual | AN2: Actual | AX2: Actual | AY2: Actual | AZ2: Actual | BA2: Actual | BB2: Actual | BD2: Actual | BE2: Actual
C3: 46143 | E3: MTD | K3: MTD | AH3: =C3 -> 46143 | AI3: YTD | AO3: YTD
C5: [ BRL M ] | E5: Base | F5: Ajuste Entre Empresas/Corp | G5: Reclass | H5: Actual Contábil | I5: Ajuste Não Recorrente | J5: Baixa Receita (Outros Anos) | K5: Actual | L5: % NR | N5: Budget | O5: % NR | P5: ∆ | Q5: ∆% | T5: HistoricoOriginal | U5: Ajuste Entre Empresas/Corp | V5: Reclass | W5: Ajuste Cloud | X5: Eliminacao Intercompany | Y5: Last Year Contábil | Z5: Ajuste Não Recorrente | AA5: Baixa Receita (Outros Anos) | AB5: Last Year | AC5: % NR | AD5: ∆ | AE5: ∆% | AI5: Base | AJ5: Ajuste Entre Empresas/Corp | AK5: Reclass | AL5: Actual Contábil | AM5: Ajuste Não Recorrente | AN5: Baixa Receita (Outros Anos) | AO5: Actual | AP5: % NR | AR5: Budget | AS5: % NR | AT5: ∆ | AU5: ∆% | AX5: HistoricoOriginal | AY5: Ajuste Entre Empresas/Corp | AZ5: Reclass | BA5: Ajuste Cloud | BB5: Eliminacao Intercompany | BC5: Last Year Contábil | BD5: Ajuste Não Recorrente | BE5: Baixa Receita (Outros Anos) | BF5: Last Year | BG5: % NR | BH5: ∆ | BI5: ∆%
B7: Gross Revenue | C7: Gross Revenue | E7: 124.22709 | F7: 0 | G7: 0 | H7: =SUM(E7:G7) -> 124.22709 | I7: 0 | J7: 2.3283064e-16 | K7: =SUM(H7:J7) -> 124.22709 | T7: 105.26204 | U7: 0 | V7: 0 | W7: 0 | X7: -1.2994338 | Y7: =SUM(T7:X7) -> 103.96261 | Z7: 0 | AA7: 0 | AB7: =SUM(Y7:AA7) -> 103.96261 | AH7: Gross Revenue | AI7: 590.92391 | AJ7: 0 | AK7: 0 | AL7: =SUM(AI7:AK7) -> 590.92391 | AM7: 0 | AN7: 3.4924597e-16 | AO7: =SUM(AL7:AN7) -> 590.92391 | AX7: 508.29344 | AY7: 0 | AZ7: 0 | BA7: 0 | BB7: -5.0745383 | BC7: =SUM(AX7:BB7) -> 503.2189 | BD7: 0 | BE7: 0 | BF7: =SUM(BC7:BE7) -> 503.2189
B8: (-) Deductions | C8: (-) Deductions | E8: -10.49242 | F8: 0 | G8: 0 | H8: =SUM(E8:G8) -> -10.49242 | I8: 0 | J8: 0 | K8: =SUM(H8:J8) -> -10.49242 | T8: -8.7770624 | U8: 0 | V8: 0 | W8: 0 | X8: 0 | Y8: =SUM(T8:X8) -> -8.7770624 | Z8: 0 | AA8: 0 | AB8: =SUM(Y8:AA8) -> -8.7770624 | AH8: (-) Deductions | AI8: -47.457135 | AJ8: 0 | AK8: 0 | AL8: =SUM(AI8:AK8) -> -47.457135 | AM8: 0 | AN8: 0 | AO8: =SUM(AL8:AN8) -> -47.457135 | AX8: -41.66283 | AY8: 0 | AZ8: 0 | BA8: 0 | BB8: 0 | BC8: =SUM(AX8:BB8) -> -41.66283 | BD8: 0 | BE8: 0 | BF8: =SUM(BC8:BE8) -> -41.66283
B9: Net Revenue | C9: Net Revenue | E9: =SUM(E7:E8) -> 113.73467 | F9: =SUM(F7:F8) -> 0 | G9: =SUM(G7:G8) -> 0 | H9: =SUM(H7:H8) -> 113.73467 | I9: =SUM(I7:I8) -> 0 | J9: =SUM(J7:J8) -> 2.3283064e-16 | K9: =SUM(K7:K8) -> 113.73467 | L9: =IFERROR(K9/K$9,0) -> 1 | N9: 113.07077 | O9: =IFERROR(N9/N$9,0) -> 1 | P9: =K9-N9 -> 0.66389816 | Q9: =IFERROR(K9/N9-1,"") -> 0.0058715277 | R9: =IF(Q9>0.05,1,IF(Q9<-0.05,-1,0)) -> 0 | T9: =SUM(T7:T8) -> 96.484978 | U9: =SUM(U7:U8) -> 0 | V9: =SUM(V7:V8) -> 0 | W9: =SUM(W7:W8) -> 0 | X9: =SUM(X7:X8) -> -1.2994338 | Y9: =SUM(T9:X9) -> 95.185544 | Z9: =SUM(Z7:Z8) -> 0 | AA9: =SUM(AA7:AA8) -> 0 | AB9: =SUM(AB7:AB8) -> 95.185544 | AC9: =IFERROR(AB9/AB$9,0) -> 1 | AD9: =$K9-AB9 -> 18.549124 | AE9: =IFERROR(K9/AB9-1,"") -> 0.19487333 | AF9: =IF(AE9>0.05,1,IF(AE9<-0.05,-1,0)) -> 1 | AH9: Net Revenue | AI9: =SUM(AI7:AI8) -> 543.46678 | AJ9: =SUM(AJ7:AJ8) -> 0 | AK9: =SUM(AK7:AK8) -> 0 | AL9: =SUM(AL7:AL8) -> 543.46678 | AM9: =SUM(AM7:AM8) -> 0 | AN9: =SUM(AN7:AN8) -> 3.4924597e-16 | AO9: =SUM(AO7:AO8) -> 543.46678 | AP9: =IFERROR(AO9/AO$9,0) -> 1 | AR9: 541.69577 | AS9: =IFERROR(AR9/AR$9,0) -> 1 | AT9: =AO9-AR9 -> 1.7710076 | AU9: =IFERROR(AO9/AR9-1,"") -> 0.0032693768 | AV9: =IF(AU9>0.05,1,IF(AU9<-0.05,-1,0)) -> 0 | AX9: =SUM(AX7:AX8) -> 466.63061 | AY9: =SUM(AY7:AY8) -> 0 | AZ9: =SUM(AZ7:AZ8) -> 0 | BA9: =SUM(BA7:BA8) -> 0 | BB9: =SUM(BB7:BB8) -> -5.0745383 | BC9: =SUM(AX9:BB9) -> 461.55607 | BD9: =SUM(BD7:BD8) -> 0 | BE9: =SUM(BE7:BE8) -> 0 | BF9: =SUM(BF7:BF8) -> 461.55607 | BG9: =IFERROR(BF9/BF$9,0) -> 1 | BH9: =$AO9-BF9 -> 81.91071 | BI9: =IFERROR(AO9/BF9-1,"") -> 0.17746644 | BJ9: =IF(BI9>0.05,1,IF(BI9<-0.05,-1,0)) -> 1
B10: (-) CoGS | C10: (-) COGS | E10: -38.090191 | F10: 0 | G10: 1.218627 | H10: =SUM(E10:G10) -> -36.871564 | I10: 0 | J10: 0 | K10: =SUM(H10:J10) -> -36.871564 | L10: =IFERROR(K10/K$9,0) -> -0.32418931 | N10: -38.26525 | O10: =IFERROR(N10/N$9,0) -> -0.33841858 | P10: =K10-N10 -> 1.3936862 | Q10: =IFERROR(K10/N10-1,"") -> -0.036421719 | T10: -33.679461 | U10: 0 | V10: 1.8643879 | W10: 0 | X10: 1.2994338 | Y10: =SUM(T10:X10) -> -30.515639 | Z10: 0 | AA10: 0 | AB10: =SUM(Y10:AA10) -> -30.515639 | AC10: =IFERROR(AB10/AB$9,0) -> -0.32059111 | AD10: =$K10-AB10 -> -6.3559243 | AE10: =IFERROR(K10/AB10-1,"") -> 0.20828416 | AH10: (-) COGS | AI10: -185.92999 | AJ10: 0 | AK10: 4.1597062 | AL10: =SUM(AI10:AK10) -> -181.77028 | AM10: 0 | AN10: 0 | AO10: =SUM(AL10:AN10) -> -181.77028 | AP10: =IFERROR(AO10/AO$9,0) -> -0.33446438 | AR10: -182.95622 | AS10: =IFERROR(AR10/AR$9,0) -> -0.33774718 | AT10: =AO10-AR10 -> 1.1859369 | AU10: =IFERROR(AO10/AR10-1,"") -> -0.0064820802 | AX10: -170.5028 | AY10: 0 | AZ10: 9.6893798 | BA10: -0.26966966 | BB10: 5.0745383 | BC10: =SUM(AX10:BB10) -> -156.00855 | BD10: 0 | BE10: 0 | BF10: =SUM(BC10:BE10) -> -156.00855 | BG10: =IFERROR(BF10/BF$9,0) -> -0.33800564 | BH10: =$AO10-BF10 -> -25.761729 | BI10: =IFERROR(AO10/BF10-1,"") -> 0.16513024
C11: = Gross Margin | E11: =SUM(E9:E10) -> 75.644477 | F11: =SUM(F9:F10) -> 0 | G11: =SUM(G9:G10) -> 1.218627 | H11: =SUM(H9:H10) -> 76.863104 | I11: =SUM(I9:I10) -> 0 | J11: =SUM(J9:J10) -> 2.3283064e-16 | K11: =SUM(K9:K10) -> 76.863104 | L11: =IFERROR(K11/K$9,0) -> 0.67581069 | N11: =N9+N10 -> 74.80552 | O11: =IFERROR(N11/N$9,0) -> 0.66158142 | P11: =K11-N11 -> 2.0575843 | Q11: =IFERROR(K11/N11-1,"") -> 0.027505782 | R11: =IF(Q11>0.05,1,IF(Q11<-0.05,-1,0)) -> 0 | T11: =SUM(T9:T10) -> 62.805517 | U11: =SUM(U9:U10) -> 0 | V11: =SUM(V9:V10) -> 1.8643879 | W11: =SUM(W9:W10) -> 0 | X11: =SUM(X9:X10) -> 0 | Y11: =SUM(Y9:Y10) -> 64.669905 | Z11: =SUM(Z9:Z10) -> 0 | AA11: =SUM(AA9:AA10) -> 0 | AB11: =SUM(AB9:AB10) -> 64.669905 | AC11: =IFERROR(AB11/AB$9,0) -> 0.67940889 | AD11: =$K11-AB11 -> 12.1932 | AE11: =IFERROR(K11/AB11-1,"") -> 0.1885452 | AF11: =IF(AE11>0.05,1,IF(AE11<-0.05,-1,0)) -> 1 | AH11: = Gross Margin | AI11: =SUM(AI9:AI10) -> 357.53679 | AJ11: =SUM(AJ9:AJ10) -> 0 | AK11: =SUM(AK9:AK10) -> 4.1597062 | AL11: =SUM(AL9:AL10) -> 361.6965 | AM11: =SUM(AM9:AM10) -> 0 | AN11: =SUM(AN9:AN10) -> 3.4924597e-16 | AO11: =SUM(AO9:AO10) -> 361.6965 | AP11: =IFERROR(AO11/AO$9,0) -> 0.66553562 | AR11: =AR9+AR10 -> 358.73955 | AS11: =IFERROR(AR11/AR$9,0) -> 0.66225282 | AT11: =AO11-AR11 -> 2.9569445 | AU11: =IFERROR(AO11/AR11-1,"") -> 0.008242594 | AV11: =IF(AU11>0.05,1,IF(AU11<-0.05,-1,0)) -> 0 | AX11: =SUM(AX9:AX10) -> 296.12781 | AY11: =SUM(AY9:AY10) -> 0 | AZ11: =SUM(AZ9:AZ10) -> 9.6893798 | BA11: =SUM(BA9:BA10) -> -0.26966966 | BB11: =SUM(BB9:BB10) -> 0 | BC11: =SUM(BC9:BC10) -> 305.54752 | BD11: =SUM(BD9:BD10) -> 0 | BE11: =SUM(BE9:BE10) -> 0 | BF11: =SUM(BF9:BF10) -> 305.54752 | BG11: =IFERROR(BF11/BF$9,0) -> 0.66199436 | BH11: =$AO11-BF11 -> 56.148981 | BI11: =IFERROR(AO11/BF11-1,"") -> 0.18376514 | BJ11: =IF(BI11>0.05,1,IF(BI11<-0.05,-1,0)) -> 1
C13: (-) Expenses | E13: =SUM(E14:E18) -> -41.175391 | F13: =SUM(F14:F18) -> -0.4807693 | G13: =SUM(G14:G18) -> -1.218627 | H13: =SUM(H14:H18) -> -42.874788 | I13: =SUM(I14:I18) -> 0.086875 | J13: =SUM(J14:J18) -> 0 | K13: =SUM(K14:K18) -> -42.787913 | L13: =IFERROR(K13/K$9,0) -> -0.37620818 | N13: =SUM(N14:N18) -> -48.034142 | O13: =IFERROR(N13/N$9,0) -> -0.42481485 | P13: =K13-N13 -> 5.2462295 | Q13: =IFERROR(K13/N13-1,"") -> -0.10921876 | T13: =SUM(T14:T18) -> -39.982952 | U13: =SUM(U14:U18) -> -0.12618796 | V13: =SUM(V14:V18) -> -1.8643879 | W13: =SUM(W14:W18) -> 0 | X13: =SUM(X14:X18) -> 0 | Y13: =SUM(Y14:Y18) -> -41.973528 | Z13: =SUM(Z14:Z18) -> 0.02257201 | AA13: =SUM(AA14:AA18) -> 0 | AB13: =SUM(AB14:AB18) -> -41.950956 | AC13: =IFERROR(AB13/AB$9,0) -> -0.44072822 | AD13: =$K13-AB13 -> -0.83695696 | AE13: =IFERROR(K13/AB13-1,"") -> 0.019950844 | AH13: (-) Expenses | AI13: =SUM(AI14:AI18) -> -230.83726 | AJ13: =SUM(AJ14:AJ18) -> 0.5436477 | AK13: =SUM(AK14:AK18) -> -4.1597062 | AL13: =SUM(AL14:AL18) -> -234.45332 | AM13: =SUM(AM14:AM18) -> 0.621875 | AN13: =SUM(AN14:AN18) -> 0 | AO13: =SUM(AO14:AO18) -> -233.83144 | AP13: =IFERROR(AO13/AO$9,0) -> -0.43025895 | AR13: =SUM(AR14:AR18) -> -232.09529 | AS13: =IFERROR(AR13/AR$9,0) -> -0.42846059 | AT13: =AO13-AR13 -> -1.7361551 | AU13: =IFERROR(AO13/AR13-1,"") -> 0.0074803546 | AX13: =SUM(AX14:AX18) -> -190.50089 | AY13: =SUM(AY14:AY18) -> -5.8884285 | AZ13: =SUM(AZ14:AZ18) -> -9.6893798 | BA13: =SUM(BA14:BA18) -> 0.26966966 | BB13: =SUM(BB14:BB18) -> 0 | BC13: =SUM(BC14:BC18) -> -205.80903 | BD13: =SUM(BD14:BD18) -> -0.55265431 | BE13: =SUM(BE14:BE18) -> 0 | BF13: =SUM(BF14:BF18) -> -206.36168 | BG13: =IFERROR(BF13/BF$9,0) -> -0.44709992 | BH13: =$AO13-BF13 -> -27.469761 | BI13: =IFERROR(AO13/BF13-1,"") -> 0.13311464
B14: (-) General & Administrative | C14: (-) General & Administrative | E14: -14.739142 | F14: -0.4652693 | G14: 2.2207367 | H14: =SUM(E14:G14) -> -12.983674 | I14: 0.086875 | J14: 0 | K14: =SUM(H14:J14) -> -12.896799 | L14: =IFERROR(K14/K$9,0) -> -0.11339374 | N14: -13.844132 | O14: =IFERROR(N14/N$9,0) -> -0.12243776 | P14: =K14-N14 -> 0.94733285 | Q14: =IFERROR(K14/N14-1,"") -> -0.068428475 | T14: -13.508229 | U14: -0.12618796 | V14: 1.063755 | W14: 0 | X14: 0 | Y14: =SUM(T14:X14) -> -12.570662 | Z14: 0.054844 | AA14: 0 | AB14: =SUM(Y14:AA14) -> -12.515818 | AC14: =IFERROR(AB14/AB$9,0) -> -0.13148864 | AD14: =$K14-AB14 -> -0.38098131 | AE14: =IFERROR(K14/AB14-1,"") -> 0.030439985 | AH14: (-) General & Administrative | AI14: -78.343974 | AJ14: 1.0550477 | AK14: 8.5753587 | AL14: =SUM(AI14:AK14) -> -68.713568 | AM14: 0.621875 | AN14: 0 | AO14: =SUM(AL14:AN14) -> -68.091693 | AP14: =IFERROR(AO14/AO$9,0) -> -0.12529136 | AR14: -67.681669 | AS14: =IFERROR(AR14/AR$9,0) -> -0.12494406 | AT14: =AO14-AR14 -> -0.41002424 | AU14: =IFERROR(AO14/AR14-1,"") -> 0.0060581284 | AX14: -64.069855 | AY14: -5.205088 | AZ14: 5.4171676 | BA14: 0 | BB14: 0 | BC14: =SUM(AX14:BB14) -> -63.857775 | BD14: 0.69235842 | BE14: 0 | BF14: =SUM(BC14:BE14) -> -63.165417 | BG14: =IFERROR(BF14/BF$9,0) -> -0.13685318 | BH14: =$AO14-BF14 -> -4.9262762 | BI14: =IFERROR(AO14/BF14-1,"") -> 0.077990084
B15: (-) Sales & Marketing | C15: (-) Sales & Marketing | E15: -13.184666 | F15: 0 | G15: -1.9152109 | H15: =SUM(E15:G15) -> -15.099876 | I15: 0 | J15: 0 | K15: =SUM(H15:J15) -> -15.099876 | L15: =IFERROR(K15/K$9,0) -> -0.13276406 | N15: -16.048389 | O15: =IFERROR(N15/N$9,0) -> -0.14193225 | P15: =K15-N15 -> 0.94851263 | Q15: =IFERROR(K15/N15-1,"") -> -0.059103292 | T15: -11.484349 | U15: 0 | V15: -2.5025589 | W15: 0 | X15: 0 | Y15: =SUM(T15:X15) -> -13.986908 | Z15: 0 | AA15: 0 | AB15: =SUM(Y15:AA15) -> -13.986908 | AC15: =IFERROR(AB15/AB$9,0) -> -0.14694362 | AD15: =$K15-AB15 -> -1.1129682 | AE15: =IFERROR(K15/AB15-1,"") -> 0.079572135 | AH15: (-) Sales & Marketing | AI15: -65.675702 | AJ15: 0 | AK15: -8.8112953 | AL15: =SUM(AI15:AK15) -> -74.486997 | AM15: 0 | AN15: 0 | AO15: =SUM(AL15:AN15) -> -74.486997 | AP15: =IFERROR(AO15/AO$9,0) -> -0.13705897 | AR15: -76.373718 | AS15: =IFERROR(AR15/AR$9,0) -> -0.14099006 | AT15: =AO15-AR15 -> 1.8867208 | AU15: =IFERROR(AO15/AR15-1,"") -> -0.024703797 | AX15: -50.426443 | AY15: -0.503801 | AZ15: -14.989079 | BA15: 0 | BB15: 0 | BC15: =SUM(AX15:BB15) -> -65.919323 | BD15: 0.078306 | BE15: 0 | BF15: =SUM(BC15:BE15) -> -65.841017 | BG15: =IFERROR(BF15/BF$9,0) -> -0.14265009 | BH15: =$AO15-BF15 -> -8.6459801 | BI15: =IFERROR(AO15/BF15-1,"") -> 0.13131602 | BK15: =AO15-K15 -> -59.387121 | BL15: =BK15/4 -> -14.84678
B16: (-) Research & Development | C16: (-) Research & Development | E16: -11.542275 | F16: -0.0155 | G16: -0.51027857 | H16: =SUM(E16:G16) -> -12.068053 | I16: 0 | J16: 0 | K16: =SUM(H16:J16) -> -12.068053 | L16: =IFERROR(K16/K$9,0) -> -0.10610708 | N16: -17.612835 | O16: =IFERROR(N16/N$9,0) -> -0.15576824 | P16: =K16-N16 -> 5.544782 | Q16: =IFERROR(K16/N16-1,"") -> -0.31481485 | T16: -14.626596 | U16: 0 | V16: -0.42558405 | W16: 0 | X16: 0 | Y16: =SUM(T16:X16) -> -15.05218 | Z16: 0 | AA16: 0 | AB16: =SUM(Y16:AA16) -> -15.05218 | AC16: =IFERROR(AB16/AB$9,0) -> -0.15813515 | AD16: =$K16-AB16 -> 2.9841272 | AE16: =IFERROR(K16/AB16-1,"") -> -0.19825216 | AH16: (-) Research & Development | AI16: -81.786056 | AJ16: -0.5114 | AK16: -2.9098954 | AL16: =SUM(AI16:AK16) -> -85.207352 | AM16: 0 | AN16: 0 | AO16: =SUM(AL16:AN16) -> -85.207352 | AP16: =IFERROR(AO16/AO$9,0) -> -0.15678484 | AR16: -85.432237 | AS16: =IFERROR(AR16/AR$9,0) -> -0.15771258 | AT16: =AO16-AR16 -> 0.22488503 | AU16: =IFERROR(AO16/AR16-1,"") -> -0.0026323206 | AX16: -74.210973 | AY16: -0.1111111 | AZ16: -0.11746809 | BA16: 0.26966966 | BB16: 0 | BC16: =SUM(AX16:BB16) -> -74.169882 | BD16: 0 | BE16: 0 | BF16: =SUM(BC16:BE16) -> -74.169882 | BG16: =IFERROR(BF16/BF$9,0) -> -0.16069528 | BH16: =$AO16-BF16 -> -11.037469 | BI16: =IFERROR(AO16/BF16-1,"") -> 0.14881336
B17: Bad Debts Provision | C17: (-) Bad Debts Provision | E17: -1.7506317 | F17: 0 | G17: 0 | H17: =SUM(E17:G17) -> -1.7506317 | I17: 0 | J17: 0 | K17: =SUM(H17:J17) -> -1.7506317 | L17: =IFERROR(K17/K$9,0) -> -0.015392243 | N17: -0.52878581 | O17: =IFERROR(N17/N$9,0) -> -0.0046765916 | P17: =K17-N17 -> -1.2218459 | Q17: =IFERROR(K17/N17-1,"") -> 2.3106631 | T17: -0.40976279 | U17: 0 | V17: 0 | W17: 0 | X17: 0 | Y17: =SUM(T17:X17) -> -0.40976279 | Z17: 0 | AA17: 0 | AB17: =SUM(Y17:AA17) -> -0.40976279 | AC17: =IFERROR(AB17/AB$9,0) -> -0.0043048847 | AD17: =$K17-AB17 -> -1.3408689 | AE17: =IFERROR(K17/AB17-1,"") -> 3.2723051 | AH17: (-) Bad Debts Provision | AI17: -4.9908547 | AJ17: 0 | AK17: 0 | AL17: =SUM(AI17:AK17) -> -4.9908547 | AM17: 0 | AN17: 0 | AO17: =SUM(AL17:AN17) -> -4.9908547 | AP17: =IFERROR(AO17/AO$9,0) -> -0.0091833667 | AR17: -2.6076659 | AS17: =IFERROR(AR17/AR$9,0) -> -0.0048138938 | AT17: =AO17-AR17 -> -2.3831888 | AU17: =IFERROR(AO17/AR17-1,"") -> 0.91391644 | AX17: -3.145584 | AY17: 0 | AZ17: 0 | BA17: 0 | BB17: 0 | BC17: =SUM(AX17:BB17) -> -3.145584 | BD17: 0 | BE17: 0 | BF17: =SUM(BC17:BE17) -> -3.145584 | BG17: =IFERROR(BF17/BF$9,0) -> -0.0068151719 | BH17: =$AO17-BF17 -> -1.8452708 | BI17: =IFERROR(AO17/BF17-1,"") -> 0.58662263
B18: Others Income and Expense | C18: (+/-) Others Income & Exp. | E18: 0.04132218 | F18: 0 | G18: -1.0138743 | H18: =SUM(E18:G18) -> -0.97255208 | I18: 0 | J18: 0 | K18: =SUM(H18:J18) -> -0.97255208 | L18: =IFERROR(K18/K$9,0) -> -0.008551061 | N18: 0 | O18: =IFERROR(N18/N$9,0) -> 0 | P18: =K18-N18 -> -0.97255208 | Q18: =IFERROR(K18/N18-1,"") | T18: 0.04598573 | U18: 0 | V18: 0 | W18: 0 | X18: 0 | Y18: =SUM(T18:X18) -> 0.04598573 | Z18: -0.03227199 | AA18: 0 | AB18: =SUM(Y18:AA18) -> 0.01371374 | AC18: =IFERROR(AB18/AB$9,0) -> 0.00014407377 | AD18: =$K18-AB18 -> -0.98626582 | AE18: =IFERROR(K18/AB18-1,"") -> -71.918078 | AH18: (+/-) Others Income & Exp. | AI18: -0.04067367 | AJ18: 0 | AK18: -1.0138743 | AL18: =SUM(AI18:AK18) -> -1.0545479 | AM18: 0 | AN18: 0 | AO18: =SUM(AL18:AN18) -> -1.0545479 | AP18: =IFERROR(AO18/AO$9,0) -> -0.0019404092 | AR18: 0 | AS18: =IFERROR(AR18/AR$9,0) -> 0 | AT18: =AO18-AR18 -> -1.0545479 | AU18: =IFERROR(AO18/AR18-1,"") | AX18: 1.3519638 | AY18: -0.06842838 | AZ18: 0 | BA18: 0 | BB18: 0 | BC18: =SUM(AX18:BB18) -> 1.2835354 | BD18: -1.3233187 | BE18: 0 | BF18: =SUM(BC18:BE18) -> -0.03978333 | BG18: =IFERROR(BF18/BF$9,0) -> -8.6193927e-05 | BH18: =$AO18-BF18 -> -1.0147646 | BI18: =IFERROR(AO18/BF18-1,"") -> 25.507282
C19: = Adjusted EBITDA | E19: =SUM(E11,E13) -> 34.469086 | F19: =SUM(F11,F13) -> -0.4807693 | G19: =SUM(G11,G13) -> 0 | H19: =SUM(H11,H13) -> 33.988317 | I19: =SUM(I11,I13) -> 0.086875 | J19: =SUM(J11,J13) -> 2.3283064e-16 | K19: =SUM(K11,K13) -> 34.075192 | L19: =IFERROR(K19/K$9,0) -> 0.29960251 | N19: =N11+N13 -> 26.771378 | O19: =IFERROR(N19/N$9,0) -> 0.23676657 | P19: =K19-N19 -> 7.3038138 | Q19: =IFERROR(K19/N19-1,"") -> 0.27282174 | R19: =IF(Q19>0.05,1,IF(Q19<-0.05,-1,0)) -> 1 | T19: =SUM(T11,T13) -> 22.822565 | U19: =SUM(U11,U13) -> -0.12618796 | V19: =SUM(V11,V13) -> 0 | W19: =SUM(W11,W13) -> 0 | X19: =SUM(X11,X13) -> 0 | Y19: =SUM(Y11,Y13) -> 22.696377 | Z19: =SUM(Z11,Z13) -> 0.02257201 | AA19: =SUM(AA11,AA13) -> 0 | AB19: =SUM(AB11,AB13) -> 22.718949 | AC19: =IFERROR(AB19/AB$9,0) -> 0.23868066 | AD19: =$K19-AB19 -> 11.356243 | AE19: =IFERROR(K19/AB19-1,"") -> 0.49985776 | AF19: =IF(AE19>0.05,1,IF(AE19<-0.05,-1,0)) -> 1 | AH19: = Adjusted EBITDA | AI19: =SUM(AI11,AI13) -> 126.69953 | AJ19: =SUM(AJ11,AJ13) -> 0.5436477 | AK19: =SUM(AK11,AK13) -> 0 | AL19: =SUM(AL11,AL13) -> 127.24318 | AM19: =SUM(AM11,AM13) -> 0.621875 | AN19: =SUM(AN11,AN13) -> 3.4924597e-16 | AO19: =SUM(AO11,AO13) -> 127.86505 | AP19: =IFERROR(AO19/AO$9,0) -> 0.23527667 | AR19: =AR11+AR13 -> 126.64426 | AS19: =IFERROR(AR19/AR$9,0) -> 0.23379223 | AT19: =AO19-AR19 -> 1.2207894 | AU19: =IFERROR(AO19/AR19-1,"") -> 0.009639516 | AV19: =IF(AU19>0.05,1,IF(AU19<-0.05,-1,0)) -> 0 | AX19: =SUM(AX11,AX13) -> 105.62692 | AY19: =SUM(AY11,AY13) -> -5.8884285 | AZ19: =SUM(AZ11,AZ13) -> 1.4210855e-14 | BA19: =SUM(BA11,BA13) -> 0 | BB19: =SUM(BB11,BB13) -> 0 | BC19: =SUM(BC11,BC13) -> 99.738487 | BD19: =SUM(BD11,BD13) -> -0.55265431 | BE19: =SUM(BE11,BE13) -> 0 | BF19: =SUM(BF11,BF13) -> 99.185833 | BG19: =IFERROR(BF19/BF$9,0) -> 0.21489444 | BH19: =$AO19-BF19 -> 28.67922 | BI19: =IFERROR(AO19/BF19-1,"") -> 0.28914633 | BJ19: =IF(BI19>0.05,1,IF(BI19<-0.05,-1,0)) -> 1
B20: BU Allocation | C20: (+/-) BU Allocation | E20: 3.4911693 | F20: 0 | G20: 0 | H20: =SUM(E20:G20) -> 3.4911693 | I20: 0 | J20: 0 | K20: =SUM(H20:J20) -> 3.4911693 | L20: =IFERROR(K20/K$9,0) -> 0.030695736 | N20: 0 | O20: =IFERROR(N20/N$9,0) -> 0 | P20: =K20-N20 -> 3.4911693 | Q20: =IFERROR(K20/N20-1,"") | T20: 0.41767093 | U20: 0 | V20: 0 | W20: 0 | X20: 0 | Y20: =SUM(T20:X20) -> 0.41767093 | Z20: 0 | AA20: 0 | AB20: =SUM(Y20:AA20) -> 0.41767093 | AC20: =IFERROR(AB20/AB$9,0) -> 0.0043879659 | AD20: =$K20-AB20 -> 3.0734984 | AE20: =IFERROR(K20/AB20-1,"") -> 7.3586602 | AH20: (+/-) BU Allocation | AI20: 16.979846 | AJ20: 0 | AK20: 0 | AL20: =SUM(AI20:AK20) -> 16.979846 | AM20: 0 | AN20: 0 | AO20: =SUM(AL20:AN20) -> 16.979846 | AP20: =IFERROR(AO20/AO$9,0) -> 0.031243576 | AR20: 0 | AS20: =IFERROR(AR20/AR$9,0) -> 0 | AT20: =AO20-AR20 -> 16.979846 | AU20: =IFERROR(AO20/AR20-1,"") | AX20: -0.88102105 | AY20: 0 | AZ20: 0 | BA20: 0 | BB20: 0 | BC20: =SUM(AX20:BB20) -> -0.88102105 | BD20: 0 | BE20: 0 | BF20: =SUM(BC20:BE20) -> -0.88102105 | BG20: =IFERROR(BF20/BF$9,0) -> -0.0019088061 | BH20: =$AO20-BF20 -> 17.860867 | BI20: =IFERROR(AO20/BF20-1,"") -> -20.272917
B21: Holding - Cost Sharing | C21: (-) Holding - Cost Sharing | E21: -6.1596697 | F21: 0 | G21: 0 | H21: =SUM(E21:G21) -> -6.1596697 | I21: 0 | J21: 0 | K21: =SUM(H21:J21) -> -6.1596697 | L21: =IFERROR(K21/K$9,0) -> -0.054158242 | N21: 0 | O21: =IFERROR(N21/N$9,0) -> 0 | P21: =K21-N21 -> -6.1596697 | Q21: =IFERROR(K21/N21-1,"") | T21: -0.67363035 | U21: 0 | V21: 0 | W21: 0 | X21: 0 | Y21: =SUM(T21:X21) -> -0.67363035 | Z21: 0 | AA21: 0 | AB21: =SUM(Y21:AA21) -> -0.67363035 | AC21: =IFERROR(AB21/AB$9,0) -> -0.0070770237 | AD21: =$K21-AB21 -> -5.4860393 | AE21: =IFERROR(K21/AB21-1,"") -> 8.1439907 | AH21: (-) Holding - Cost Sharing | AI21: -37.973932 | AJ21: 7.2759576e-18 | AK21: 0 | AL21: =SUM(AI21:AK21) -> -37.973932 | AM21: 0 | AN21: 0 | AO21: =SUM(AL21:AN21) -> -37.973932 | AP21: =IFERROR(AO21/AO$9,0) -> -0.069873511 | AR21: 0 | AS21: =IFERROR(AR21/AR$9,0) -> 0 | AT21: =AO21-AR21 -> -37.973932 | AU21: =IFERROR(AO21/AR21-1,"") | AX21: -2.314233 | AY21: 0 | AZ21: 0 | BA21: 0 | BB21: 0 | BC21: =SUM(AX21:BB21) -> -2.314233 | BD21: 0 | BE21: 0 | BF21: =SUM(BC21:BE21) -> -2.314233 | BG21: =IFERROR(BF21/BF$9,0) -> -0.0050139802 | BH21: =$AO21-BF21 -> -35.659699 | BI21: =IFERROR(AO21/BF21-1,"") -> 15.408863
B22: Shared Services | C22: (+/-) Shared Services | E22: 2.6647991 | F22: 0 | G22: 0 | H22: =SUM(E22:G22) -> 2.6647991 | I22: 0 | J22: 0 | K22: =SUM(H22:J22) -> 2.6647991 | L22: =IFERROR(K22/K$9,0) -> 0.023429963 | N22: 0 | O22: =IFERROR(N22/N$9,0) -> 0 | P22: =K22-N22 -> 2.6647991 | Q22: =IFERROR(K22/N22-1,"") | T22: 0.18852078 | U22: 0 | V22: 0 | W22: 0 | X22: 0 | Y22: =SUM(T22:X22) -> 0.18852078 | Z22: 0 | AA22: 0 | AB22: =SUM(Y22:AA22) -> 0.18852078 | AC22: =IFERROR(AB22/AB$9,0) -> 0.001980561 | AD22: =$K22-AB22 -> 2.4762783 | AE22: =IFERROR(K22/AB22-1,"") -> 13.135307 | AH22: (+/-) Shared Services | AI22: 20.976155 | AJ22: 0 | AK22: 0 | AL22: =SUM(AI22:AK22) -> 20.976155 | AM22: 0 | AN22: 0 | AO22: =SUM(AL22:AN22) -> 20.976155 | AP22: =IFERROR(AO22/AO$9,0) -> 0.038596941 | AR22: 0 | AS22: =IFERROR(AR22/AR$9,0) -> 0 | AT22: =AO22-AR22 -> 20.976155 | AU22: =IFERROR(AO22/AR22-1,"") | AX22: 3.1251551 | AY22: 0 | AZ22: 0 | BA22: 0 | BB22: 0 | BC22: =SUM(AX22:BB22) -> 3.1251551 | BD22: 0 | BE22: 0 | BF22: =SUM(BC22:BE22) -> 3.1251551 | BG22: =IFERROR(BF22/BF$9,0) -> 0.0067709111 | BH22: =$AO22-BF22 -> 17.851 | BI22: =IFERROR(AO22/BF22-1,"") -> 5.7120366
C24: Managerial EBITDA | E24: =SUM(E19:E22) -> 34.465385 | F24: =SUM(F19:F22) -> -0.4807693 | G24: =SUM(G19:G22) -> 0 | H24: =SUM(H19:H22) -> 33.984616 | I24: =SUM(I19:I22) -> 0.086875 | J24: =SUM(J19:J22) -> 2.3283064e-16 | K24: =SUM(K19:K22) -> 34.071491 | L24: =IFERROR(K24/K$9,0) -> 0.29956997 | N24: =N19+N20+N21+N22 -> 26.771378 | O24: =IFERROR(N24/N$9,0) -> 0.23676657 | P24: =K24-N24 -> 7.3001126 | Q24: =IFERROR(K24/N24-1,"") -> 0.27268348 | R24: =IF(Q24>0.05,1,IF(Q24<-0.05,-1,0)) -> 1 | T24: =SUM(T19:T22) -> 22.755126 | U24: =SUM(U19:U22) -> -0.12618796 | V24: =SUM(V19:V22) -> 0 | W24: =SUM(W19:W22) -> 0 | X24: =SUM(X19:X22) -> 0 | Y24: =SUM(Y19:Y22) -> 22.628938 | Z24: =SUM(Z19:Z22) -> 0.02257201 | AA24: =SUM(AA19:AA22) -> 0 | AB24: =SUM(AB19:AB22) -> 22.65151 | AC24: =IFERROR(AB24/AB$9,0) -> 0.23797217 | AD24: =$K24-AB24 -> 11.41998 | AE24: =IFERROR(K24/AB24-1,"") -> 0.50415977 | AF24: =IF(AE24>0.05,1,IF(AE24<-0.05,-1,0)) -> 1 | AH24: Managerial EBITDA | AI24: =SUM(AI19:AI22) -> 126.6816 | AJ24: =SUM(AJ19:AJ22) -> 0.5436477 | AK24: =SUM(AK19:AK22) -> 0 | AL24: =SUM(AL19:AL22) -> 127.22525 | AM24: =SUM(AM19:AM22) -> 0.621875 | AN24: =SUM(AN19:AN22) -> 3.4924597e-16 | AO24: =SUM(AO19:AO22) -> 127.84712 | AP24: =IFERROR(AO24/AO$9,0) -> 0.23524367 | AR24: =AR19+AR20+AR21+AR22 -> 126.64426 | AS24: =IFERROR(AR24/AR$9,0) -> 0.23379223 | AT24: =AO24-AR24 -> 1.2028584 | AU24: =IFERROR(AO24/AR24-1,"") -> 0.0094979306 | AV24: =IF(AU24>0.05,1,IF(AU24<-0.05,-1,0)) -> 0 | AX24: =SUM(AX19:AX22) -> 105.55682 | AY24: =SUM(AY19:AY22) -> -5.8884285 | AZ24: =SUM(AZ19:AZ22) -> 1.4210855e-14 | BA24: =SUM(BA19:BA22) -> 0 | BB24: =SUM(BB19:BB22) -> 0 | BC24: =SUM(BC19:BC22) -> 99.668388 | BD24: =SUM(BD19:BD22) -> -0.55265431 | BE24: =SUM(BE19:BE22) -> 0 | BF24: =SUM(BF19:BF22) -> 99.115734 | BG24: =IFERROR(BF24/BF$9,0) -> 0.21474256 | BH24: =$AO24-BF24 -> 28.731388 | BI24: =IFERROR(AO24/BF24-1,"") -> 0.28987717 | BJ24: =IF(BI24>0.05,1,IF(BI24<-0.05,-1,0)) -> 1
B25: Adjustments to EBITDA | C25: (+/-) Non-recurring | E25: -0.4807693 | F25: 0.4807693 | G25: 0 | H25: =SUM(E25:G25) -> 0 | I25: -0.086875 | J25: 0 | K25: =SUM(H25:J25) -> -0.086875 | L25: =IFERROR(K25/K$9,0) -> -0.00076383922 | N25: -0.088 | O25: =IFERROR(N25/N$9,0) -> -0.00077827364 | P25: =K25-N25 -> 0.001125 | Q25: =IFERROR(K25/N25-1,"") -> -0.012784091 | T25: -0.12618796 | U25: 0.12618796 | V25: 0 | W25: 0 | X25: 0 | Y25: =SUM(T25:X25) -> 0 | Z25: -0.02257201 | AA25: 0 | AB25: =SUM(Y25:AA25) -> -0.02257201 | AC25: =IFERROR(AB25/AB$9,0) -> -0.00023713695 | AD25: =$K25-AB25 -> -0.06430299 | AE25: =IFERROR(K25/AB25-1,"") -> 2.8487933 | AH25: (+/-) Non-recurring | AI25: 0.54338492 | AJ25: -0.5436477 | AK25: 0 | AL25: =SUM(AI25:AK25) -> -0.00026278 | AM25: -0.621875 | AN25: 0 | AO25: =SUM(AL25:AN25) -> -0.62213778 | AP25: =IFERROR(AO25/AO$9,0) -> -0.0011447577 | AR25: -0.69 | AS25: =IFERROR(AR25/AR$9,0) -> -0.0012737777 | AT25: =AO25-AR25 -> 0.06786222 | AU25: =IFERROR(AO25/AR25-1,"") -> -0.098351043 | AX25: -5.8884285 | AY25: 5.8884285 | AZ25: 0 | BA25: 0 | BB25: 0 | BC25: =SUM(AX25:BB25) -> 0 | BD25: 0.55265431 | BE25: 0 | BF25: =SUM(BC25:BE25) -> 0.55265431 | BG25: =IFERROR(BF25/BF$9,0) -> 0.001197372 | BH25: =$AO25-BF25 -> -1.1747921 | BI25: =IFERROR(AO25/BF25-1,"") -> -2.1257268
C26: = EBITDA | E26: =SUM(E24:E25) -> 33.984616 | F26: =SUM(F24:F25) -> 0 | G26: =SUM(G24:G25) -> 0 | H26: =SUM(H24:H25) -> 33.984616 | I26: =SUM(I24:I25) -> 0 | J26: =SUM(J24:J25) -> 2.3283064e-16 | K26: =SUM(K24:K25) -> 33.984616 | L26: =IFERROR(K26/K$9,0) -> 0.29880613 | N26: =N24+N25 -> 26.683378 | O26: =IFERROR(N26/N$9,0) -> 0.23598829 | P26: =K26-N26 -> 7.3012376 | Q26: =IFERROR(K26/N26-1,"") -> 0.27362494 | R26: =IF(Q26>0.05,1,IF(Q26<-0.05,-1,0)) -> 1 | T26: =SUM(T24:T25) -> 22.628938 | U26: =SUM(U24:U25) -> 0 | V26: =SUM(V24:V25) -> 0 | W26: =SUM(W24:W25) -> 0 | X26: =SUM(X24:X25) -> 0 | Y26: =SUM(Y24:Y25) -> 22.628938 | Z26: =SUM(Z24:Z25) -> 0 | AA26: =SUM(AA24:AA25) -> 0 | AB26: =SUM(AB24:AB25) -> 22.628938 | AC26: =IFERROR(AB26/AB$9,0) -> 0.23773503 | AD26: =$K26-AB26 -> 11.355677 | AE26: =IFERROR(K26/AB26-1,"") -> 0.50182104 | AF26: =IF(AE26>0.05,1,IF(AE26<-0.05,-1,0)) -> 1 | AH26: = EBITDA | AI26: =SUM(AI24:AI25) -> 127.22498 | AJ26: =SUM(AJ24:AJ25) -> 0 | AK26: =SUM(AK24:AK25) -> 0 | AL26: =SUM(AL24:AL25) -> 127.22498 | AM26: =SUM(AM24:AM25) -> 0 | AN26: =SUM(AN24:AN25) -> 3.4924597e-16 | AO26: =SUM(AO24:AO25) -> 127.22498 | AP26: =IFERROR(AO26/AO$9,0) -> 0.23409892 | AR26: =AR24+AR25 -> 125.95426 | AS26: =IFERROR(AR26/AR$9,0) -> 0.23251845 | AT26: =AO26-AR26 -> 1.2707207 | AU26: =IFERROR(AO26/AR26-1,"") -> 0.010088747 | AV26: =IF(AU26>0.05,1,IF(AU26<-0.05,-1,0)) -> 0 | AX26: =SUM(AX24:AX25) -> 99.668388 | AY26: =SUM(AY24:AY25) -> 0 | AZ26: =SUM(AZ24:AZ25) -> 1.4210855e-14 | BA26: =SUM(BA24:BA25) -> 0 | BB26: =SUM(BB24:BB25) -> 0 | BC26: =SUM(BC24:BC25) -> 99.668388 | BD26: =SUM(BD24:BD25) -> 0 | BE26: =SUM(BE24:BE25) -> 0 | BF26: =SUM(BF24:BF25) -> 99.668388 | BG26: =IFERROR(BF26/BF$9,0) -> 0.21593994 | BH26: =$AO26-BF26 -> 27.556596 | BI26: =IFERROR(AO26/BF26-1,"") -> 0.27648281 | BJ26: =IF(BI26>0.05,1,IF(BI26<-0.05,-1,0)) -> 1
C27: (-) D&A | E27: =SUM(E28:E29) -> -8.7318616 | F27: =SUM(F28:F29) -> 0 | G27: =SUM(G28:G29) -> 0 | H27: =SUM(H28:H29) -> -8.7318616 | I27: =SUM(I28:I29) -> 0 | J27: =SUM(J28:J29) -> 0 | K27: =SUM(K28:K29) -> -8.7318616 | L27: =IFERROR(K27/K$9,0) -> -0.076773966 | N27: =SUM(N28:N29) -> -8.8445773 | O27: =IFERROR(N27/N$9,0) -> -0.078221607 | P27: =K27-N27 -> 0.11271576 | Q27: =IFERROR(K27/N27-1,"") -> -0.012744053 | T27: =SUM(T28:T29) -> -7.6700771 | U27: =SUM(U28:U29) -> 0 | V27: =SUM(V28:V29) -> 0 | W27: =SUM(W28:W29) -> 0 | X27: =SUM(X28:X29) -> 0 | Y27: =SUM(Y28:Y29) -> -7.6700771 | Z27: =SUM(Z28:Z29) -> 0 | AA27: =SUM(AA28:AA29) -> 0 | AB27: =SUM(AB28:AB29) -> -7.6700771 | AC27: =IFERROR(AB27/AB$9,0) -> -0.080580273 | AD27: =$K27-AB27 -> -1.0617844 | AE27: =IFERROR(K27/AB27-1,"") -> 0.13843204 | AF27: =IF(AE27>0.05,1,IF(AE27<-0.05,-1,0)) -> 1 | AI27: =SUM(AI28:AI29) -> -43.955698 | AJ27: =SUM(AJ28:AJ29) -> 0 | AK27: =SUM(AK28:AK29) -> 0 | AL27: =SUM(AL28:AL29) -> -43.955698 | AM27: =SUM(AM28:AM29) -> 0 | AN27: =SUM(AN28:AN29) -> 0 | AO27: =SUM(AO28:AO29) -> -43.955698 | AP27: =IFERROR(AO27/AO$9,0) -> -0.080880193 | AR27: =SUM(AR28:AR29) -> -45.689141 | AS27: =IFERROR(AR27/AR$9,0) -> -0.084344651 | AT27: =AO27-AR27 -> 1.733443 | AU27: =IFERROR(AO27/AR27-1,"") -> -0.037939934 | AV27: =IF(AU27>0.05,1,IF(AU27<-0.05,-1,0)) -> 0 | AX27: =SUM(AX28:AX29) -> -40.793179 | AY27: =SUM(AY28:AY29) -> 0 | AZ27: =SUM(AZ28:AZ29) -> 0 | BA27: =SUM(BA28:BA29) -> 0 | BB27: =SUM(BB28:BB29) -> 0 | BC27: =SUM(BC28:BC29) -> -40.793179 | BD27: =SUM(BD28:BD29) -> 0 | BE27: =SUM(BE28:BE29) -> 0 | BF27: =SUM(BF28:BF29) -> -40.793179 | BG27: =IFERROR(BF27/BF$9,0) -> -0.088381849 | BH27: =$AO27-BF27 -> -3.162519 | BI27: =IFERROR(AO27/BF27-1,"") -> 0.077525683 | BJ27: =IF(BI27>0.05,1,IF(BI27<-0.05,-1,0)) -> 1
B28: D&A | C28: (-) D&A Operating Assests | E28: -3.9002693 | F28: 0 | G28: 0 | H28: =SUM(E28:G28) -> -3.9002693 | I28: 0 | J28: 0 | K28: =SUM(H28:J28) -> -3.9002693 | L28: =IFERROR(K28/K$9,0) -> -0.034292704 | N28: -3.8564283 | O28: =IFERROR(N28/N$9,0) -> -0.034106324 | P28: =K28-N28 -> -0.043840937 | Q28: =IFERROR(K28/N28-1,"") -> 0.011368275 | T28: -2.503726 | U28: 0 | V28: 0 | W28: 0 | X28: 0 | Y28: =SUM(T28:X28) -> -2.503726 | Z28: 0 | AA28: 0 | AB28: =SUM(Y28:AA28) -> -2.503726 | AC28: =IFERROR(AB28/AB$9,0) -> -0.026303637 | AD28: =$K28-AB28 -> -1.3965433 | AE28: =IFERROR(K28/AB28-1,"") -> 0.55778598 | AH28: (-) D&A | AI28: -19.652629 | AJ28: 0 | AK28: 0 | AL28: =SUM(AI28:AK28) -> -19.652629 | AM28: 0 | AN28: 0 | AO28: =SUM(AL28:AN28) -> -19.652629 | AP28: =IFERROR(AO28/AO$9,0) -> -0.036161602 | AR28: -19.727686 | AS28: =IFERROR(AR28/AR$9,0) -> -0.036418387 | AT28: =AO28-AR28 -> 0.075056793 | AU28: =IFERROR(AO28/AR28-1,"") -> -0.0038046425 | AX28: -15.198728 | AY28: 0 | AZ28: 0 | BA28: 0 | BB28: 0 | BC28: =SUM(AX28:BB28) -> -15.198728 | BD28: 0 | BE28: 0 | BF28: =SUM(BC28:BE28) -> -15.198728 | BG28: =IFERROR(BF28/BF$9,0) -> -0.03292932 | BH28: =$AO28-BF28 -> -4.4539018 | BI28: =IFERROR(AO28/BF28-1,"") -> 0.29304439
B29: M&A Amortization | C29: (-) M&A Amortization | E29: -4.8315923 | F29: 0 | G29: 0 | H29: =SUM(E29:G29) -> -4.8315923 | I29: 0 | J29: 0 | K29: =SUM(H29:J29) -> -4.8315923 | L29: =IFERROR(K29/K$9,0) -> -0.042481263 | N29: -4.988149 | O29: =IFERROR(N29/N$9,0) -> -0.044115283 | P29: =K29-N29 -> 0.1565567 | Q29: =IFERROR(K29/N29-1,"") -> -0.03138573 | T29: -5.1663511 | U29: 0 | V29: 0 | W29: 0 | X29: 0 | Y29: =SUM(T29:X29) -> -5.1663511 | Z29: 0 | AA29: 0 | AB29: =SUM(Y29:AA29) -> -5.1663511 | AC29: =IFERROR(AB29/AB$9,0) -> -0.054276636 | AD29: =$K29-AB29 -> 0.33475884 | AE29: =IFERROR(K29/AB29-1,"") -> -0.064795991 | AH29: (-) M&A Amortization | AI29: -24.303068 | AJ29: 0 | AK29: 0 | AL29: =SUM(AI29:AK29) -> -24.303068 | AM29: 0 | AN29: 0 | AO29: =SUM(AL29:AN29) -> -24.303068 | AP29: =IFERROR(AO29/AO$9,0) -> -0.044718591 | AR29: -25.961455 | AS29: =IFERROR(AR29/AR$9,0) -> -0.047926264 | AT29: =AO29-AR29 -> 1.6583862 | AU29: =IFERROR(AO29/AR29-1,"") -> -0.063878785 | AX29: -25.594451 | AY29: 0 | AZ29: 0 | BA29: 0 | BB29: 0 | BC29: =SUM(AX29:BB29) -> -25.594451 | BD29: 0 | BE29: 0 | BF29: =SUM(BC29:BE29) -> -25.594451 | BG29: =IFERROR(BF29/BF$9,0) -> -0.055452529 | BH29: =$AO29-BF29 -> 1.2913828 | BI29: =IFERROR(AO29/BF29-1,"") -> -0.050455576
B30: Financial Results | C30: (+/-) Financial Results | E30: -0.74368261 | F30: 0 | G30: 0 | H30: =SUM(E30:G30) -> -0.74368261 | I30: 0 | J30: 0 | K30: =SUM(H30:J30) -> -0.74368261 | L30: =IFERROR(K30/K$9,0) -> -0.0065387504 | N30: -1.4781771 | O30: =IFERROR(N30/N$9,0) -> -0.013073026 | P30: =K30-N30 -> 0.73449446 | Q30: =IFERROR(K30/N30-1,"") -> -0.49689207 | T30: -3.2063321 | U30: 0 | V30: 0 | W30: 0 | X30: 0 | Y30: =SUM(T30:X30) -> -3.2063321 | Z30: 0 | AA30: 0 | AB30: =SUM(Y30:AA30) -> -3.2063321 | AC30: =IFERROR(AB30/AB$9,0) -> -0.033685074 | AD30: =$K30-AB30 -> 2.4626495 | AE30: =IFERROR(K30/AB30-1,"") -> -0.76805815 | AH30: (+/-) Financial Results | AI30: -5.262409 | AJ30: 0 | AK30: 0 | AL30: =SUM(AI30:AK30) -> -5.262409 | AM30: 0 | AN30: 0 | AO30: =SUM(AL30:AN30) -> -5.262409 | AP30: =IFERROR(AO30/AO$9,0) -> -0.0096830371 | AR30: -8.0803088 | AS30: =IFERROR(AR30/AR$9,0) -> -0.014916692 | AT30: =AO30-AR30 -> 2.8178998 | AU30: =IFERROR(AO30/AR30-1,"") -> -0.34873664 | AX30: -10.368245 | AY30: 0 | AZ30: 0 | BA30: 0 | BB30: 0 | BC30: =SUM(AX30:BB30) -> -10.368245 | BD30: 0 | BE30: 0 | BF30: =SUM(BC30:BE30) -> -10.368245 | BG30: =IFERROR(BF30/BF$9,0) -> -0.022463673 | BH30: =$AO30-BF30 -> 5.1058358 | BI30: =IFERROR(AO30/BF30-1,"") -> -0.49244939
C31: (+) Financial Revenue | K31: 2.7418117 | L31: =IFERROR(K31/K$9,0) -> 0.024107088 | N31: 1.1928444 | O31: =IFERROR(N31/N$9,0) -> 0.010549538 | P31: =K31-N31 -> 1.5489673 | Q31: =IFERROR(K31/N31-1,"") -> 1.2985493 | AB31: 0.99911402 | AC31: =IFERROR(AB31/AB$9,0) -> 0.010496489 | AD31: =$K31-AB31 -> 1.7426977 | AE31: =IFERROR(K31/AB31-1,"") -> 1.744243 | AO31: 17.139972 | AP31: =IFERROR(AO31/AO$9,0) -> 0.031538214 | AR31: 6.0266249 | AS31: =IFERROR(AR31/AR$9,0) -> 0.011125479 | AT31: =AO31-AR31 -> 11.113347 | AU31: =IFERROR(AO31/AR31-1,"") -> 1.8440415 | BF31: 9.9846335 | BG31: =IFERROR(BF31/BF$9,0) -> 0.021632547 | BH31: =$AO31-BF31 -> 7.155338 | BI31: =IFERROR(AO31/BF31-1,"") -> 0.71663502
C32: (-) Financial Expenses | K32: -3.4471245 | L32: =IFERROR(K32/K$9,0) -> -0.030308477 | N32: -2.6710215 | O32: =IFERROR(N32/N$9,0) -> -0.023622564 | P32: =K32-N32 -> -0.77610307 | Q32: =IFERROR(K32/N32-1,"") -> 0.29056415 | AB32: -4.2054469 | AC32: =IFERROR(AB32/AB$9,0) -> -0.044181571 | AD32: =$K32-AB32 -> 0.75832236 | AE32: =IFERROR(K32/AB32-1,"") -> -0.18031909 | AO32: -22.36428 | AP32: =IFERROR(AO32/AO$9,0) -> -0.041151145 | AR32: -14.106934 | AS32: =IFERROR(AR32/AR$9,0) -> -0.026042171 | AT32: =AO32-AR32 -> -8.2573468 | AU32: =IFERROR(AO32/AR32-1,"") -> 0.58533959 | BF32: -20.368833 | BG32: =IFERROR(BF32/BF$9,0) -> -0.044130788 | BH32: =$AO32-BF32 -> -1.9954473 | BI32: =IFERROR(AO32/BF32-1,"") -> 0.097965713
C33: (-) Income Tax | E33: =SUM(E34:E35) -> -5.7406935 | F33: =SUM(F34:F35) -> 0 | G33: =SUM(G34:G35) -> 0 | H33: =SUM(H34:H35) -> -5.7406935 | I33: =SUM(I34:I35) -> 0 | J33: =SUM(J34:J35) -> 0 | K33: =SUM(K34:K35) -> -5.7406935 | L33: =IFERROR(K33/K$9,0) -> -0.050474439 | N33: =SUM(N34:N35) -> -7.4642437 | O33: =IFERROR(N33/N$9,0) -> -0.066013911 | P33: =K33-N33 -> 1.7235502 | Q33: =IFERROR(K33/N33-1,"") -> -0.23090755 | T33: =SUM(T34:T35) -> -14.041346 | U33: =SUM(U34:U35) -> 0 | V33: =SUM(V34:V35) -> 0 | W33: =SUM(W34:W35) -> 0 | X33: =SUM(X34:X35) -> 0 | Y33: =SUM(Y34:Y35) -> -14.041346 | Z33: =SUM(Z34:Z35) -> 0 | AA33: =SUM(AA34:AA35) -> 0 | AB33: =SUM(AB34:AB35) -> -14.041346 | AC33: =IFERROR(AB33/AB$9,0) -> -0.14751553 | AD33: =$K33-AB33 -> 8.3006529 | AE33: =IFERROR(K33/AB33-1,"") -> -0.5911579 | AI33: =SUM(AI34:AI35) -> -28.282652 | AJ33: =SUM(AJ34:AJ35) -> 0 | AK33: =SUM(AK34:AK35) -> 0 | AL33: =SUM(AL34:AL35) -> -28.282652 | AM33: =SUM(AM34:AM35) -> 0 | AN33: =SUM(AN34:AN35) -> 0 | AO33: =SUM(AO34:AO35) -> -28.282652 | AP33: =IFERROR(AO33/AO$9,0) -> -0.05204118 | AR33: =SUM(AR34:AR35) -> -35.778353 | AS33: =IFERROR(AR33/AR$9,0) -> -0.066048796 | AT33: =AO33-AR33 -> 7.495701 | AU33: =IFERROR(AO33/AR33-1,"") -> -0.2095038 | AX33: =SUM(AX34:AX35) -> -23.010915 | AY33: =SUM(AY34:AY35) -> 0 | AZ33: =SUM(AZ34:AZ35) -> 0 | BA33: =SUM(BA34:BA35) -> 0 | BB33: =SUM(BB34:BB35) -> 0 | BC33: =SUM(BC34:BC35) -> -23.010915 | BD33: =SUM(BD34:BD35) -> 0 | BE33: =SUM(BE34:BE35) -> 0 | BF33: =SUM(BF34:BF35) -> -23.010915 | BG33: =IFERROR(BF33/BF$9,0) -> -0.04985508 | BH33: =$AO33-BF33 -> -5.2717377 | BI33: =IFERROR(AO33/BF33-1,"") -> 0.22909727
B34: Income Tax | C34: (-) Current | E34: -5.1142733 | F34: 0 | G34: 0 | H34: =SUM(E34:G34) -> -5.1142733 | I34: 0 | J34: 0 | K34: =SUM(H34:J34) -> -5.1142733 | L34: =IFERROR(K34/K$9,0) -> -0.044966706 | N34: -5.4016825 | O34: =IFERROR(N34/N$9,0) -> -0.04777258 | P34: =K34-N34 -> 0.28740912 | Q34: =IFERROR(K34/N34-1,"") -> -0.053207334 | T34: -5.7813332 | U34: 0 | V34: 0 | W34: 0 | X34: 0 | Y34: =SUM(T34:X34) -> -5.7813332 | Z34: 0 | AA34: 0 | AB34: =SUM(Y34:AA34) -> -5.7813332 | AC34: =IFERROR(AB34/AB$9,0) -> -0.060737513 | AD34: =$K34-AB34 -> 0.66705987 | AE34: =IFERROR(K34/AB34-1,"") -> -0.11538167 | AH34: (-) Income Tax | AI34: -17.499858 | AJ34: 0 | AK34: 0 | AL34: =SUM(AI34:AK34) -> -17.499858 | AM34: 0 | AN34: 0 | AO34: =SUM(AL34:AN34) -> -17.499858 | AP34: =IFERROR(AO34/AO$9,0) -> -0.032200419 | AR34: -25.48615 | AS34: =IFERROR(AR34/AR$9,0) -> -0.047048826 | AT34: =AO34-AR34 -> 7.9862921 | AU34: =IFERROR(AO34/AR34-1,"") -> -0.31335812 | AX34: -17.445239 | AY34: 0 | AZ34: 0 | BA34: 0 | BB34: 0 | BC34: =SUM(AX34:BB34) -> -17.445239 | BD34: 0 | BE34: 0 | BF34: =SUM(BC34:BE34) -> -17.445239 | BG34: =IFERROR(BF34/BF$9,0) -> -0.037796577 | BH34: =$AO34-BF34 -> -0.054618422 | BI34: =IFERROR(AO34/BF34-1,"") -> 0.0031308497
B35: Deferred Tax | C35: (+/-) Deferred | E35: -0.62642019 | F35: 0 | G35: 0 | H35: =SUM(E35:G35) -> -0.62642019 | I35: 0 | J35: 0 | K35: =SUM(H35:J35) -> -0.62642019 | L35: =IFERROR(K35/K$9,0) -> -0.005507733 | N35: -2.0625613 | O35: =IFERROR(N35/N$9,0) -> -0.01824133 | P35: =K35-N35 -> 1.4361411 | Q35: =IFERROR(K35/N35-1,"") -> -0.69629014 | T35: -8.2600132 | U35: 0 | V35: 0 | W35: 0 | X35: 0 | Y35: =SUM(T35:X35) -> -8.2600132 | Z35: 0 | AA35: 0 | AB35: =SUM(Y35:AA35) -> -8.2600132 | AC35: =IFERROR(AB35/AB$9,0) -> -0.086778022 | AD35: =$K35-AB35 -> 7.633593 | AE35: =IFERROR(K35/AB35-1,"") -> -0.92416233 | AH35: (+/-) Deferred Tax | AI35: -10.782795 | AJ35: 0 | AK35: 0 | AL35: =SUM(AI35:AK35) -> -10.782795 | AM35: 0 | AN35: 0 | AO35: =SUM(AL35:AN35) -> -10.782795 | AP35: =IFERROR(AO35/AO$9,0) -> -0.019840761 | AR35: -10.292204 | AS35: =IFERROR(AR35/AR$9,0) -> -0.01899997 | AT35: =AO35-AR35 -> -0.4905911 | AU35: =IFERROR(AO35/AR35-1,"") -> 0.047666284 | AX35: -5.5656754 | AY35: 0 | AZ35: 0 | BA35: 0 | BB35: 0 | BC35: =SUM(AX35:BB35) -> -5.5656754 | BD35: 0 | BE35: 0 | BF35: =SUM(BC35:BE35) -> -5.5656754 | BG35: =IFERROR(BF35/BF$9,0) -> -0.012058503 | BH35: =$AO35-BF35 -> -5.2171193 | BI35: =IFERROR(AO35/BF35-1,"") -> 0.93737399
C36: Adjusted Net Income | E36: =SUM(E24,E27,E30,E33) -> 19.249147 | F36: =SUM(F24,F27,F30,F33) -> -0.4807693 | G36: =SUM(G24,G27,G30,G33) -> 0 | H36: =SUM(H24,H27,H30,H33) -> 18.768378 | I36: =SUM(I24,I27,I30,I33) -> 0.086875 | J36: =SUM(J24,J27,J30,J33) -> 2.3283064e-16 | K36: =SUM(K24,K27,K30,K33) -> 18.855253 | L36: =IFERROR(K36/K$9,0) -> 0.16578281 | N36: =SUM(N24,N27,N30,N33) -> 8.9843798 | O36: =IFERROR(N36/N$9,0) -> 0.079458023 | P36: =K36-N36 -> 9.870873 | Q36: =IFERROR(K36/N36-1,"") -> 1.0986705 | T36: =SUM(T24,T27,T30,T33) -> -2.1626294 | U36: =SUM(U24,U27,U30,U33) -> -0.12618796 | V36: =SUM(V24,V27,V30,V33) -> 0 | W36: =SUM(W24,W27,W30,W33) -> 0 | X36: =SUM(X24,X27,X30,X33) -> 0 | Y36: =SUM(Y24,Y27,Y30,Y33) -> -2.2888174 | Z36: =SUM(Z24,Z27,Z30,Z33) -> 0.02257201 | AA36: =SUM(AA24,AA27,AA30,AA33) -> 0 | AB36: =SUM(AB24,AB27,AB30,AB33) -> -2.2662454 | AC36: =IFERROR(AB36/AB$9,0) -> -0.023808714 | AD36: =$K36-AB36 -> 21.121498 | AE36: =IFERROR(K36/AB36-1,"") -> -9.3200403 | AH36: Adjusted Net Income | AI36: =SUM(AI24,AI27,AI30,AI33) -> 49.18084 | AJ36: =SUM(AJ24,AJ27,AJ30,AJ33) -> 0.5436477 | AK36: =SUM(AK24,AK27,AK30,AK33) -> 0 | AL36: =SUM(AL24,AL27,AL30,AL33) -> 49.724488 | AM36: =SUM(AM24,AM27,AM30,AM33) -> 0.621875 | AN36: =SUM(AN24,AN27,AN30,AN33) -> 3.4924597e-16 | AO36: =SUM(AO24,AO27,AO30,AO33) -> 50.346363 | AP36: =IFERROR(AO36/AO$9,0) -> 0.092639265 | AR36: =SUM(AR24,AR27,AR30,AR33) -> 37.096461 | AS36: =IFERROR(AR36/AR$9,0) -> 0.068482094 | AT36: =AO36-AR36 -> 13.249902 | AU36: =IFERROR(AO36/AR36-1,"") -> 0.35717429 | AX36: =SUM(AX24,AX27,AX30,AX33) -> 31.384478 | AY36: =SUM(AY24,AY27,AY30,AY33) -> -5.8884285 | AZ36: =SUM(AZ24,AZ27,AZ30,AZ33) -> 1.4210855e-14 | BA36: =SUM(BA24,BA27,BA30,BA33) -> 0 | BB36: =SUM(BB24,BB27,BB30,BB33) -> 0 | BC36: =SUM(BC24,BC27,BC30,BC33) -> 25.49605 | BD36: =SUM(BD24,BD27,BD30,BD33) -> -0.55265431 | BE36: =SUM(BE24,BE27,BE30,BE33) -> 0 | BF36: =SUM(BF24,BF27,BF30,BF33) -> 24.943396 | BG36: =IFERROR(BF36/BF$9,0) -> 0.054041962 | BH36: =$AO36-BF36 -> 25.402967 | BI36: =IFERROR(AO36/BF36-1,"") -> 1.0184246
B37: Adjustments | C37: (+/-) Non-recurring | E37: 0 | F37: 0 | G37: 0 | H37: =SUM(E37:G37) -> 0 | I37: 0 | J37: 0 | K37: =SUM(H37:J37) -> 0 | L37: =IFERROR(K37/K$9,0) -> 0 | N37: 0 | O37: =IFERROR(N37/N$9,0) -> 0 | P37: =K37-N37 -> 0 | Q37: =IFERROR(K37/N37-1,"") | T37: 0 | U37: 0 | V37: 0 | W37: 0 | X37: 0 | Y37: =SUM(T37:X37) -> 0 | Z37: 0 | AA37: 0 | AB37: =SUM(Y37:AA37) -> 0 | AC37: =IFERROR(AB37/AB$9,0) -> 0 | AD37: =$K37-AB37 -> 0 | AE37: =IFERROR(K37/AB37-1,"") | AH37: (+/-) Non-recurring | AI37: 0 | AJ37: 0 | AK37: 0 | AL37: =SUM(AI37:AK37) -> 0 | AM37: 0 | AN37: 0 | AO37: =SUM(AL37:AN37) -> 0 | AP37: =IFERROR(AO37/AO$9,0) -> 0 | AR37: 0 | AS37: =IFERROR(AR37/AR$9,0) -> 0 | AT37: =AO37-AR37 -> 0 | AU37: =IFERROR(AO37/AR37-1,"") | AX37: -0.00013779 | AY37: 0 | AZ37: 0 | BA37: 0 | BB37: 0 | BC37: =SUM(AX37:BB37) -> -0.00013779 | BD37: 0 | BE37: 0 | BF37: =SUM(BC37:BE37) -> -0.00013779 | BG37: =IFERROR(BF37/BF$9,0) -> -2.9853361e-07 | BH37: =$AO37-BF37 -> 0.00013779 | BI37: =IFERROR(AO37/BF37-1,"") -> -1
C38: = Net Income | E38: =SUM(E26,E28:E29,E30,E34:E35,E37) -> 18.768378 | F38: =SUM(F26,F28:F29,F30,F34:F35,F37) -> 0 | G38: =SUM(G26,G28:G29,G30,G34:G35,G37) -> 0 | H38: =SUM(H26,H28:H29,H30,H34:H35,H37) -> 18.768378 | I38: =SUM(I26,I28:I29,I30,I34:I35,I37) -> 0 | J38: =SUM(J26,J28:J29,J30,J34:J35,J37) -> 2.3283064e-16 | K38: =SUM(K26,K28:K29,K30,K34:K35,K37) -> 18.768378 | L38: =IFERROR(K38/K$9,0) -> 0.16501897 | N38: =N36+N37+N25 -> 8.8963798 | O38: =IFERROR(N38/N$9,0) -> 0.078679749 | P38: =K38-N38 -> 9.871998 | Q38: =IFERROR(K38/N38-1,"") -> 1.1096646 | R38: =IF(Q38>0.05,1,IF(Q38<-0.05,-1,0)) -> 1 | T38: =SUM(T26,T28:T29,T30,T34:T35,T37) -> -2.2888174 | U38: =SUM(U26,U28:U29,U30,U34:U35,U37) -> 0 | V38: =SUM(V26,V28:V29,V30,V34:V35,V37) -> 0 | W38: =SUM(W26,W28:W29,W30,W34:W35,W37) -> 0 | X38: =SUM(X26,X28:X29,X30,X34:X35,X37) -> 0 | Y38: =SUM(T38:X38) -> -2.2888174 | Z38: =SUM(Z26,Z28:Z29,Z30,Z34:Z35,Z37) -> 0 | AA38: =SUM(AA26,AA28:AA29,AA30,AA34:AA35,AA37) -> 0 | AB38: =SUM(AB26,AB28:AB29,AB30,AB34:AB35,AB37) -> -2.2888174 | AC38: =IFERROR(AB38/AB$9,0) -> -0.024045851 | AD38: =$K38-AB38 -> 21.057195 | AE38: =IFERROR(K38/AB38-1,"") -> -9.2000329 | AF38: =IF(AE38>0.05,1,IF(AE38<-0.05,-1,0)) -> -1 | AH38: = Net Income | AI38: =SUM(AI26,AI28:AI29,AI30,AI34:AI35,AI37) -> 49.724225 | AJ38: =SUM(AJ26,AJ28:AJ29,AJ30,AJ34:AJ35,AJ37) -> 0 | AK38: =SUM(AK26,AK28:AK29,AK30,AK34:AK35,AK37) -> 0 | AL38: =SUM(AL26,AL28:AL29,AL30,AL34:AL35,AL37) -> 49.724225 | AM38: =SUM(AM26,AM28:AM29,AM30,AM34:AM35,AM37) -> 0 | AN38: =SUM(AN26,AN28:AN29,AN30,AN34:AN35,AN37) -> 3.4924597e-16 | AO38: =SUM(AO26,AO28:AO29,AO30,AO34:AO35,AO37) -> 49.724225 | AP38: =IFERROR(AO38/AO$9,0) -> 0.091494507 | AR38: =AR36+AR37+AR25 -> 36.406461 | AS38: =IFERROR(AR38/AR$9,0) -> 0.067208316 | AT38: =AO38-AR38 -> 13.317764 | AU38: =IFERROR(AO38/AR38-1,"") -> 0.36580772 | AV38: =IF(AU38>0.05,1,IF(AU38<-0.05,-1,0)) -> 1 | AX38: =SUM(AX26,AX28:AX29,AX30,AX34:AX35,AX37) -> 25.495912 | AY38: =SUM(AY26,AY28:AY29,AY30,AY34:AY35,AY37) -> 0 | AZ38: =SUM(AZ26,AZ28:AZ29,AZ30,AZ34:AZ35,AZ37) -> 1.4210855e-14 | BA38: =SUM(BA26,BA28:BA29,BA30,BA34:BA35,BA37) -> 0 | BB38: =SUM(BB26,BB28:BB29,BB30,BB34:BB35,BB37) -> 0 | BC38: =SUM(AX38:BB38) -> 25.495912 | BD38: =SUM(BD26,BD28:BD29,BD30,BD34:BD35,BD37) -> 0 | BE38: =SUM(BE26,BE28:BE29,BE30,BE34:BE35,BE37) -> 0 | BF38: =SUM(BF26,BF28:BF29,BF30,BF34:BF35,BF37) -> 25.495912 | BG38: =IFERROR(BF38/BF$9,0) -> 0.055239036 | BH38: =$AO38-BF38 -> 24.228313 | BI38: =IFERROR(AO38/BF38-1,"") -> 0.95028225 | BJ38: =IF(BI38>0.05,1,IF(BI38<-0.05,-1,0)) -> 1
C40: R&D + Capex | E40: =E16+E41 -> -23.65411 | F40: 0 | G40: 0 | H40: =SUM(E40:G40) -> -23.65411 | I40: 0 | J40: 0 | K40: =K16+K41 -> -24.179889 | L40: =IFERROR(K40/K$9,0) -> -0.2125991 | N40: =N16+N41 -> -27.223851 | O40: =IFERROR(N40/N$9,0) -> -0.24076824 | P40: =K40-N40 -> 3.0439621 | Q40: =IFERROR(K40/N40-1,"") -> -0.11181233 | T40: =T16+T41 -> -18.441405 | U40: 0 | V40: 0 | W40: 0 | X40: 0 | Y40: =SUM(T40:X40) -> -18.441405 | Z40: 0 | AA40: 0 | AB40: =AB16+AB41 -> -18.866989 | AC40: =IFERROR(AB40/AB$9,0) -> -0.19821276 | AD40: =$K40-AB40 -> -5.3128992 | AE40: =IFERROR(K40/AB40-1,"") -> 0.28159762 | AH40: R&D + Capex | AI40: =AI16+AI41 -> -113.81438 | AJ40: 0 | AK40: 0 | AL40: =SUM(AI40:AK40) -> -113.81438 | AM40: 0 | AN40: 0 | AO40: =AO16+AO41 -> -117.23568 | AP40: =IFERROR(AO40/AO$9,0) -> -0.2157182 | AR40: =AR41+AR16 -> -131.47638 | AS40: =IFERROR(AR40/AR$9,0) -> -0.24271258 | AT40: =AO40-AR40 -> 14.2407 | AU40: =IFERROR(AO40/AR40-1,"") -> -0.10831375 | AX40: =AX16+AX41 -> -91.103219 | AY40: 0 | AZ40: 0 | BA40: 0 | BB40: 0 | BC40: =SUM(AX40:BB40) -> -91.103219 | BD40: 0 | BE40: 0 | BF40: =SUM(BC40:BE40) -> -91.103219 | BG40: =IFERROR(BF40/BF$9,0) -> -0.19738278 | BH40: =$AO40-BF40 -> -26.132459 | BI40: =IFERROR(AO40/BF40-1,"") -> 0.28684452
B41: Capex | C41: (-) Capex | E41: ='Painel Resultado (MTD)'!AO11 -> -12.111835 | F41: 0 | G41: 0 | H41: =SUM(E41:G41) -> -12.111835 | I41: 0 | J41: 0 | K41: =SUM(H41:J41) -> -12.111835 | L41: =IFERROR(K41/K$9,0) -> -0.10649203 | N41: =N46 -> -9.6110155 | O41: =IFERROR(N41/N$9,0) -> -0.085 | P41: =K41-N41 -> -2.5008199 | Q41: =IFERROR(K41/N41-1,"") -> 0.2602035 | T41: ='Painel Resultado (MTD)'!BC11 -> -3.8148089 | U41: 0 | V41: 0 | W41: 0 | X41: 0 | Y41: =SUM(T41:X41) -> -3.8148089 | Z41: 0 | AA41: 0 | AB41: =SUM(Y41:AA41) -> -3.8148089 | AC41: =IFERROR(AB41/AB$9,0) -> -0.040077608 | AD41: =$K41-AB41 -> -8.2970264 | AE41: =IFERROR(K41/AB41-1,"") -> 2.1749521 | AH41: (-) Capex | AI41: ='Painel Resultado (YTD)'!AO11 -> -32.028326 | AJ41: 0 | AK41: 0 | AL41: =SUM(AI41:AK41) -> -32.028326 | AM41: 0 | AN41: 0 | AO41: =SUM(AL41:AN41) -> -32.028326 | AP41: =IFERROR(AO41/AO$9,0) -> -0.058933365 | AR41: =AR46 -> -46.044141 | AS41: =IFERROR(AR41/AR$9,0) -> -0.085 | AT41: =AO41-AR41 -> 14.015814 | AU41: =IFERROR(AO41/AR41-1,"") -> -0.30439952 | AX41: ='Painel Resultado (YTD)'!BC11 -> -16.892246 | AY41: 0 | AZ41: 0 | BA41: 0 | BB41: 0 | BC41: =SUM(AX41:BB41) -> -16.892246 | BD41: 0 | BE41: 0 | BF41: =SUM(BC41:BE41) -> -16.892246 | BG41: =IFERROR(BF41/BF$9,0) -> -0.03659847 | BH41: =$AO41-BF41 -> -15.13608 | BI41: =IFERROR(AO41/BF41-1,"") -> 0.89603718
C42: = Adjusted EBITDA After Capex | E42: =SUM(E19,E41) -> 22.357251 | F42: =SUM(F19,F41) -> -0.4807693 | G42: =SUM(G19,G41) -> 0 | H42: =SUM(E42:G42) -> 21.876481 | I42: =SUM(I19,I41) -> 0.086875 | J42: =SUM(J19,J41) -> 2.3283064e-16 | K42: =K19+K41 -> 21.963356 | L42: =IFERROR(K42/K$9,0) -> 0.19311048 | N42: =N19+N41 -> 17.160363 | O42: =IFERROR(N42/N$9,0) -> 0.15176657 | P42: =K42-N42 -> 4.802994 | Q42: =IFERROR(K42/N42-1,"") -> 0.27988884 | R42: =IF(Q42>0.05,1,IF(Q42<-0.05,-1,0)) -> 1 | T42: =SUM(T19,T41) -> 19.007756 | U42: =SUM(U19,U41) -> -0.12618796 | V42: =SUM(V19,V41) -> 0 | W42: =SUM(W19,W41) -> 0 | X42: =SUM(X19,X41) -> 0 | Y42: =SUM(T42:X42) -> 18.881568 | Z42: =SUM(Z19,Z41) -> 0.02257201 | AA42: =SUM(AA19,AA41) -> 0 | AB42: =AB19+AB41 -> 18.90414 | AC42: =IFERROR(AB42/AB$9,0) -> 0.19860306 | AD42: =$K42-AB42 -> 3.0592164 | AE42: =IFERROR(K42/AB42-1,"") -> 0.16182785 | AF42: =IF(AE42>0.05,1,IF(AE42<-0.05,-1,0)) -> 1 | AH42: = Adjusted EBITDA After Capex | AI42: =SUM(AI19,AI41) -> 94.671204 | AJ42: =SUM(AJ19,AJ41) -> 0.5436477 | AK42: =SUM(AK19,AK41) -> 0 | AL42: =SUM(AI42:AK42) -> 95.214852 | AM42: =SUM(AM19,AM41) -> 0.621875 | AN42: =SUM(AN19,AN41) -> 3.4924597e-16 | AO42: =AO19+AO41 -> 95.836727 | AP42: =IFERROR(AO42/AO$9,0) -> 0.1763433 | AR42: =AR19+AR41 -> 80.600123 | AS42: =IFERROR(AR42/AR$9,0) -> 0.14879223 | AT42: =AO42-AR42 -> 15.236604 | AU42: =IFERROR(AO42/AR42-1,"") -> 0.18903946 | AV42: =IF(AU42>0.05,1,IF(AU42<-0.05,-1,0)) -> 1 | AX42: =SUM(AX19,AX41) -> 88.73467 | AY42: =SUM(AY19,AY41) -> -5.8884285 | AZ42: =SUM(AZ19,AZ41) -> 1.4210855e-14 | BA42: =SUM(BA19,BA41) -> 0 | BB42: =SUM(BB19,BB41) -> 0 | BC42: =SUM(AX42:BB42) -> 82.846241 | BD42: =SUM(BD19,BD41) -> -0.55265431 | BE42: =SUM(BE19,BE41) -> 0 | BF42: =BF19+BF41 -> 82.293587 | BG42: =IFERROR(BF42/BF$9,0) -> 0.17829597 | BH42: =$AO42-BF42 -> 13.54314 | BI42: =IFERROR(AO42/BF42-1,"") -> 0.16457102 | BJ42: =IF(BI42>0.05,1,IF(BI42<-0.05,-1,0)) -> 1
Q43: =IFERROR(K43/N43-1,"") | AU43: =IFERROR(AO43/AR43-1,"")
C45: BGT
C46: Capex Target | N46: =O46*N9 -> -9.6110155 | O46: -0.085 | AR46: =AS46*AR9 -> -46.044141 | AS46: -0.085
C47: Ajuste Ativacao | N47: =N46-N48 -> -9.151419 | O47: =N47/N9 -> -0.080935321 | AR47: =AR46-AR48 -> -43.559139 | AS47: =AR47/AR9 -> -0.080412551
C48: Capex s/Ativação | N48: -0.45959642 | O48: =N48/N10 -> 0.012010804 | AR48: -2.4850015 | AS48: =AR48/AR10 -> 0.013582493
L49: =L11/AC11-1 -> -0.0052960732

Sheet P&L Contábil (2)
C2: 1000000 | E2: Actual | F2: Actual | G2: Actual | I2: Actual | J2: Actual | T2: Actual | U2: Actual | V2: Actual | W2: Actual | X2: Actual | Z2: Actual | AA2: Actual | AI2: Actual | AJ2: Actual | AK2: Actual | AM2: Actual | AN2: Actual | AX2: Actual | AY2: Actual | AZ2: Actual | BA2: Actual | BB2: Actual | BD2: Actual | BE2: Actual
C3: 46143 | E3: MTD | K3: MTD | AH3: =C3 -> 46143 | AI3: YTD | AO3: YTD
C5: [ BRL M ] | E5: Base | F5: Ajuste Entre Empresas/Corp | G5: Reclass | H5: Actual Contábil | I5: Ajuste Não Recorrente | J5: Baixa Receita (Outros Anos) | K5: Actual | L5: % NR | N5: Budget | O5: % NR | P5: ∆ | Q5: ∆% | T5: HistoricoOriginal | U5: Ajuste Entre Empresas/Corp | V5: Reclass | W5: Ajuste Cloud | X5: Eliminacao Intercompany | Y5: Last Year Contábil | Z5: Ajuste Não Recorrente | AA5: Baixa Receita (Outros Anos) | AB5: Last Year | AC5: % NR | AD5: ∆ | AE5: ∆% | AI5: Base | AJ5: Ajuste Entre Empresas/Corp | AK5: Reclass | AL5: Actual Contábil | AM5: Ajuste Não Recorrente | AN5: Baixa Receita (Outros Anos) | AO5: Actual | AP5: % NR | AR5: Budget | AS5: % NR | AT5: ∆ | AU5: ∆% | AX5: HistoricoOriginal | AY5: Ajuste Entre Empresas/Corp | AZ5: Reclass | BA5: Ajuste Cloud | BB5: Eliminacao Intercompany | BC5: Last Year Contábil | BD5: Ajuste Não Recorrente | BE5: Baixa Receita (Outros Anos) | BF5: Last Year | BG5: % NR | BH5: ∆ | BI5: ∆%
B7: Gross Revenue | C7: Gross Revenue | E7: 124.22709 | F7: 0 | G7: 0 | H7: =SUM(E7:G7) -> 124.22709 | I7: 0 | J7: 2.3283064e-16 | K7: =SUM(H7:J7) -> 124.22709 | T7: 105.26204 | U7: 0 | V7: 0 | W7: 0 | X7: -1.2994338 | Y7: =SUM(T7:X7) -> 103.96261 | Z7: 0 | AA7: 0 | AB7: =SUM(Y7:AA7) -> 103.96261 | AH7: Gross Revenue | AI7: 590.92391 | AJ7: 0 | AK7: 0 | AL7: =SUM(AI7:AK7) -> 590.92391 | AM7: 0 | AN7: 3.4924597e-16 | AO7: =SUM(AL7:AN7) -> 590.92391 | AX7: 508.29344 | AY7: 0 | AZ7: 0 | BA7: 0 | BB7: -5.0745383 | BC7: =SUM(AX7:BB7) -> 503.2189 | BD7: 0 | BE7: 0 | BF7: =SUM(BC7:BE7) -> 503.2189
B8: (-) Deductions | C8: (-) Deductions | E8: -10.49242 | F8: 0 | G8: 0 | H8: =SUM(E8:G8) -> -10.49242 | I8: 0 | J8: 0 | K8: =SUM(H8:J8) -> -10.49242 | T8: -8.7770624 | U8: 0 | V8: 0 | W8: 0 | X8: 0 | Y8: =SUM(T8:X8) -> -8.7770624 | Z8: 0 | AA8: 0 | AB8: =SUM(Y8:AA8) -> -8.7770624 | AH8: (-) Deductions | AI8: -47.457135 | AJ8: 0 | AK8: 0 | AL8: =SUM(AI8:AK8) -> -47.457135 | AM8: 0 | AN8: 0 | AO8: =SUM(AL8:AN8) -> -47.457135 | AX8: -41.66283 | AY8: 0 | AZ8: 0 | BA8: 0 | BB8: 0 | BC8: =SUM(AX8:BB8) -> -41.66283 | BD8: 0 | BE8: 0 | BF8: =SUM(BC8:BE8) -> -41.66283
B9: Net Revenue | C9: Net Revenue | E9: =SUM(E7:E8) -> 113.73467 | F9: =SUM(F7:F8) -> 0 | G9: =SUM(G7:G8) -> 0 | H9: =SUM(H7:H8) -> 113.73467 | I9: =SUM(I7:I8) -> 0 | J9: =SUM(J7:J8) -> 2.3283064e-16 | K9: =SUM(K7:K8) -> 113.73467 | L9: =IFERROR(K9/K$9,0) -> 1 | N9: 113.07077 | O9: =IFERROR(N9/N$9,0) -> 1 | P9: =K9-N9 -> 0.66389816 | Q9: =IFERROR(K9/N9-1,"") -> 0.0058715277 | R9: =IF(Q9>0.05,1,IF(Q9<-0.05,-1,0)) -> 0 | T9: =SUM(T7:T8) -> 96.484978 | U9: =SUM(U7:U8) -> 0 | V9: =SUM(V7:V8) -> 0 | W9: =SUM(W7:W8) -> 0 | X9: =SUM(X7:X8) -> -1.2994338 | Y9: =SUM(T9:X9) -> 95.185544 | Z9: =SUM(Z7:Z8) -> 0 | AA9: =SUM(AA7:AA8) -> 0 | AB9: =SUM(AB7:AB8) -> 95.185544 | AC9: =IFERROR(AB9/AB$9,0) -> 1 | AD9: =$K9-AB9 -> 18.549124 | AE9: =IFERROR(K9/AB9-1,"") -> 0.19487333 | AF9: =IF(AE9>0.05,1,IF(AE9<-0.05,-1,0)) -> 1 | AH9: Net Revenue | AI9: =SUM(AI7:AI8) -> 543.46678 | AJ9: =SUM(AJ7:AJ8) -> 0 | AK9: =SUM(AK7:AK8) -> 0 | AL9: =SUM(AL7:AL8) -> 543.46678 | AM9: =SUM(AM7:AM8) -> 0 | AN9: =SUM(AN7:AN8) -> 3.4924597e-16 | AO9: =SUM(AO7:AO8) -> 543.46678 | AP9: =IFERROR(AO9/AO$9,0) -> 1 | AR9: 541.69577 | AS9: =IFERROR(AR9/AR$9,0) -> 1 | AT9: =AO9-AR9 -> 1.7710076 | AU9: =IFERROR(AO9/AR9-1,"") -> 0.0032693768 | AV9: =IF(AU9>0.05,1,IF(AU9<-0.05,-1,0)) -> 0 | AX9: =SUM(AX7:AX8) -> 466.63061 | AY9: =SUM(AY7:AY8) -> 0 | AZ9: =SUM(AZ7:AZ8) -> 0 | BA9: =SUM(BA7:BA8) -> 0 | BB9: =SUM(BB7:BB8) -> -5.0745383 | BC9: =SUM(AX9:BB9) -> 461.55607 | BD9: =SUM(BD7:BD8) -> 0 | BE9: =SUM(BE7:BE8) -> 0 | BF9: =SUM(BF7:BF8) -> 461.55607 | BG9: =IFERROR(BF9/BF$9,0) -> 1 | BH9: =$AO9-BF9 -> 81.91071 | BI9: =IFERROR(AO9/BF9-1,"") -> 0.17746644 | BJ9: =IF(BI9>0.05,1,IF(BI9<-0.05,-1,0)) -> 1
B10: (-) CoGS | C10: (-) COGS | E10: -38.090191 | F10: 0 | G10: 1.218627 | H10: =SUM(E10:G10) -> -36.871564 | I10: 0 | J10: 0 | K10: =SUM(H10:J10) -> -36.871564 | L10: =IFERROR(K10/K$9,0) -> -0.32418931 | N10: -38.26525 | O10: =IFERROR(N10/N$9,0) -> -0.33841858 | P10: =K10-N10 -> 1.3936862 | Q10: =IFERROR(K10/N10-1,"") -> -0.036421719 | T10: -33.679461 | U10: 0 | V10: 1.8643879 | W10: 0 | X10: 1.2994338 | Y10: =SUM(T10:X10) -> -30.515639 | Z10: 0 | AA10: 0 | AB10: =SUM(Y10:AA10) -> -30.515639 | AC10: =IFERROR(AB10/AB$9,0) -> -0.32059111 | AD10: =$K10-AB10 -> -6.3559243 | AE10: =IFERROR(K10/AB10-1,"") -> 0.20828416 | AH10: (-) COGS | AI10: -185.92999 | AJ10: 0 | AK10: 4.1597062 | AL10: =SUM(AI10:AK10) -> -181.77028 | AM10: 0 | AN10: 0 | AO10: =SUM(AL10:AN10) -> -181.77028 | AP10: =IFERROR(AO10/AO$9,0) -> -0.33446438 | AR10: -182.95622 | AS10: =IFERROR(AR10/AR$9,0) -> -0.33774718 | AT10: =AO10-AR10 -> 1.1859369 | AU10: =IFERROR(AO10/AR10-1,"") -> -0.0064820802 | AX10: -170.5028 | AY10: 0 | AZ10: 9.6893798 | BA10: -0.26966966 | BB10: 5.0745383 | BC10: =SUM(AX10:BB10) -> -156.00855 | BD10: 0 | BE10: 0 | BF10: =SUM(BC10:BE10) -> -156.00855 | BG10: =IFERROR(BF10/BF$9,0) -> -0.33800564 | BH10: =$AO10-BF10 -> -25.761729 | BI10: =IFERROR(AO10/BF10-1,"") -> 0.16513024
C11: = Gross Margin | E11: =SUM(E9:E10) -> 75.644477 | F11: =SUM(F9:F10) -> 0 | G11: =SUM(G9:G10) -> 1.218627 | H11: =SUM(H9:H10) -> 76.863104 | I11: =SUM(I9:I10) -> 0 | J11: =SUM(J9:J10) -> 2.3283064e-16 | K11: =SUM(K9:K10) -> 76.863104 | L11: =IFERROR(K11/K$9,0) -> 0.67581069 | N11: =N9+N10 -> 74.80552 | O11: =IFERROR(N11/N$9,0) -> 0.66158142 | P11: =K11-N11 -> 2.0575843 | Q11: =IFERROR(K11/N11-1,"") -> 0.027505782 | R11: =IF(Q11>0.05,1,IF(Q11<-0.05,-1,0)) -> 0 | T11: =SUM(T9:T10) -> 62.805517 | U11: =SUM(U9:U10) -> 0 | V11: =SUM(V9:V10) -> 1.8643879 | W11: =SUM(W9:W10) -> 0 | X11: =SUM(X9:X10) -> 0 | Y11: =SUM(Y9:Y10) -> 64.669905 | Z11: =SUM(Z9:Z10) -> 0 | AA11: =SUM(AA9:AA10) -> 0 | AB11: =SUM(AB9:AB10) -> 64.669905 | AC11: =IFERROR(AB11/AB$9,0) -> 0.67940889 | AD11: =$K11-AB11 -> 12.1932 | AE11: =IFERROR(K11/AB11-1,"") -> 0.1885452 | AF11: =IF(AE11>0.05,1,IF(AE11<-0.05,-1,0)) -> 1 | AH11: = Gross Margin | AI11: =SUM(AI9:AI10) -> 357.53679 | AJ11: =SUM(AJ9:AJ10) -> 0 | AK11: =SUM(AK9:AK10) -> 4.1597062 | AL11: =SUM(AL9:AL10) -> 361.6965 | AM11: =SUM(AM9:AM10) -> 0 | AN11: =SUM(AN9:AN10) -> 3.4924597e-16 | AO11: =SUM(AO9:AO10) -> 361.6965 | AP11: =IFERROR(AO11/AO$9,0) -> 0.66553562 | AR11: =AR9+AR10 -> 358.73955 | AS11: =IFERROR(AR11/AR$9,0) -> 0.66225282 | AT11: =AO11-AR11 -> 2.9569445 | AU11: =IFERROR(AO11/AR11-1,"") -> 0.008242594 | AV11: =IF(AU11>0.05,1,IF(AU11<-0.05,-1,0)) -> 0 | AX11: =SUM(AX9:AX10) -> 296.12781 | AY11: =SUM(AY9:AY10) -> 0 | AZ11: =SUM(AZ9:AZ10) -> 9.6893798 | BA11: =SUM(BA9:BA10) -> -0.26966966 | BB11: =SUM(BB9:BB10) -> 0 | BC11: =SUM(BC9:BC10) -> 305.54752 | BD11: =SUM(BD9:BD10) -> 0 | BE11: =SUM(BE9:BE10) -> 0 | BF11: =SUM(BF9:BF10) -> 305.54752 | BG11: =IFERROR(BF11/BF$9,0) -> 0.66199436 | BH11: =$AO11-BF11 -> 56.148981 | BI11: =IFERROR(AO11/BF11-1,"") -> 0.18376514 | BJ11: =IF(BI11>0.05,1,IF(BI11<-0.05,-1,0)) -> 1
C13: (-) Expenses | E13: =SUM(E14:E18) -> -41.175391 | F13: =SUM(F14:F18) -> -0.4807693 | G13: =SUM(G14:G18) -> -1.218627 | H13: =SUM(H14:H18) -> -42.874788 | I13: =SUM(I14:I18) -> 0.086875 | J13: =SUM(J14:J18) -> 0 | K13: =SUM(K14:K18) -> -42.787913 | L13: =IFERROR(K13/K$9,0) -> -0.37620818 | N13: =SUM(N14:N18) -> -48.034142 | O13: =IFERROR(N13/N$9,0) -> -0.42481485 | P13: =K13-N13 -> 5.2462295 | Q13: =IFERROR(K13/N13-1,"") -> -0.10921876 | T13: =SUM(T14:T18) -> -39.982952 | U13: =SUM(U14:U18) -> -0.12618796 | V13: =SUM(V14:V18) -> -1.8643879 | W13: =SUM(W14:W18) -> 0 | X13: =SUM(X14:X18) -> 0 | Y13: =SUM(Y14:Y18) -> -41.973528 | Z13: =SUM(Z14:Z18) -> 0.02257201 | AA13: =SUM(AA14:AA18) -> 0 | AB13: =SUM(AB14:AB18) -> -41.950956 | AC13: =IFERROR(AB13/AB$9,0) -> -0.44072822 | AD13: =$K13-AB13 -> -0.83695696 | AE13: =IFERROR(K13/AB13-1,"") -> 0.019950844 | AH13: (-) Expenses | AI13: =SUM(AI14:AI18) -> -230.83726 | AJ13: =SUM(AJ14:AJ18) -> 0.5436477 | AK13: =SUM(AK14:AK18) -> -4.1597062 | AL13: =SUM(AL14:AL18) -> -234.45332 | AM13: =SUM(AM14:AM18) -> 0.621875 | AN13: =SUM(AN14:AN18) -> 0 | AO13: =SUM(AO14:AO18) -> -233.83144 | AP13: =IFERROR(AO13/AO$9,0) -> -0.43025895 | AR13: =SUM(AR14:AR18) -> -232.09529 | AS13: =IFERROR(AR13/AR$9,0) -> -0.42846059 | AT13: =AO13-AR13 -> -1.7361551 | AU13: =IFERROR(AO13/AR13-1,"") -> 0.0074803546 | AX13: =SUM(AX14:AX18) -> -190.50089 | AY13: =SUM(AY14:AY18) -> -5.8884285 | AZ13: =SUM(AZ14:AZ18) -> -9.6893798 | BA13: =SUM(BA14:BA18) -> 0.26966966 | BB13: =SUM(BB14:BB18) -> 0 | BC13: =SUM(BC14:BC18) -> -205.80903 | BD13: =SUM(BD14:BD18) -> -0.55265431 | BE13: =SUM(BE14:BE18) -> 0 | BF13: =SUM(BF14:BF18) -> -206.36168 | BG13: =IFERROR(BF13/BF$9,0) -> -0.44709992 | BH13: =$AO13-BF13 -> -27.469761 | BI13: =IFERROR(AO13/BF13-1,"") -> 0.13311464
B14: (-) General & Administrative | C14: (-) General & Administrative | E14: -14.739142 | F14: -0.4652693 | G14: 2.2207367 | H14: =SUM(E14:G14) -> -12.983674 | I14: 0.086875 | J14: 0 | K14: =SUM(H14:J14) -> -12.896799 | L14: =IFERROR(K14/K$9,0) -> -0.11339374 | N14: -13.844132 | O14: =IFERROR(N14/N$9,0) -> -0.12243776 | P14: =K14-N14 -> 0.94733285 | Q14: =IFERROR(K14/N14-1,"") -> -0.068428475 | T14: -13.508229 | U14: -0.12618796 | V14: 1.063755 | W14: 0 | X14: 0 | Y14: =SUM(T14:X14) -> -12.570662 | Z14: 0.054844 | AA14: 0 | AB14: =SUM(Y14:AA14) -> -12.515818 | AC14: =IFERROR(AB14/AB$9,0) -> -0.13148864 | AD14: =$K14-AB14 -> -0.38098131 | AE14: =IFERROR(K14/AB14-1,"") -> 0.030439985 | AH14: (-) General & Administrative | AI14: -78.343974 | AJ14: 1.0550477 | AK14: 8.5753587 | AL14: =SUM(AI14:AK14) -> -68.713568 | AM14: 0.621875 | AN14: 0 | AO14: =SUM(AL14:AN14) -> -68.091693 | AP14: =IFERROR(AO14/AO$9,0) -> -0.12529136 | AR14: -67.681669 | AS14: =IFERROR(AR14/AR$9,0) -> -0.12494406 | AT14: =AO14-AR14 -> -0.41002424 | AU14: =IFERROR(AO14/AR14-1,"") -> 0.0060581284 | AX14: -64.069855 | AY14: -5.205088 | AZ14: 5.4171676 | BA14: 0 | BB14: 0 | BC14: =SUM(AX14:BB14) -> -63.857775 | BD14: 0.69235842 | BE14: 0 | BF14: =SUM(BC14:BE14) -> -63.165417 | BG14: =IFERROR(BF14/BF$9,0) -> -0.13685318 | BH14: =$AO14-BF14 -> -4.9262762 | BI14: =IFERROR(AO14/BF14-1,"") -> 0.077990084
B15: (-) Sales & Marketing | C15: (-) Sales & Marketing | E15: -13.184666 | F15: 0 | G15: -1.9152109 | H15: =SUM(E15:G15) -> -15.099876 | I15: 0 | J15: 0 | K15: =SUM(H15:J15) -> -15.099876 | L15: =IFERROR(K15/K$9,0) -> -0.13276406 | N15: -16.048389 | O15: =IFERROR(N15/N$9,0) -> -0.14193225 | P15: =K15-N15 -> 0.94851263 | Q15: =IFERROR(K15/N15-1,"") -> -0.059103292 | T15: -11.484349 | U15: 0 | V15: -2.5025589 | W15: 0 | X15: 0 | Y15: =SUM(T15:X15) -> -13.986908 | Z15: 0 | AA15: 0 | AB15: =SUM(Y15:AA15) -> -13.986908 | AC15: =IFERROR(AB15/AB$9,0) -> -0.14694362 | AD15: =$K15-AB15 -> -1.1129682 | AE15: =IFERROR(K15/AB15-1,"") -> 0.079572135 | AH15: (-) Sales & Marketing | AI15: -65.675702 | AJ15: 0 | AK15: -8.8112953 | AL15: =SUM(AI15:AK15) -> -74.486997 | AM15: 0 | AN15: 0 | AO15: =SUM(AL15:AN15) -> -74.486997 | AP15: =IFERROR(AO15/AO$9,0) -> -0.13705897 | AR15: -76.373718 | AS15: =IFERROR(AR15/AR$9,0) -> -0.14099006 | AT15: =AO15-AR15 -> 1.8867208 | AU15: =IFERROR(AO15/AR15-1,"") -> -0.024703797 | AX15: -50.426443 | AY15: -0.503801 | AZ15: -14.989079 | BA15: 0 | BB15: 0 | BC15: =SUM(AX15:BB15) -> -65.919323 | BD15: 0.078306 | BE15: 0 | BF15: =SUM(BC15:BE15) -> -65.841017 | BG15: =IFERROR(BF15/BF$9,0) -> -0.14265009 | BH15: =$AO15-BF15 -> -8.6459801 | BI15: =IFERROR(AO15/BF15-1,"") -> 0.13131602 | BK15: =AO15-K15 -> -59.387121 | BL15: =BK15/4 -> -14.84678
B16: (-) Research & Development | C16: (-) Research & Development | E16: -11.542275 | F16: -0.0155 | G16: -0.51027857 | H16: =SUM(E16:G16) -> -12.068053 | I16: 0 | J16: 0 | K16: =SUM(H16:J16) -> -12.068053 | L16: =IFERROR(K16/K$9,0) -> -0.10610708 | N16: -17.612835 | O16: =IFERROR(N16/N$9,0) -> -0.15576824 | P16: =K16-N16 -> 5.544782 | Q16: =IFERROR(K16/N16-1,"") -> -0.31481485 | T16: -14.626596 | U16: 0 | V16: -0.42558405 | W16: 0 | X16: 0 | Y16: =SUM(T16:X16) -> -15.05218 | Z16: 0 | AA16: 0 | AB16: =SUM(Y16:AA16) -> -15.05218 | AC16: =IFERROR(AB16/AB$9,0) -> -0.15813515 | AD16: =$K16-AB16 -> 2.9841272 | AE16: =IFERROR(K16/AB16-1,"") -> -0.19825216 | AH16: (-) Research & Development | AI16: -81.786056 | AJ16: -0.5114 | AK16: -2.9098954 | AL16: =SUM(AI16:AK16) -> -85.207352 | AM16: 0 | AN16: 0 | AO16: =SUM(AL16:AN16) -> -85.207352 | AP16: =IFERROR(AO16/AO$9,0) -> -0.15678484 | AR16: -85.432237 | AS16: =IFERROR(AR16/AR$9,0) -> -0.15771258 | AT16: =AO16-AR16 -> 0.22488503 | AU16: =IFERROR(AO16/AR16-1,"") -> -0.0026323206 | AX16: -74.210973 | AY16: -0.1111111 | AZ16: -0.11746809 | BA16: 0.26966966 | BB16: 0 | BC16: =SUM(AX16:BB16) -> -74.169882 | BD16: 0 | BE16: 0 | BF16: =SUM(BC16:BE16) -> -74.169882 | BG16: =IFERROR(BF16/BF$9,0) -> -0.16069528 | BH16: =$AO16-BF16 -> -11.037469 | BI16: =IFERROR(AO16/BF16-1,"") -> 0.14881336
B17: Bad Debts Provision | C17: (-) Bad Debts Provision | E17: -1.7506317 | F17: 0 | G17: 0 | H17: =SUM(E17:G17) -> -1.7506317 | I17: 0 | J17: 0 | K17: =SUM(H17:J17) -> -1.7506317 | L17: =IFERROR(K17/K$9,0) -> -0.015392243 | N17: -0.52878581 | O17: =IFERROR(N17/N$9,0) -> -0.0046765916 | P17: =K17-N17 -> -1.2218459 | Q17: =IFERROR(K17/N17-1,"") -> 2.3106631 | T17: -0.40976279 | U17: 0 | V17: 0 | W17: 0 | X17: 0 | Y17: =SUM(T17:X17) -> -0.40976279 | Z17: 0 | AA17: 0 | AB17: =SUM(Y17:AA17) -> -0.40976279 | AC17: =IFERROR(AB17/AB$9,0) -> -0.0043048847 | AD17: =$K17-AB17 -> -1.3408689 | AE17: =IFERROR(K17/AB17-1,"") -> 3.2723051 | AH17: (-) Bad Debts Provision | AI17: -4.9908547 | AJ17: 0 | AK17: 0 | AL17: =SUM(AI17:AK17) -> -4.9908547 | AM17: 0 | AN17: 0 | AO17: =SUM(AL17:AN17) -> -4.9908547 | AP17: =IFERROR(AO17/AO$9,0) -> -0.0091833667 | AR17: -2.6076659 | AS17: =IFERROR(AR17/AR$9,0) -> -0.0048138938 | AT17: =AO17-AR17 -> -2.3831888 | AU17: =IFERROR(AO17/AR17-1,"") -> 0.91391644 | AX17: -3.145584 | AY17: 0 | AZ17: 0 | BA17: 0 | BB17: 0 | BC17: =SUM(AX17:BB17) -> -3.145584 | BD17: 0 | BE17: 0 | BF17: =SUM(BC17:BE17) -> -3.145584 | BG17: =IFERROR(BF17/BF$9,0) -> -0.0068151719 | BH17: =$AO17-BF17 -> -1.8452708 | BI17: =IFERROR(AO17/BF17-1,"") -> 0.58662263
B18: Others Income and Expense | C18: (+/-) Others Income & Exp. | E18: 0.04132218 | F18: 0 | G18: -1.0138743 | H18: =SUM(E18:G18) -> -0.97255208 | I18: 0 | J18: 0 | K18: =SUM(H18:J18) -> -0.97255208 | L18: =IFERROR(K18/K$9,0) -> -0.008551061 | N18: 0 | O18: =IFERROR(N18/N$9,0) -> 0 | P18: =K18-N18 -> -0.97255208 | Q18: =IFERROR(K18/N18-1,"") | T18: 0.04598573 | U18: 0 | V18: 0 | W18: 0 | X18: 0 | Y18: =SUM(T18:X18) -> 0.04598573 | Z18: -0.03227199 | AA18: 0 | AB18: =SUM(Y18:AA18) -> 0.01371374 | AC18: =IFERROR(AB18/AB$9,0) -> 0.00014407377 | AD18: =$K18-AB18 -> -0.98626582 | AE18: =IFERROR(K18/AB18-1,"") -> -71.918078 | AH18: (+/-) Others Income & Exp. | AI18: -0.04067367 | AJ18: 0 | AK18: -1.0138743 | AL18: =SUM(AI18:AK18) -> -1.0545479 | AM18: 0 | AN18: 0 | AO18: =SUM(AL18:AN18) -> -1.0545479 | AP18: =IFERROR(AO18/AO$9,0) -> -0.0019404092 | AR18: 0 | AS18: =IFERROR(AR18/AR$9,0) -> 0 | AT18: =AO18-AR18 -> -1.0545479 | AU18: =IFERROR(AO18/AR18-1,"") | AX18: 1.3519638 | AY18: -0.06842838 | AZ18: 0 | BA18: 0 | BB18: 0 | BC18: =SUM(AX18:BB18) -> 1.2835354 | BD18: -1.3233187 | BE18: 0 | BF18: =SUM(BC18:BE18) -> -0.03978333 | BG18: =IFERROR(BF18/BF$9,0) -> -8.6193927e-05 | BH18: =$AO18-BF18 -> -1.0147646 | BI18: =IFERROR(AO18/BF18-1,"") -> 25.507282
C19: = Adjusted EBITDA | E19: =SUM(E11,E13) -> 34.469086 | F19: =SUM(F11,F13) -> -0.4807693 | G19: =SUM(G11,G13) -> 0 | H19: =SUM(H11,H13) -> 33.988317 | I19: =SUM(I11,I13) -> 0.086875 | J19: =SUM(J11,J13) -> 2.3283064e-16 | K19: =SUM(K11,K13) -> 34.075192 | L19: =IFERROR(K19/K$9,0) -> 0.29960251 | N19: =N11+N13 -> 26.771378 | O19: =IFERROR(N19/N$9,0) -> 0.23676657 | P19: =K19-N19 -> 7.3038138 | Q19: =IFERROR(K19/N19-1,"") -> 0.27282174 | R19: =IF(Q19>0.05,1,IF(Q19<-0.05,-1,0)) -> 1 | T19: =SUM(T11,T13) -> 22.822565 | U19: =SUM(U11,U13) -> -0.12618796 | V19: =SUM(V11,V13) -> 0 | W19: =SUM(W11,W13) -> 0 | X19: =SUM(X11,X13) -> 0 | Y19: =SUM(Y11,Y13) -> 22.696377 | Z19: =SUM(Z11,Z13) -> 0.02257201 | AA19: =SUM(AA11,AA13) -> 0 | AB19: =SUM(AB11,AB13) -> 22.718949 | AC19: =IFERROR(AB19/AB$9,0) -> 0.23868066 | AD19: =$K19-AB19 -> 11.356243 | AE19: =IFERROR(K19/AB19-1,"") -> 0.49985776 | AF19: =IF(AE19>0.05,1,IF(AE19<-0.05,-1,0)) -> 1 | AH19: = Adjusted EBITDA | AI19: =SUM(AI11,AI13) -> 126.69953 | AJ19: =SUM(AJ11,AJ13) -> 0.5436477 | AK19: =SUM(AK11,AK13) -> 0 | AL19: =SUM(AL11,AL13) -> 127.24318 | AM19: =SUM(AM11,AM13) -> 0.621875 | AN19: =SUM(AN11,AN13) -> 3.4924597e-16 | AO19: =SUM(AO11,AO13) -> 127.86505 | AP19: =IFERROR(AO19/AO$9,0) -> 0.23527667 | AR19: =AR11+AR13 -> 126.64426 | AS19: =IFERROR(AR19/AR$9,0) -> 0.23379223 | AT19: =AO19-AR19 -> 1.2207894 | AU19: =IFERROR(AO19/AR19-1,"") -> 0.009639516 | AV19: =IF(AU19>0.05,1,IF(AU19<-0.05,-1,0)) -> 0 | AX19: =SUM(AX11,AX13) -> 105.62692 | AY19: =SUM(AY11,AY13) -> -5.8884285 | AZ19: =SUM(AZ11,AZ13) -> 1.4210855e-14 | BA19: =SUM(BA11,BA13) -> 0 | BB19: =SUM(BB11,BB13) -> 0 | BC19: =SUM(BC11,BC13) -> 99.738487 | BD19: =SUM(BD11,BD13) -> -0.55265431 | BE19: =SUM(BE11,BE13) -> 0 | BF19: =SUM(BF11,BF13) -> 99.185833 | BG19: =IFERROR(BF19/BF$9,0) -> 0.21489444 | BH19: =$AO19-BF19 -> 28.67922 | BI19: =IFERROR(AO19/BF19-1,"") -> 0.28914633 | BJ19: =IF(BI19>0.05,1,IF(BI19<-0.05,-1,0)) -> 1
B20: BU Allocation | C20: (+/-) BU Allocation | E20: 3.4911693 | F20: 0 | G20: 0 | H20: =SUM(E20:G20) -> 3.4911693 | I20: 0 | J20: 0 | K20: =SUM(H20:J20) -> 3.4911693 | L20: =IFERROR(K20/K$9,0) -> 0.030695736 | N20: 0 | O20: =IFERROR(N20/N$9,0) -> 0 | P20: =K20-N20 -> 3.4911693 | Q20: =IFERROR(K20/N20-1,"") | T20: 0.41767093 | U20: 0 | V20: 0 | W20: 0 | X20: 0 | Y20: =SUM(T20:X20) -> 0.41767093 | Z20: 0 | AA20: 0 | AB20: =SUM(Y20:AA20) -> 0.41767093 | AC20: =IFERROR(AB20/AB$9,0) -> 0.0043879659 | AD20: =$K20-AB20 -> 3.0734984 | AE20: =IFERROR(K20/AB20-1,"") -> 7.3586602 | AH20: (+/-) BU Allocation | AI20: 16.979846 | AJ20: 0 | AK20: 0 | AL20: =SUM(AI20:AK20) -> 16.979846 | AM20: 0 | AN20: 0 | AO20: =SUM(AL20:AN20) -> 16.979846 | AP20: =IFERROR(AO20/AO$9,0) -> 0.031243576 | AR20: 0 | AS20: =IFERROR(AR20/AR$9,0) -> 0 | AT20: =AO20-AR20 -> 16.979846 | AU20: =IFERROR(AO20/AR20-1,"") | AX20: -0.88102105 | AY20: 0 | AZ20: 0 | BA20: 0 | BB20: 0 | BC20: =SUM(AX20:BB20) -> -0.88102105 | BD20: 0 | BE20: 0 | BF20: =SUM(BC20:BE20) -> -0.88102105 | BG20: =IFERROR(BF20/BF$9,0) -> -0.0019088061 | BH20: =$AO20-BF20 -> 17.860867 | BI20: =IFERROR(AO20/BF20-1,"") -> -20.272917
B21: Holding - Cost Sharing | C21: (-) Holding - Cost Sharing | E21: -6.1596697 | F21: 0 | G21: 0 | H21: =SUM(E21:G21) -> -6.1596697 | I21: 0 | J21: 0 | K21: =SUM(H21:J21) -> -6.1596697 | L21: =IFERROR(K21/K$9,0) -> -0.054158242 | N21: 0 | O21: =IFERROR(N21/N$9,0) -> 0 | P21: =K21-N21 -> -6.1596697 | Q21: =IFERROR(K21/N21-1,"") | T21: -0.67363035 | U21: 0 | V21: 0 | W21: 0 | X21: 0 | Y21: =SUM(T21:X21) -> -0.67363035 | Z21: 0 | AA21: 0 | AB21: =SUM(Y21:AA21) -> -0.67363035 | AC21: =IFERROR(AB21/AB$9,0) -> -0.0070770237 | AD21: =$K21-AB21 -> -5.4860393 | AE21: =IFERROR(K21/AB21-1,"") -> 8.1439907 | AH21: (-) Holding - Cost Sharing | AI21: -37.973932 | AJ21: 7.2759576e-18 | AK21: 0 | AL21: =SUM(AI21:AK21) -> -37.973932 | AM21: 0 | AN21: 0 | AO21: =SUM(AL21:AN21) -> -37.973932 | AP21: =IFERROR(AO21/AO$9,0) -> -0.069873511 | AR21: 0 | AS21: =IFERROR(AR21/AR$9,0) -> 0 | AT21: =AO21-AR21 -> -37.973932 | AU21: =IFERROR(AO21/AR21-1,"") | AX21: -2.314233 | AY21: 0 | AZ21: 0 | BA21: 0 | BB21: 0 | BC21: =SUM(AX21:BB21) -> -2.314233 | BD21: 0 | BE21: 0 | BF21: =SUM(BC21:BE21) -> -2.314233 | BG21: =IFERROR(BF21/BF$9,0) -> -0.0050139802 | BH21: =$AO21-BF21 -> -35.659699 | BI21: =IFERROR(AO21/BF21-1,"") -> 15.408863
B22: Shared Services | C22: (+/-) Shared Services | E22: 2.6647991 | F22: 0 | G22: 0 | H22: =SUM(E22:G22) -> 2.6647991 | I22: 0 | J22: 0 | K22: =SUM(H22:J22) -> 2.6647991 | L22: =IFERROR(K22/K$9,0) -> 0.023429963 | N22: 0 | O22: =IFERROR(N22/N$9,0) -> 0 | P22: =K22-N22 -> 2.6647991 | Q22: =IFERROR(K22/N22-1,"") | T22: 0.18852078 | U22: 0 | V22: 0 | W22: 0 | X22: 0 | Y22: =SUM(T22:X22) -> 0.18852078 | Z22: 0 | AA22: 0 | AB22: =SUM(Y22:AA22) -> 0.18852078 | AC22: =IFERROR(AB22/AB$9,0) -> 0.001980561 | AD22: =$K22-AB22 -> 2.4762783 | AE22: =IFERROR(K22/AB22-1,"") -> 13.135307 | AH22: (+/-) Shared Services | AI22: 20.976155 | AJ22: 0 | AK22: 0 | AL22: =SUM(AI22:AK22) -> 20.976155 | AM22: 0 | AN22: 0 | AO22: =SUM(AL22:AN22) -> 20.976155 | AP22: =IFERROR(AO22/AO$9,0) -> 0.038596941 | AR22: 0 | AS22: =IFERROR(AR22/AR$9,0) -> 0 | AT22: =AO22-AR22 -> 20.976155 | AU22: =IFERROR(AO22/AR22-1,"") | AX22: 3.1251551 | AY22: 0 | AZ22: 0 | BA22: 0 | BB22: 0 | BC22: =SUM(AX22:BB22) -> 3.1251551 | BD22: 0 | BE22: 0 | BF22: =SUM(BC22:BE22) -> 3.1251551 | BG22: =IFERROR(BF22/BF$9,0) -> 0.0067709111 | BH22: =$AO22-BF22 -> 17.851 | BI22: =IFERROR(AO22/BF22-1,"") -> 5.7120366
C24: Managerial EBITDA | E24: =SUM(E19:E22) -> 34.465385 | F24: =SUM(F19:F22) -> -0.4807693 | G24: =SUM(G19:G22) -> 0 | H24: =SUM(H19:H22) -> 33.984616 | I24: =SUM(I19:I22) -> 0.086875 | J24: =SUM(J19:J22) -> 2.3283064e-16 | K24: =SUM(K19:K22) -> 34.071491 | L24: =IFERROR(K24/K$9,0) -> 0.29956997 | N24: =N19+N20+N21+N22 -> 26.771378 | O24: =IFERROR(N24/N$9,0) -> 0.23676657 | P24: =K24-N24 -> 7.3001126 | Q24: =IFERROR(K24/N24-1,"") -> 0.27268348 | R24: =IF(Q24>0.05,1,IF(Q24<-0.05,-1,0)) -> 1 | T24: =SUM(T19:T22) -> 22.755126 | U24: =SUM(U19:U22) -> -0.12618796 | V24: =SUM(V19:V22) -> 0 | W24: =SUM(W19:W22) -> 0 | X24: =SUM(X19:X22) -> 0 | Y24: =SUM(Y19:Y22) -> 22.628938 | Z24: =SUM(Z19:Z22) -> 0.02257201 | AA24: =SUM(AA19:AA22) -> 0 | AB24: =SUM(AB19:AB22) -> 22.65151 | AC24: =IFERROR(AB24/AB$9,0) -> 0.23797217 | AD24: =$K24-AB24 -> 11.41998 | AE24: =IFERROR(K24/AB24-1,"") -> 0.50415977 | AF24: =IF(AE24>0.05,1,IF(AE24<-0.05,-1,0)) -> 1 | AH24: Managerial EBITDA | AI24: =SUM(AI19:AI22) -> 126.6816 | AJ24: =SUM(AJ19:AJ22) -> 0.5436477 | AK24: =SUM(AK19:AK22) -> 0 | AL24: =SUM(AL19:AL22) -> 127.22525 | AM24: =SUM(AM19:AM22) -> 0.621875 | AN24: =SUM(AN19:AN22) -> 3.4924597e-16 | AO24: =SUM(AO19:AO22) -> 127.84712 | AP24: =IFERROR(AO24/AO$9,0) -> 0.23524367 | AR24: =AR19+AR20+AR21+AR22 -> 126.64426 | AS24: =IFERROR(AR24/AR$9,0) -> 0.23379223 | AT24: =AO24-AR24 -> 1.2028584 | AU24: =IFERROR(AO24/AR24-1,"") -> 0.0094979306 | AV24: =IF(AU24>0.05,1,IF(AU24<-0.05,-1,0)) -> 0 | AX24: =SUM(AX19:AX22) -> 105.55682 | AY24: =SUM(AY19:AY22) -> -5.8884285 | AZ24: =SUM(AZ19:AZ22) -> 1.4210855e-14 | BA24: =SUM(BA19:BA22) -> 0 | BB24: =SUM(BB19:BB22) -> 0 | BC24: =SUM(BC19:BC22) -> 99.668388 | BD24: =SUM(BD19:BD22) -> -0.55265431 | BE24: =SUM(BE19:BE22) -> 0 | BF24: =SUM(BF19:BF22) -> 99.115734 | BG24: =IFERROR(BF24/BF$9,0) -> 0.21474256 | BH24: =$AO24-BF24 -> 28.731388 | BI24: =IFERROR(AO24/BF24-1,"") -> 0.28987717 | BJ24: =IF(BI24>0.05,1,IF(BI24<-0.05,-1,0)) -> 1
B25: Adjustments to EBITDA | C25: (+/-) Non-recurring | E25: -0.4807693 | F25: 0.4807693 | G25: 0 | H25: =SUM(E25:G25) -> 0 | I25: -0.086875 | J25: 0 | K25: =SUM(H25:J25) -> -0.086875 | L25: =IFERROR(K25/K$9,0) -> -0.00076383922 | N25: -0.088 | O25: =IFERROR(N25/N$9,0) -> -0.00077827364 | P25: =K25-N25 -> 0.001125 | Q25: =IFERROR(K25/N25-1,"") -> -0.012784091 | T25: -0.12618796 | U25: 0.12618796 | V25: 0 | W25: 0 | X25: 0 | Y25: =SUM(T25:X25) -> 0 | Z25: -0.02257201 | AA25: 0 | AB25: =SUM(Y25:AA25) -> -0.02257201 | AC25: =IFERROR(AB25/AB$9,0) -> -0.00023713695 | AD25: =$K25-AB25 -> -0.06430299 | AE25: =IFERROR(K25/AB25-1,"") -> 2.8487933 | AH25: (+/-) Non-recurring | AI25: 0.54338492 | AJ25: -0.5436477 | AK25: 0 | AL25: =SUM(AI25:AK25) -> -0.00026278 | AM25: -0.621875 | AN25: 0 | AO25: =SUM(AL25:AN25) -> -0.62213778 | AP25: =IFERROR(AO25/AO$9,0) -> -0.0011447577 | AR25: -0.69 | AS25: =IFERROR(AR25/AR$9,0) -> -0.0012737777 | AT25: =AO25-AR25 -> 0.06786222 | AU25: =IFERROR(AO25/AR25-1,"") -> -0.098351043 | AX25: -5.8884285 | AY25: 5.8884285 | AZ25: 0 | BA25: 0 | BB25: 0 | BC25: =SUM(AX25:BB25) -> 0 | BD25: 0.55265431 | BE25: 0 | BF25: =SUM(BC25:BE25) -> 0.55265431 | BG25: =IFERROR(BF25/BF$9,0) -> 0.001197372 | BH25: =$AO25-BF25 -> -1.1747921 | BI25: =IFERROR(AO25/BF25-1,"") -> -2.1257268
C26: = EBITDA | E26: =SUM(E24:E25) -> 33.984616 | F26: =SUM(F24:F25) -> 0 | G26: =SUM(G24:G25) -> 0 | H26: =SUM(H24:H25) -> 33.984616 | I26: =SUM(I24:I25) -> 0 | J26: =SUM(J24:J25) -> 2.3283064e-16 | K26: =SUM(K24:K25) -> 33.984616 | L26: =IFERROR(K26/K$9,0) -> 0.29880613 | N26: =N24+N25 -> 26.683378 | O26: =IFERROR(N26/N$9,0) -> 0.23598829 | P26: =K26-N26 -> 7.3012376 | Q26: =IFERROR(K26/N26-1,"") -> 0.27362494 | R26: =IF(Q26>0.05,1,IF(Q26<-0.05,-1,0)) -> 1 | T26: =SUM(T24:T25) -> 22.628938 | U26: =SUM(U24:U25) -> 0 | V26: =SUM(V24:V25) -> 0 | W26: =SUM(W24:W25) -> 0 | X26: =SUM(X24:X25) -> 0 | Y26: =SUM(Y24:Y25) -> 22.628938 | Z26: =SUM(Z24:Z25) -> 0 | AA26: =SUM(AA24:AA25) -> 0 | AB26: =SUM(AB24:AB25) -> 22.628938 | AC26: =IFERROR(AB26/AB$9,0) -> 0.23773503 | AD26: =$K26-AB26 -> 11.355677 | AE26: =IFERROR(K26/AB26-1,"") -> 0.50182104 | AF26: =IF(AE26>0.05,1,IF(AE26<-0.05,-1,0)) -> 1 | AH26: = EBITDA | AI26: =SUM(AI24:AI25) -> 127.22498 | AJ26: =SUM(AJ24:AJ25) -> 0 | AK26: =SUM(AK24:AK25) -> 0 | AL26: =SUM(AL24:AL25) -> 127.22498 | AM26: =SUM(AM24:AM25) -> 0 | AN26: =SUM(AN24:AN25) -> 3.4924597e-16 | AO26: =SUM(AO24:AO25) -> 127.22498 | AP26: =IFERROR(AO26/AO$9,0) -> 0.23409892 | AR26: =AR24+AR25 -> 125.95426 | AS26: =IFERROR(AR26/AR$9,0) -> 0.23251845 | AT26: =AO26-AR26 -> 1.2707207 | AU26: =IFERROR(AO26/AR26-1,"") -> 0.010088747 | AV26: =IF(AU26>0.05,1,IF(AU26<-0.05,-1,0)) -> 0 | AX26: =SUM(AX24:AX25) -> 99.668388 | AY26: =SUM(AY24:AY25) -> 0 | AZ26: =SUM(AZ24:AZ25) -> 1.4210855e-14 | BA26: =SUM(BA24:BA25) -> 0 | BB26: =SUM(BB24:BB25) -> 0 | BC26: =SUM(BC24:BC25) -> 99.668388 | BD26: =SUM(BD24:BD25) -> 0 | BE26: =SUM(BE24:BE25) -> 0 | BF26: =SUM(BF24:BF25) -> 99.668388 | BG26: =IFERROR(BF26/BF$9,0) -> 0.21593994 | BH26: =$AO26-BF26 -> 27.556596 | BI26: =IFERROR(AO26/BF26-1,"") -> 0.27648281 | BJ26: =IF(BI26>0.05,1,IF(BI26<-0.05,-1,0)) -> 1
C27: (-) D&A | E27: =SUM(E28:E29) -> -8.7318616 | F27: =SUM(F28:F29) -> 0 | G27: =SUM(G28:G29) -> 0 | H27: =SUM(H28:H29) -> -8.7318616 | I27: =SUM(I28:I29) -> 0 | J27: =SUM(J28:J29) -> 0 | K27: =SUM(K28:K29) -> -8.7318616 | L27: =IFERROR(K27/K$9,0) -> -0.076773966 | N27: =SUM(N28:N29) -> -8.8445773 | O27: =IFERROR(N27/N$9,0) -> -0.078221607 | P27: =K27-N27 -> 0.11271576 | Q27: =IFERROR(K27/N27-1,"") -> -0.012744053 | T27: =SUM(T28:T29) -> -7.6700771 | U27: =SUM(U28:U29) -> 0 | V27: =SUM(V28:V29) -> 0 | W27: =SUM(W28:W29) -> 0 | X27: =SUM(X28:X29) -> 0 | Y27: =SUM(Y28:Y29) -> -7.6700771 | Z27: =SUM(Z28:Z29) -> 0 | AA27: =SUM(AA28:AA29) -> 0 | AB27: =SUM(AB28:AB29) -> -7.6700771 | AC27: =IFERROR(AB27/AB$9,0) -> -0.080580273 | AD27: =$K27-AB27 -> -1.0617844 | AE27: =IFERROR(K27/AB27-1,"") -> 0.13843204 | AF27: =IF(AE27>0.05,1,IF(AE27<-0.05,-1,0)) -> 1 | AI27: =SUM(AI28:AI29) -> -43.955698 | AJ27: =SUM(AJ28:AJ29) -> 0 | AK27: =SUM(AK28:AK29) -> 0 | AL27: =SUM(AL28:AL29) -> -43.955698 | AM27: =SUM(AM28:AM29) -> 0 | AN27: =SUM(AN28:AN29) -> 0 | AO27: =SUM(AO28:AO29) -> -43.955698 | AP27: =IFERROR(AO27/AO$9,0) -> -0.080880193 | AR27: =SUM(AR28:AR29) -> -45.689141 | AS27: =IFERROR(AR27/AR$9,0) -> -0.084344651 | AT27: =AO27-AR27 -> 1.733443 | AU27: =IFERROR(AO27/AR27-1,"") -> -0.037939934 | AV27: =IF(AU27>0.05,1,IF(AU27<-0.05,-1,0)) -> 0 | AX27: =SUM(AX28:AX29) -> -40.793179 | AY27: =SUM(AY28:AY29) -> 0 | AZ27: =SUM(AZ28:AZ29) -> 0 | BA27: =SUM(BA28:BA29) -> 0 | BB27: =SUM(BB28:BB29) -> 0 | BC27: =SUM(BC28:BC29) -> -40.793179 | BD27: =SUM(BD28:BD29) -> 0 | BE27: =SUM(BE28:BE29) -> 0 | BF27: =SUM(BF28:BF29) -> -40.793179 | BG27: =IFERROR(BF27/BF$9,0) -> -0.088381849 | BH27: =$AO27-BF27 -> -3.162519 | BI27: =IFERROR(AO27/BF27-1,"") -> 0.077525683 | BJ27: =IF(BI27>0.05,1,IF(BI27<-0.05,-1,0)) -> 1
B28: D&A | C28: (-) D&A Operating Assests | E28: -3.9002693 | F28: 0 | G28: 0 | H28: =SUM(E28:G28) -> -3.9002693 | I28: 0 | J28: 0 | K28: =SUM(H28:J28) -> -3.9002693 | L28: =IFERROR(K28/K$9,0) -> -0.034292704 | N28: -3.8564283 | O28: =IFERROR(N28/N$9,0) -> -0.034106324 | P28: =K28-N28 -> -0.043840937 | Q28: =IFERROR(K28/N28-1,"") -> 0.011368275 | T28: -2.503726 | U28: 0 | V28: 0 | W28: 0 | X28: 0 | Y28: =SUM(T28:X28) -> -2.503726 | Z28: 0 | AA28: 0 | AB28: =SUM(Y28:AA28) -> -2.503726 | AC28: =IFERROR(AB28/AB$9,0) -> -0.026303637 | AD28: =$K28-AB28 -> -1.3965433 | AE28: =IFERROR(K28/AB28-1,"") -> 0.55778598 | AH28: (-) D&A | AI28: -19.652629 | AJ28: 0 | AK28: 0 | AL28: =SUM(AI28:AK28) -> -19.652629 | AM28: 0 | AN28: 0 | AO28: =SUM(AL28:AN28) -> -19.652629 | AP28: =IFERROR(AO28/AO$9,0) -> -0.036161602 | AR28: -19.727686 | AS28: =IFERROR(AR28/AR$9,0) -> -0.036418387 | AT28: =AO28-AR28 -> 0.075056793 | AU28: =IFERROR(AO28/AR28-1,"") -> -0.0038046425 | AX28: -15.198728 | AY28: 0 | AZ28: 0 | BA28: 0 | BB28: 0 | BC28: =SUM(AX28:BB28) -> -15.198728 | BD28: 0 | BE28: 0 | BF28: =SUM(BC28:BE28) -> -15.198728 | BG28: =IFERROR(BF28/BF$9,0) -> -0.03292932 | BH28: =$AO28-BF28 -> -4.4539018 | BI28: =IFERROR(AO28/BF28-1,"") -> 0.29304439
B29: M&A Amortization | C29: (-) M&A Amortization | E29: -4.8315923 | F29: 0 | G29: 0 | H29: =SUM(E29:G29) -> -4.8315923 | I29: 0 | J29: 0 | K29: =SUM(H29:J29) -> -4.8315923 | L29: =IFERROR(K29/K$9,0) -> -0.042481263 | N29: -4.988149 | O29: =IFERROR(N29/N$9,0) -> -0.044115283 | P29: =K29-N29 -> 0.1565567 | Q29: =IFERROR(K29/N29-1,"") -> -0.03138573 | T29: -5.1663511 | U29: 0 | V29: 0 | W29: 0 | X29: 0 | Y29: =SUM(T29:X29) -> -5.1663511 | Z29: 0 | AA29: 0 | AB29: =SUM(Y29:AA29) -> -5.1663511 | AC29: =IFERROR(AB29/AB$9,0) -> -0.054276636 | AD29: =$K29-AB29 -> 0.33475884 | AE29: =IFERROR(K29/AB29-1,"") -> -0.064795991 | AH29: (-) M&A Amortization | AI29: -24.303068 | AJ29: 0 | AK29: 0 | AL29: =SUM(AI29:AK29) -> -24.303068 | AM29: 0 | AN29: 0 | AO29: =SUM(AL29:AN29) -> -24.303068 | AP29: =IFERROR(AO29/AO$9,0) -> -0.044718591 | AR29: -25.961455 | AS29: =IFERROR(AR29/AR$9,0) -> -0.047926264 | AT29: =AO29-AR29 -> 1.6583862 | AU29: =IFERROR(AO29/AR29-1,"") -> -0.063878785 | AX29: -25.594451 | AY29: 0 | AZ29: 0 | BA29: 0 | BB29: 0 | BC29: =SUM(AX29:BB29) -> -25.594451 | BD29: 0 | BE29: 0 | BF29: =SUM(BC29:BE29) -> -25.594451 | BG29: =IFERROR(BF29/BF$9,0) -> -0.055452529 | BH29: =$AO29-BF29 -> 1.2913828 | BI29: =IFERROR(AO29/BF29-1,"") -> -0.050455576
B30: Financial Results | C30: (+/-) Financial Results | E30: -0.74368261 | F30: 0 | G30: 0 | H30: =SUM(E30:G30) -> -0.74368261 | I30: 0 | J30: 0 | K30: =SUM(H30:J30) -> -0.74368261 | L30: =IFERROR(K30/K$9,0) -> -0.0065387504 | N30: -1.4781771 | O30: =IFERROR(N30/N$9,0) -> -0.013073026 | P30: =K30-N30 -> 0.73449446 | Q30: =IFERROR(K30/N30-1,"") -> -0.49689207 | T30: -3.2063321 | U30: 0 | V30: 0 | W30: 0 | X30: 0 | Y30: =SUM(T30:X30) -> -3.2063321 | Z30: 0 | AA30: 0 | AB30: =SUM(Y30:AA30) -> -3.2063321 | AC30: =IFERROR(AB30/AB$9,0) -> -0.033685074 | AD30: =$K30-AB30 -> 2.4626495 | AE30: =IFERROR(K30/AB30-1,"") -> -0.76805815 | AH30: (+/-) Financial Results | AI30: -5.262409 | AJ30: 0 | AK30: 0 | AL30: =SUM(AI30:AK30) -> -5.262409 | AM30: 0 | AN30: 0 | AO30: =SUM(AL30:AN30) -> -5.262409 | AP30: =IFERROR(AO30/AO$9,0) -> -0.0096830371 | AR30: -8.0803088 | AS30: =IFERROR(AR30/AR$9,0) -> -0.014916692 | AT30: =AO30-AR30 -> 2.8178998 | AU30: =IFERROR(AO30/AR30-1,"") -> -0.34873664 | AX30: -10.368245 | AY30: 0 | AZ30: 0 | BA30: 0 | BB30: 0 | BC30: =SUM(AX30:BB30) -> -10.368245 | BD30: 0 | BE30: 0 | BF30: =SUM(BC30:BE30) -> -10.368245 | BG30: =IFERROR(BF30/BF$9,0) -> -0.022463673 | BH30: =$AO30-BF30 -> 5.1058358 | BI30: =IFERROR(AO30/BF30-1,"") -> -0.49244939
C31: (+) Financial Revenue | K31: 2.7418117 | L31: =IFERROR(K31/K$9,0) -> 0.024107088 | N31: 1.1928444 | O31: =IFERROR(N31/N$9,0) -> 0.010549538 | P31: =K31-N31 -> 1.5489673 | Q31: =IFERROR(K31/N31-1,"") -> 1.2985493 | AB31: 0.99911402 | AC31: =IFERROR(AB31/AB$9,0) -> 0.010496489 | AD31: =$K31-AB31 -> 1.7426977 | AE31: =IFERROR(K31/AB31-1,"") -> 1.744243 | AO31: 17.139972 | AP31: =IFERROR(AO31/AO$9,0) -> 0.031538214 | AR31: 6.0266249 | AS31: =IFERROR(AR31/AR$9,0) -> 0.011125479 | AT31: =AO31-AR31 -> 11.113347 | AU31: =IFERROR(AO31/AR31-1,"") -> 1.8440415 | BF31: 9.9846335 | BG31: =IFERROR(BF31/BF$9,0) -> 0.021632547 | BH31: =$AO31-BF31 -> 7.155338 | BI31: =IFERROR(AO31/BF31-1,"") -> 0.71663502
C32: (-) Financial Expenses | K32: -3.4471245 | L32: =IFERROR(K32/K$9,0) -> -0.030308477 | N32: -2.6710215 | O32: =IFERROR(N32/N$9,0) -> -0.023622564 | P32: =K32-N32 -> -0.77610307 | Q32: =IFERROR(K32/N32-1,"") -> 0.29056415 | AB32: -4.2054469 | AC32: =IFERROR(AB32/AB$9,0) -> -0.044181571 | AD32: =$K32-AB32 -> 0.75832236 | AE32: =IFERROR(K32/AB32-1,"") -> -0.18031909 | AO32: -22.36428 | AP32: =IFERROR(AO32/AO$9,0) -> -0.041151145 | AR32: -14.106934 | AS32: =IFERROR(AR32/AR$9,0) -> -0.026042171 | AT32: =AO32-AR32 -> -8.2573468 | AU32: =IFERROR(AO32/AR32-1,"") -> 0.58533959 | BF32: -20.368833 | BG32: =IFERROR(BF32/BF$9,0) -> -0.044130788 | BH32: =$AO32-BF32 -> -1.9954473 | BI32: =IFERROR(AO32/BF32-1,"") -> 0.097965713
C33: (-) Income Tax | E33: =SUM(E34:E35) -> -5.7406935 | F33: =SUM(F34:F35) -> 0 | G33: =SUM(G34:G35) -> 0 | H33: =SUM(H34:H35) -> -5.7406935 | I33: =SUM(I34:I35) -> 0 | J33: =SUM(J34:J35) -> 0 | K33: =SUM(K34:K35) -> -5.7406935 | L33: =IFERROR(K33/K$9,0) -> -0.050474439 | N33: =SUM(N34:N35) -> -7.4642437 | O33: =IFERROR(N33/N$9,0) -> -0.066013911 | P33: =K33-N33 -> 1.7235502 | Q33: =IFERROR(K33/N33-1,"") -> -0.23090755 | T33: =SUM(T34:T35) -> -14.041346 | U33: =SUM(U34:U35) -> 0 | V33: =SUM(V34:V35) -> 0 | W33: =SUM(W34:W35) -> 0 | X33: =SUM(X34:X35) -> 0 | Y33: =SUM(Y34:Y35) -> -14.041346 | Z33: =SUM(Z34:Z35) -> 0 | AA33: =SUM(AA34:AA35) -> 0 | AB33: =SUM(AB34:AB35) -> -14.041346 | AC33: =IFERROR(AB33/AB$9,0) -> -0.14751553 | AD33: =$K33-AB33 -> 8.3006529 | AE33: =IFERROR(K33/AB33-1,"") -> -0.5911579 | AI33: =SUM(AI34:AI35) -> -28.282652 | AJ33: =SUM(AJ34:AJ35) -> 0 | AK33: =SUM(AK34:AK35) -> 0 | AL33: =SUM(AL34:AL35) -> -28.282652 | AM33: =SUM(AM34:AM35) -> 0 | AN33: =SUM(AN34:AN35) -> 0 | AO33: =SUM(AO34:AO35) -> -28.282652 | AP33: =IFERROR(AO33/AO$9,0) -> -0.05204118 | AR33: =SUM(AR34:AR35) -> -35.778353 | AS33: =IFERROR(AR33/AR$9,0) -> -0.066048796 | AT33: =AO33-AR33 -> 7.495701 | AU33: =IFERROR(AO33/AR33-1,"") -> -0.2095038 | AX33: =SUM(AX34:AX35) -> -23.010915 | AY33: =SUM(AY34:AY35) -> 0 | AZ33: =SUM(AZ34:AZ35) -> 0 | BA33: =SUM(BA34:BA35) -> 0 | BB33: =SUM(BB34:BB35) -> 0 | BC33: =SUM(BC34:BC35) -> -23.010915 | BD33: =SUM(BD34:BD35) -> 0 | BE33: =SUM(BE34:BE35) -> 0 | BF33: =SUM(BF34:BF35) -> -23.010915 | BG33: =IFERROR(BF33/BF$9,0) -> -0.04985508 | BH33: =$AO33-BF33 -> -5.2717377 | BI33: =IFERROR(AO33/BF33-1,"") -> 0.22909727
B34: Income Tax | C34: (-) Current | E34: -5.1142733 | F34: 0 | G34: 0 | H34: =SUM(E34:G34) -> -5.1142733 | I34: 0 | J34: 0 | K34: =SUM(H34:J34) -> -5.1142733 | L34: =IFERROR(K34/K$9,0) -> -0.044966706 | N34: -5.4016825 | O34: =IFERROR(N34/N$9,0) -> -0.04777258 | P34: =K34-N34 -> 0.28740912 | Q34: =IFERROR(K34/N34-1,"") -> -0.053207334 | T34: -5.7813332 | U34: 0 | V34: 0 | W34: 0 | X34: 0 | Y34: =SUM(T34:X34) -> -5.7813332 | Z34: 0 | AA34: 0 | AB34: =SUM(Y34:AA34) -> -5.7813332 | AC34: =IFERROR(AB34/AB$9,0) -> -0.060737513 | AD34: =$K34-AB34 -> 0.66705987 | AE34: =IFERROR(K34/AB34-1,"") -> -0.11538167 | AH34: (-) Income Tax | AI34: -17.499858 | AJ34: 0 | AK34: 0 | AL34: =SUM(AI34:AK34) -> -17.499858 | AM34: 0 | AN34: 0 | AO34: =SUM(AL34:AN34) -> -17.499858 | AP34: =IFERROR(AO34/AO$9,0) -> -0.032200419 | AR34: -25.48615 | AS34: =IFERROR(AR34/AR$9,0) -> -0.047048826 | AT34: =AO34-AR34 -> 7.9862921 | AU34: =IFERROR(AO34/AR34-1,"") -> -0.31335812 | AX34: -17.445239 | AY34: 0 | AZ34: 0 | BA34: 0 | BB34: 0 | BC34: =SUM(AX34:BB34) -> -17.445239 | BD34: 0 | BE34: 0 | BF34: =SUM(BC34:BE34) -> -17.445239 | BG34: =IFERROR(BF34/BF$9,0) -> -0.037796577 | BH34: =$AO34-BF34 -> -0.054618422 | BI34: =IFERROR(AO34/BF34-1,"") -> 0.0031308497
B35: Deferred Tax | C35: (+/-) Deferred | E35: -0.62642019 | F35: 0 | G35: 0 | H35: =SUM(E35:G35) -> -0.62642019 | I35: 0 | J35: 0 | K35: =SUM(H35:J35) -> -0.62642019 | L35: =IFERROR(K35/K$9,0) -> -0.005507733 | N35: -2.0625613 | O35: =IFERROR(N35/N$9,0) -> -0.01824133 | P35: =K35-N35 -> 1.4361411 | Q35: =IFERROR(K35/N35-1,"") -> -0.69629014 | T35: -8.2600132 | U35: 0 | V35: 0 | W35: 0 | X35: 0 | Y35: =SUM(T35:X35) -> -8.2600132 | Z35: 0 | AA35: 0 | AB35: =SUM(Y35:AA35) -> -8.2600132 | AC35: =IFERROR(AB35/AB$9,0) -> -0.086778022 | AD35: =$K35-AB35 -> 7.633593 | AE35: =IFERROR(K35/AB35-1,"") -> -0.92416233 | AH35: (+/-) Deferred Tax | AI35: -10.782795 | AJ35: 0 | AK35: 0 | AL35: =SUM(AI35:AK35) -> -10.782795 | AM35: 0 | AN35: 0 | AO35: =SUM(AL35:AN35) -> -10.782795 | AP35: =IFERROR(AO35/AO$9,0) -> -0.019840761 | AR35: -10.292204 | AS35: =IFERROR(AR35/AR$9,0) -> -0.01899997 | AT35: =AO35-AR35 -> -0.4905911 | AU35: =IFERROR(AO35/AR35-1,"") -> 0.047666284 | AX35: -5.5656754 | AY35: 0 | AZ35: 0 | BA35: 0 | BB35: 0 | BC35: =SUM(AX35:BB35) -> -5.5656754 | BD35: 0 | BE35: 0 | BF35: =SUM(BC35:BE35) -> -5.5656754 | BG35: =IFERROR(BF35/BF$9,0) -> -0.012058503 | BH35: =$AO35-BF35 -> -5.2171193 | BI35: =IFERROR(AO35/BF35-1,"") -> 0.93737399
C36: Adjusted Net Income | E36: =SUM(E24,E27,E30,E33) -> 19.249147 | F36: =SUM(F24,F27,F30,F33) -> -0.4807693 | G36: =SUM(G24,G27,G30,G33) -> 0 | H36: =SUM(H24,H27,H30,H33) -> 18.768378 | I36: =SUM(I24,I27,I30,I33) -> 0.086875 | J36: =SUM(J24,J27,J30,J33) -> 2.3283064e-16 | K36: =SUM(K24,K27,K30,K33) -> 18.855253 | L36: =IFERROR(K36/K$9,0) -> 0.16578281 | N36: =SUM(N24,N27,N30,N33) -> 8.9843798 | O36: =IFERROR(N36/N$9,0) -> 0.079458023 | P36: =K36-N36 -> 9.870873 | Q36: =IFERROR(K36/N36-1,"") -> 1.0986705 | T36: =SUM(T24,T27,T30,T33) -> -2.1626294 | U36: =SUM(U24,U27,U30,U33) -> -0.12618796 | V36: =SUM(V24,V27,V30,V33) -> 0 | W36: =SUM(W24,W27,W30,W33) -> 0 | X36: =SUM(X24,X27,X30,X33) -> 0 | Y36: =SUM(Y24,Y27,Y30,Y33) -> -2.2888174 | Z36: =SUM(Z24,Z27,Z30,Z33) -> 0.02257201 | AA36: =SUM(AA24,AA27,AA30,AA33) -> 0 | AB36: =SUM(AB24,AB27,AB30,AB33) -> -2.2662454 | AC36: =IFERROR(AB36/AB$9,0) -> -0.023808714 | AD36: =$K36-AB36 -> 21.121498 | AE36: =IFERROR(K36/AB36-1,"") -> -9.3200403 | AH36: Adjusted Net Income | AI36: =SUM(AI24,AI27,AI30,AI33) -> 49.18084 | AJ36: =SUM(AJ24,AJ27,AJ30,AJ33) -> 0.5436477 | AK36: =SUM(AK24,AK27,AK30,AK33) -> 0 | AL36: =SUM(AL24,AL27,AL30,AL33) -> 49.724488 | AM36: =SUM(AM24,AM27,AM30,AM33) -> 0.621875 | AN36: =SUM(AN24,AN27,AN30,AN33) -> 3.4924597e-16 | AO36: =SUM(AO24,AO27,AO30,AO33) -> 50.346363 | AP36: =IFERROR(AO36/AO$9,0) -> 0.092639265 | AR36: =SUM(AR24,AR27,AR30,AR33) -> 37.096461 | AS36: =IFERROR(AR36/AR$9,0) -> 0.068482094 | AT36: =AO36-AR36 -> 13.249902 | AU36: =IFERROR(AO36/AR36-1,"") -> 0.35717429 | AX36: =SUM(AX24,AX27,AX30,AX33) -> 31.384478 | AY36: =SUM(AY24,AY27,AY30,AY33) -> -5.8884285 | AZ36: =SUM(AZ24,AZ27,AZ30,AZ33) -> 1.4210855e-14 | BA36: =SUM(BA24,BA27,BA30,BA33) -> 0 | BB36: =SUM(BB24,BB27,BB30,BB33) -> 0 | BC36: =SUM(BC24,BC27,BC30,BC33) -> 25.49605 | BD36: =SUM(BD24,BD27,BD30,BD33) -> -0.55265431 | BE36: =SUM(BE24,BE27,BE30,BE33) -> 0 | BF36: =SUM(BF24,BF27,BF30,BF33) -> 24.943396 | BG36: =IFERROR(BF36/BF$9,0) -> 0.054041962 | BH36: =$AO36-BF36 -> 25.402967 | BI36: =IFERROR(AO36/BF36-1,"") -> 1.0184246
B37: Adjustments | C37: (+/-) Non-recurring | E37: 0 | F37: 0 | G37: 0 | H37: =SUM(E37:G37) -> 0 | I37: 0 | J37: 0 | K37: =SUM(H37:J37) -> 0 | L37: =IFERROR(K37/K$9,0) -> 0 | N37: 0 | O37: =IFERROR(N37/N$9,0) -> 0 | P37: =K37-N37 -> 0 | Q37: =IFERROR(K37/N37-1,"") | T37: 0 | U37: 0 | V37: 0 | W37: 0 | X37: 0 | Y37: =SUM(T37:X37) -> 0 | Z37: 0 | AA37: 0 | AB37: =SUM(Y37:AA37) -> 0 | AC37: =IFERROR(AB37/AB$9,0) -> 0 | AD37: =$K37-AB37 -> 0 | AE37: =IFERROR(K37/AB37-1,"") | AH37: (+/-) Non-recurring | AI37: 0 | AJ37: 0 | AK37: 0 | AL37: =SUM(AI37:AK37) -> 0 | AM37: 0 | AN37: 0 | AO37: =SUM(AL37:AN37) -> 0 | AP37: =IFERROR(AO37/AO$9,0) -> 0 | AR37: 0 | AS37: =IFERROR(AR37/AR$9,0) -> 0 | AT37: =AO37-AR37 -> 0 | AU37: =IFERROR(AO37/AR37-1,"") | AX37: -0.00013779 | AY37: 0 | AZ37: 0 | BA37: 0 | BB37: 0 | BC37: =SUM(AX37:BB37) -> -0.00013779 | BD37: 0 | BE37: 0 | BF37: =SUM(BC37:BE37) -> -0.00013779 | BG37: =IFERROR(BF37/BF$9,0) -> -2.9853361e-07 | BH37: =$AO37-BF37 -> 0.00013779 | BI37: =IFERROR(AO37/BF37-1,"") -> -1
C38: = Net Income | E38: =SUM(E26,E28:E29,E30,E34:E35,E37) -> 18.768378 | F38: =SUM(F26,F28:F29,F30,F34:F35,F37) -> 0 | G38: =SUM(G26,G28:G29,G30,G34:G35,G37) -> 0 | H38: =SUM(H26,H28:H29,H30,H34:H35,H37) -> 18.768378 | I38: =SUM(I26,I28:I29,I30,I34:I35,I37) -> 0 | J38: =SUM(J26,J28:J29,J30,J34:J35,J37) -> 2.3283064e-16 | K38: =SUM(K26,K28:K29,K30,K34:K35,K37) -> 18.768378 | L38: =IFERROR(K38/K$9,0) -> 0.16501897 | N38: =N36+N37+N25 -> 8.8963798 | O38: =IFERROR(N38/N$9,0) -> 0.078679749 | P38: =K38-N38 -> 9.871998 | Q38: =IFERROR(K38/N38-1,"") -> 1.1096646 | R38: =IF(Q38>0.05,1,IF(Q38<-0.05,-1,0)) -> 1 | T38: =SUM(T26,T28:T29,T30,T34:T35,T37) -> -2.2888174 | U38: =SUM(U26,U28:U29,U30,U34:U35,U37) -> 0 | V38: =SUM(V26,V28:V29,V30,V34:V35,V37) -> 0 | W38: =SUM(W26,W28:W29,W30,W34:W35,W37) -> 0 | X38: =SUM(X26,X28:X29,X30,X34:X35,X37) -> 0 | Y38: =SUM(T38:X38) -> -2.2888174 | Z38: =SUM(Z26,Z28:Z29,Z30,Z34:Z35,Z37) -> 0 | AA38: =SUM(AA26,AA28:AA29,AA30,AA34:AA35,AA37) -> 0 | AB38: =SUM(AB26,AB28:AB29,AB30,AB34:AB35,AB37) -> -2.2888174 | AC38: =IFERROR(AB38/AB$9,0) -> -0.024045851 | AD38: =$K38-AB38 -> 21.057195 | AE38: =IFERROR(K38/AB38-1,"") -> -9.2000329 | AF38: =IF(AE38>0.05,1,IF(AE38<-0.05,-1,0)) -> -1 | AH38: = Net Income | AI38: =SUM(AI26,AI28:AI29,AI30,AI34:AI35,AI37) -> 49.724225 | AJ38: =SUM(AJ26,AJ28:AJ29,AJ30,AJ34:AJ35,AJ37) -> 0 | AK38: =SUM(AK26,AK28:AK29,AK30,AK34:AK35,AK37) -> 0 | AL38: =SUM(AL26,AL28:AL29,AL30,AL34:AL35,AL37) -> 49.724225 | AM38: =SUM(AM26,AM28:AM29,AM30,AM34:AM35,AM37) -> 0 | AN38: =SUM(AN26,AN28:AN29,AN30,AN34:AN35,AN37) -> 3.4924597e-16 | AO38: =SUM(AO26,AO28:AO29,AO30,AO34:AO35,AO37) -> 49.724225 | AP38: =IFERROR(AO38/AO$9,0) -> 0.091494507 | AR38: =AR36+AR37+AR25 -> 36.406461 | AS38: =IFERROR(AR38/AR$9,0) -> 0.067208316 | AT38: =AO38-AR38 -> 13.317764 | AU38: =IFERROR(AO38/AR38-1,"") -> 0.36580772 | AV38: =IF(AU38>0.05,1,IF(AU38<-0.05,-1,0)) -> 1 | AX38: =SUM(AX26,AX28:AX29,AX30,AX34:AX35,AX37) -> 25.495912 | AY38: =SUM(AY26,AY28:AY29,AY30,AY34:AY35,AY37) -> 0 | AZ38: =SUM(AZ26,AZ28:AZ29,AZ30,AZ34:AZ35,AZ37) -> 1.4210855e-14 | BA38: =SUM(BA26,BA28:BA29,BA30,BA34:BA35,BA37) -> 0 | BB38: =SUM(BB26,BB28:BB29,BB30,BB34:BB35,BB37) -> 0 | BC38: =SUM(AX38:BB38) -> 25.495912 | BD38: =SUM(BD26,BD28:BD29,BD30,BD34:BD35,BD37) -> 0 | BE38: =SUM(BE26,BE28:BE29,BE30,BE34:BE35,BE37) -> 0 | BF38: =SUM(BF26,BF28:BF29,BF30,BF34:BF35,BF37) -> 25.495912 | BG38: =IFERROR(BF38/BF$9,0) -> 0.055239036 | BH38: =$AO38-BF38 -> 24.228313 | BI38: =IFERROR(AO38/BF38-1,"") -> 0.95028225 | BJ38: =IF(BI38>0.05,1,IF(BI38<-0.05,-1,0)) -> 1
C40: R&D + Capex | E40: =E16+E41 -> -23.65411 | F40: 0 | G40: 0 | H40: =SUM(E40:G40) -> -23.65411 | I40: 0 | J40: 0 | K40: =K16+K41 -> -24.179889 | L40: =IFERROR(K40/K$9,0) -> -0.2125991 | N40: =N16+N41 -> -27.223851 | O40: =IFERROR(N40/N$9,0) -> -0.24076824 | P40: =K40-N40 -> 3.0439621 | Q40: =IFERROR(K40/N40-1,"") -> -0.11181233 | T40: =T16+T41 -> -18.441405 | U40: 0 | V40: 0 | W40: 0 | X40: 0 | Y40: =SUM(T40:X40) -> -18.441405 | Z40: 0 | AA40: 0 | AB40: =AB16+AB41 -> -18.866989 | AC40: =IFERROR(AB40/AB$9,0) -> -0.19821276 | AD40: =$K40-AB40 -> -5.3128992 | AE40: =IFERROR(K40/AB40-1,"") -> 0.28159762 | AH40: R&D + Capex | AI40: =AI16+AI41 -> -113.81438 | AJ40: 0 | AK40: 0 | AL40: =SUM(AI40:AK40) -> -113.81438 | AM40: 0 | AN40: 0 | AO40: =AO16+AO41 -> -117.23568 | AP40: =IFERROR(AO40/AO$9,0) -> -0.2157182 | AR40: =AR41+AR16 -> -131.47638 | AS40: =IFERROR(AR40/AR$9,0) -> -0.24271258 | AT40: =AO40-AR40 -> 14.2407 | AU40: =IFERROR(AO40/AR40-1,"") -> -0.10831375 | AX40: =AX16+AX41 -> -91.103219 | AY40: 0 | AZ40: 0 | BA40: 0 | BB40: 0 | BC40: =SUM(AX40:BB40) -> -91.103219 | BD40: 0 | BE40: 0 | BF40: =SUM(BC40:BE40) -> -91.103219 | BG40: =IFERROR(BF40/BF$9,0) -> -0.19738278 | BH40: =$AO40-BF40 -> -26.132459 | BI40: =IFERROR(AO40/BF40-1,"") -> 0.28684452
B41: Capex | C41: (-) Capex | E41: ='Painel Resultado (MTD)'!AO11 -> -12.111835 | F41: 0 | G41: 0 | H41: =SUM(E41:G41) -> -12.111835 | I41: 0 | J41: 0 | K41: =SUM(H41:J41) -> -12.111835 | L41: =IFERROR(K41/K$9,0) -> -0.10649203 | N41: =N46 -> -9.6110155 | O41: =IFERROR(N41/N$9,0) -> -0.085 | P41: =K41-N41 -> -2.5008199 | Q41: =IFERROR(K41/N41-1,"") -> 0.2602035 | T41: ='Painel Resultado (MTD)'!BC11 -> -3.8148089 | U41: 0 | V41: 0 | W41: 0 | X41: 0 | Y41: =SUM(T41:X41) -> -3.8148089 | Z41: 0 | AA41: 0 | AB41: =SUM(Y41:AA41) -> -3.8148089 | AC41: =IFERROR(AB41/AB$9,0) -> -0.040077608 | AD41: =$K41-AB41 -> -8.2970264 | AE41: =IFERROR(K41/AB41-1,"") -> 2.1749521 | AH41: (-) Capex | AI41: ='Painel Resultado (YTD)'!AO11 -> -32.028326 | AJ41: 0 | AK41: 0 | AL41: =SUM(AI41:AK41) -> -32.028326 | AM41: 0 | AN41: 0 | AO41: =SUM(AL41:AN41) -> -32.028326 | AP41: =IFERROR(AO41/AO$9,0) -> -0.058933365 | AR41: =AR46 -> -46.044141 | AS41: =IFERROR(AR41/AR$9,0) -> -0.085 | AT41: =AO41-AR41 -> 14.015814 | AU41: =IFERROR(AO41/AR41-1,"") -> -0.30439952 | AX41: ='Painel Resultado (YTD)'!BC11 -> -16.892246 | AY41: 0 | AZ41: 0 | BA41: 0 | BB41: 0 | BC41: =SUM(AX41:BB41) -> -16.892246 | BD41: 0 | BE41: 0 | BF41: =SUM(BC41:BE41) -> -16.892246 | BG41: =IFERROR(BF41/BF$9,0) -> -0.03659847 | BH41: =$AO41-BF41 -> -15.13608 | BI41: =IFERROR(AO41/BF41-1,"") -> 0.89603718
C42: = Adjusted EBITDA After Capex | E42: =SUM(E19,E41) -> 22.357251 | F42: =SUM(F19,F41) -> -0.4807693 | G42: =SUM(G19,G41) -> 0 | H42: =SUM(E42:G42) -> 21.876481 | I42: =SUM(I19,I41) -> 0.086875 | J42: =SUM(J19,J41) -> 2.3283064e-16 | K42: =K19+K41 -> 21.963356 | L42: =IFERROR(K42/K$9,0) -> 0.19311048 | N42: =N19+N41 -> 17.160363 | O42: =IFERROR(N42/N$9,0) -> 0.15176657 | P42: =K42-N42 -> 4.802994 | Q42: =IFERROR(K42/N42-1,"") -> 0.27988884 | R42: =IF(Q42>0.05,1,IF(Q42<-0.05,-1,0)) -> 1 | T42: =SUM(T19,T41) -> 19.007756 | U42: =SUM(U19,U41) -> -0.12618796 | V42: =SUM(V19,V41) -> 0 | W42: =SUM(W19,W41) -> 0 | X42: =SUM(X19,X41) -> 0 | Y42: =SUM(T42:X42) -> 18.881568 | Z42: =SUM(Z19,Z41) -> 0.02257201 | AA42: =SUM(AA19,AA41) -> 0 | AB42: =AB19+AB41 -> 18.90414 | AC42: =IFERROR(AB42/AB$9,0) -> 0.19860306 | AD42: =$K42-AB42 -> 3.0592164 | AE42: =IFERROR(K42/AB42-1,"") -> 0.16182785 | AF42: =IF(AE42>0.05,1,IF(AE42<-0.05,-1,0)) -> 1 | AH42: = Adjusted EBITDA After Capex | AI42: =SUM(AI19,AI41) -> 94.671204 | AJ42: =SUM(AJ19,AJ41) -> 0.5436477 | AK42: =SUM(AK19,AK41) -> 0 | AL42: =SUM(AI42:AK42) -> 95.214852 | AM42: =SUM(AM19,AM41) -> 0.621875 | AN42: =SUM(AN19,AN41) -> 3.4924597e-16 | AO42: =AO19+AO41 -> 95.836727 | AP42: =IFERROR(AO42/AO$9,0) -> 0.1763433 | AR42: =AR19+AR41 -> 80.600123 | AS42: =IFERROR(AR42/AR$9,0) -> 0.14879223 | AT42: =AO42-AR42 -> 15.236604 | AU42: =IFERROR(AO42/AR42-1,"") -> 0.18903946 | AV42: =IF(AU42>0.05,1,IF(AU42<-0.05,-1,0)) -> 1 | AX42: =SUM(AX19,AX41) -> 88.73467 | AY42: =SUM(AY19,AY41) -> -5.8884285 | AZ42: =SUM(AZ19,AZ41) -> 1.4210855e-14 | BA42: =SUM(BA19,BA41) -> 0 | BB42: =SUM(BB19,BB41) -> 0 | BC42: =SUM(AX42:BB42) -> 82.846241 | BD42: =SUM(BD19,BD41) -> -0.55265431 | BE42: =SUM(BE19,BE41) -> 0 | BF42: =BF19+BF41 -> 82.293587 | BG42: =IFERROR(BF42/BF$9,0) -> 0.17829597 | BH42: =$AO42-BF42 -> 13.54314 | BI42: =IFERROR(AO42/BF42-1,"") -> 0.16457102 | BJ42: =IF(BI42>0.05,1,IF(BI42<-0.05,-1,0)) -> 1
Q43: =IFERROR(K43/N43-1,"") | AU43: =IFERROR(AO43/AR43-1,"")
C45: BGT
C46: Capex Target | N46: =O46*N9 -> -9.6110155 | O46: -0.085 | AR46: =AS46*AR9 -> -46.044141 | AS46: -0.085
C47: Ajuste Ativacao | N47: =N46-N48 -> -9.151419 | O47: =N47/N9 -> -0.080935321 | AR47: =AR46-AR48 -> -43.559139 | AS47: =AR47/AR9 -> -0.080412551
C48: Capex s/Ativação | N48: -0.45959642 | O48: =N48/N10 -> 0.012010804 | AR48: -2.4850015 | AS48: =AR48/AR10 -> 0.013582493

Sheet Painel Resultado (MTD)
C2: 1000000
C3: ='P&L Contábil'!$C$3 -> 46143
E4: Net Revenue | U4: Adj. Ebitda | AO4: Capex | BI4: Adj. Ebitda After Capex | CC4: Net Revenue
E6: Net Sales | F6: Net Sales | P6: Net Sales | U6: Adjusted EBITDA | W6: Adjusted EBITDA | AI6: Adjusted EBITDA | AO6: Capex | AQ6: Capex | BC6: Capex
E7: Actual | F7: Budget | P7: Actual | U7: Actual | W7: Budget | AI7: Actual | AO7: Actual | AQ7: Budget | BC7: Actual
E8: =YEAR($C$3) -> 2026 | F8: =E8 -> 2026 | P8: =F8-1 -> 2025 | U8: =YEAR($C$3) -> 2026 | W8: =U8 -> 2026 | AI8: =W8-1 -> 2025 | AO8: =YEAR($C$3) -> 2026 | AQ8: =AO8 -> 2026 | BC8: =AQ8-1 -> 2025
B9: [ BRL M ] | E9: Actual | F9: Budget | G9: ∆ | H9: ∆% | K9: RFC | L9: ∆ | M9: ∆% | P9: LY | Q9: ∆ | R9: ∆% | U9: Actual | V9: %NR | W9: Budget | X9: %NR | Y9: ∆ | Z9: ∆% | AC9: RFC | AD9: %NR | AE9: ∆ | AF9: ∆% | AI9: LY | AJ9: %NR | AK9: ∆ | AL9: ∆% | AO9: Actual | AP9: %NR | AQ9: Budget | AR9: %NR | AS9: ∆ | AT9: ∆% | AW9: RFC | AX9: %NR | AY9: ∆ | AZ9: ∆% | BC9: LY | BD9: %NR | BE9: ∆ | BF9: ∆% | BI9: Actual | BJ9: %NR | BK9: Budget | BL9: %NR | BM9: ∆ | BN9: ∆% | BQ9: RFC | BR9: %NR | BS9: ∆ | BT9: ∆% | BW9: LY | BX9: %NR | BY9: ∆ | BZ9: ∆% | CC9: Flash | CD9: ∆
B11: = | C11: Consolidado nstech | E11: =SUM(E51,E13,E88) -> 113.73467 | F11: =SUM(F51,F13,F88) -> 113.07077 | G11: =$E11-F11 -> 0.66389816 | H11: =IFERROR($E11/F11-1,0) -> 0.0058715277 | I11: =H11 -> 0.0058715277 | K11: =SUM(K51,K13,K88) -> 111.61943 | L11: =$E11-K11 -> 2.1152409 | M11: =IFERROR($E11/K11-1,0) -> 0.018950473 | N11: =M11 -> 0.018950473 | P11: =SUM(P51,P13,P88) -> 95.185544 | Q11: =$E11-P11 -> 18.549124 | R11: =IFERROR($E11/P11-1,0) -> 0.19487333 | S11: =R11 -> 0.19487333 | U11: =SUM(U51,U13,U88) -> 34.075192 | V11: =IFERROR(U11/$E11,0) -> 0.29960251 | W11: =SUM(W51,W13,W88) -> 17.619959 | X11: =IFERROR(W11/$F11,0) -> 0.15583125 | Y11: =$U11-W11 -> 16.455233 | Z11: =IFERROR($U11/W11-1,0) -> 0.93389734 | AA11: =Z11 -> 0.93389734 | AC11: =SUM(AC51,AC13,AC88) -> 28.200049 | AD11: =IFERROR(AC11/$P11,0) -> 0.29626399 | AE11: =$U11-AC11 -> 5.8751425 | AF11: =IFERROR($U11/AC11-1,0) -> 0.20833802 | AG11: =AF11 -> 0.20833802 | AI11: =SUM(AI51,AI13,AI88) -> 22.729355 | AJ11: =IFERROR(AI11/$P11,0) -> 0.23878999 | AK11: =$U11-AI11 -> 11.345837 | AL11: =IFERROR($U11/AI11-1,0) -> 0.4991711 | AM11: =AL11 -> 0.4991711 | AO11: =SUM(AO51,AO13,AO88) -> -12.111835 | AP11: =IFERROR(AO11/$E11,0) -> -0.10649203 | AQ11: =SUM(AQ51,AQ13,AQ88) -> -0.45959642 | AR11: =IFERROR(AQ11/$F11,0) -> -0.0040646794 | AS11: =$AO11-AQ11 -> -11.652239 | AT11: =IFERROR($AO11/AQ11-1,0) -> 25.353198 | AU11: =AT11 -> 25.353198 | AW11: =SUM(AW51,AW13,AW88) -> -10.470946 | AX11: =IFERROR(AW11/$P11,0) -> -0.11000564 | AY11: =$AO11-AW11 -> -1.6408889 | AZ11: =IFERROR($AO11/AW11-1,0) -> 0.15670875 | BA11: =AZ11 -> 0.15670875 | BC11: =SUM(BC51,BC13,BC88) -> -3.8148089 | BD11: =IFERROR(BC11/$P11,0) -> -0.040077608 | BE11: =$AO11-BC11 -> -8.2970264 | BF11: =IFERROR($AO11/BC11-1,0) -> 2.1749521 | BG11: =BF11 -> 2.1749521 | BI11: =SUM(BI51,BI13,BI88) -> 21.963356 | BJ11: =IFERROR(BI11/$E11,0) -> 0.19311048 | BK11: =SUM(BK51,BK13,BK88) -> 17.160363 | BL11: =IFERROR(BK11/$F11,0) -> 0.15176657 | BM11: =$BI11-BK11 -> 4.802994 | BN11: =BM11/ABS(BK11) -> 0.27988884 | BO11: =BN11 -> 0.27988884 | BQ11: =SUM(BQ51,BQ13,BQ88) -> 17.729103 | BR11: =IFERROR(BQ11/$P11,0) -> 0.18625836 | BS11: =$BI11-BQ11 -> 4.2342536 | BT11: =IFERROR(BS11/ABS(BQ11),"") -> 0.23883067 | BU11: =BT11 -> 0.23883067 | BW11: =SUM(BW51,BW13,BW88) -> 18.914546 | BX11: =IFERROR(BW11/$P11,0) -> 0.19871238 | BY11: =$BI11-BW11 -> 3.0488105 | BZ11: =IFERROR(BY11/ABS(BW11),"") -> 0.16118867 | CA11: =BZ11 -> 0.16118867 | CC11: =SUM(CC51,CC13,CC88) -> 113.17039 | CD11: =$E11-CC11 -> 0.56427821
B13: 1 | C13: Consolidado PSL | E13: =SUM(E47:E49,E42,E40,E14,E45,E30) -> 51.660081 | F13: =SUM(F47:F49,F42,F40,F14,F45,F30) -> 51.246121 | G13: =$E13-F13 -> 0.41395998 | H13: =IFERROR($E13/F13-1,0) -> 0.0080778793 | I13: =H13 -> 0.0080778793 | K13: =SUM(K47:K49,K42,K40,K14,K45,K30) -> 51.247609 | L13: =$E13-K13 -> 0.41247229 | M13: =IFERROR($E13/K13-1,0) -> 0.0080486153 | N13: =M13 -> 0.0080486153 | P13: =SUM(P47:P49,P42,P40,P14,P45,P30) -> 42.076201 | Q13: =$E13-P13 -> 9.5838801 | R13: =IFERROR($E13/P13-1,0) -> 0.22777437 | S13: =R13 -> 0.22777437 | U13: =SUM(U47:U49,U42,U40,U14,U45,U30) -> 28.246903 | V13: =IFERROR(U13/$E13,0) -> 0.54678395 | W13: =SUM(W47:W49,W42,W40,W14,W45,W30) -> 19.336203 | X13: =IFERROR(W13/$F13,0) -> 0.37732032 | Y13: =$U13-W13 -> 8.9107003 | Z13: =IFERROR($U13/W13-1,0) -> 0.46082989 | AA13: =Z13 -> 0.46082989 | AC13: =SUM(AC47:AC49,AC42,AC40,AC14,AC45,AC30) -> 28.049643 | AD13: =IFERROR(AC13/$P13,0) -> 0.66663914 | AE13: =$U13-AC13 -> 0.19726068 | AF13: =IFERROR($U13/AC13-1,0) -> 0.0070325559 | AG13: =AF13 -> 0.0070325559 | AI13: =SUM(AI47:AI49,AI42,AI40,AI14,AI45,AI30) -> 17.431653 | AJ13: =IFERROR(AI13/$P13,0) -> 0.41428771 | AK13: =$U13-AI13 -> 10.81525 | AL13: =IFERROR($U13/AI13-1,0) -> 0.62043746 | AM13: =AL13 -> 0.62043746 | AO13: =SUM(AO47:AO49,AO42,AO40,AO14,AO45,AO30) -> -8.9636222 | AP13: =IFERROR(AO13/$E13,0) -> -0.17351158 | AQ13: =SUM(AQ47:AQ49,AQ42,AQ40,AQ14,AQ45,AQ30) -> -0.39462914 | AR13: =IFERROR(AQ13/$F13,0) -> -0.0077006636 | AS13: =$AO13-AQ13 -> -8.568993 | AT13: =IFERROR($AO13/AQ13-1,0) -> 21.71404 | AU13: =AT13 -> 21.71404 | AW13: =SUM(AW47:AW49,AW42,AW40,AW14,AW45,AW30) -> -8.7441718 | AX13: =IFERROR(AW13/$P13,0) -> -0.20781752 | AY13: =$AO13-AW13 -> -0.21945039 | AZ13: =IFERROR($AO13/AW13-1,0) -> 0.025096761 | BA13: =AZ13 -> 0.025096761 | BC13: =SUM(BC47:BC49,BC42,BC40,BC14,BC45,BC30) -> -1.69894 | BD13: =IFERROR(BC13/$P13,0) -> -0.040377693 | BE13: =$AO13-BC13 -> -7.2646822 | BF13: =IFERROR($AO13/BC13-1,0) -> 4.2760088 | BG13: =BF13 -> 4.2760088 | BI13: =SUM(BI47:BI49,BI42,BI40,BI14,BI45,BI30) -> 19.283281 | BJ13: =IFERROR(BI13/$E13,0) -> 0.37327237 | BK13: =SUM(BK47:BK49,BK42,BK40,BK14,BK45,BK30) -> 18.941574 | BL13: =IFERROR(BK13/$F13,0) -> 0.36961966 | BM13: =$BI13-BK13 -> 0.34170728 | BN13: =BM13/ABS(BK13) -> 0.018040068 | BO13: =BN13 -> 0.018040068 | BQ13: =SUM(BQ47:BQ49,BQ42,BQ40,BQ14,BQ45,BQ30) -> 19.305471 | BR13: =IFERROR(BQ13/$P13,0) -> 0.45882162 | BS13: =$BI13-BQ13 -> -0.022189705 | BT13: =IFERROR(BS13/ABS(BQ13),"") -> -0.0011493998 | BU13: =BT13 -> -0.0011493998 | BW13: =SUM(BW47:BW49,BW42,BW40,BW14,BW45,BW30) -> 15.732713 | BX13: =IFERROR(BW13/$P13,0) -> 0.37391001 | BY13: =$BI13-BW13 -> 3.5505683 | BZ13: =IFERROR(BY13/ABS(BW13),"") -> 0.22568061 | CA13: =BZ13 -> 0.22568061 | CC13: =SUM(CC47:CC49,CC42,CC40,CC14,CC45,CC30) -> 51.635762 | CD13: =$E13-CC13 -> 0.02431927
B14: 1.1 | C14: Torre TMS | E14: =E15+E20+E29 -> 25.651114 | F14: =F15+F20+F29 -> 25.30685 | G14: =$E14-F14 -> 0.3442645 | H14: =IFERROR($E14/F14-1,0) -> 0.013603609 | I14: =H14 -> 0.013603609 | K14: =K15+K20+K29 -> 25.446828 | L14: =$E14-K14 -> 0.20428659 | M14: =IFERROR($E14/K14-1,0) -> 0.0080279785 | N14: =M14 -> 0.0080279785 | P14: =P15+P20+P29 -> 20.618384 | Q14: =$E14-P14 -> 5.0327305 | R14: =IFERROR($E14/P14-1,0) -> 0.24408948 | S14: =R14 -> 0.24408948 | U14: =U15+U20+U29 -> 14.728183 | V14: =IFERROR(U14/$E14,0) -> 0.57417322 | W14: =W15+W20+W29 -> 10.03465 | X14: =IFERROR(W14/$F14,0) -> 0.39651914 | Y14: =$U14-W14 -> 4.6935326 | Z14: =IFERROR($U14/W14-1,0) -> 0.46773254 | AA14: =Z14 -> 0.46773254 | AC14: =AC15+AC20+AC29 -> 15.094052 | AD14: =IFERROR(AC14/$P14,0) -> 0.73206766 | AE14: =$U14-AC14 -> -0.36586902 | AF14: =IFERROR($U14/AC14-1,0) -> -0.024239284 | AG14: =AF14 -> -0.024239284 | AI14: =AI15+AI20+AI29 -> 8.9857383 | AJ14: =IFERROR(AI14/$P14,0) -> 0.43581196 | AK14: =$U14-AI14 -> 5.7424447 | AL14: =IFERROR($U14/AI14-1,0) -> 0.63906209 | AM14: =AL14 -> 0.63906209 | AO14: =AO15+AO20+AO29 -> -5.7033915 | AP14: =IFERROR(AO14/$E14,0) -> -0.22234478 | AQ14: =AQ15+AQ20+AQ29 -> -0.003 | AR14: =IFERROR(AQ14/$F14,0) -> -0.00011854498 | AS14: =$AO14-AQ14 -> -5.7003915 | AT14: =IFERROR($AO14/AQ14-1,0) -> 1900.1305 | AU14: =AT14 -> 1900.1305 | AW14: =AW15+AW20+AW29 -> -5.5833781 | AX14: =IFERROR(AW14/$P14,0) -> -0.27079611 | AY14: =$AO14-AW14 -> -0.12001338 | AZ14: =IFERROR($AO14/AW14-1,0) -> 0.021494762 | BA14: =AZ14 -> 0.021494762 | BC14: =BC15+BC20+BC29 -> -1.1578482 | BD14: =IFERROR(BC14/$P14,0) -> -0.056156108 | BE14: =$AO14-BC14 -> -4.5455433 | BF14: =IFERROR($AO14/BC14-1,0) -> 3.9258543 | BG14: =BF14 -> 3.9258543 | BI14: =BI15+BI20+BI29 -> 9.0247915 | BJ14: =IFERROR(BI14/$E14,0) -> 0.35182844 | BK14: =BK15+BK20+BK29 -> 10.03165 | BL14: =IFERROR(BK14/$F14,0) -> 0.3964006 | BM14: =$BI14-BK14 -> -1.0068589 | BN14: =BM14/ABS(BK14) -> -0.10036822 | BO14: =BN14 -> -0.10036822 | BQ14: =BQ15+BQ20+BQ29 -> 9.5106739 | BR14: =IFERROR(BQ14/$P14,0) -> 0.46127155 | BS14: =$BI14-BQ14 -> -0.4858824 | BT14: =IFERROR(BS14/ABS(BQ14),"") -> -0.051088114 | BU14: =BT14 -> -0.051088114 | BW14: =BW15+BW20+BW29 -> 7.8278901 | BX14: =IFERROR(BW14/$P14,0) -> 0.37965585 | BY14: =$BI14-BW14 -> 1.1969014 | BZ14: =IFERROR(BY14/ABS(BW14),"") -> 0.15290217 | CA14: =BZ14 -> 0.15290217 | CC14: =CC15+CC20+CC29 -> 25.62645 | CD14: =$E14-CC14 -> 0.024664012
B15: 1.1.1 | C15: Torre ICP Pequeno e Micro | E15: =SUM(E16:E19) -> 12.433257 | F15: =SUM(F16:F19) -> 11.293878 | G15: =$E15-F15 -> 1.1393781 | H15: =IFERROR($E15/F15-1,0) -> 0.10088457 | I15: =H15 -> 0.10088457 | K15: =SUM(K16:K19) -> 12.239777 | L15: =$E15-K15 -> 0.19347997 | M15: =IFERROR($E15/K15-1,0) -> 0.015807475 | N15: =M15 -> 0.015807475 | P15: =SUM(P16:P19) -> 9.2389702 | Q15: =$E15-P15 -> 3.1942863 | R15: =IFERROR($E15/P15-1,0) -> 0.34574052 | S15: =R15 -> 0.34574052 | U15: =SUM(U16:U19) -> 10.026409 | V15: =IFERROR(U15/$E15,0) -> 0.80641858 | W15: =SUM(W16:W19) -> 6.5063722 | X15: =IFERROR(W15/$F15,0) -> 0.57609724 | Y15: =$U15-W15 -> 3.5200369 | Z15: =IFERROR($U15/W15-1,0) -> 0.54101376 | AA15: =Z15 -> 0.54101376 | AC15: =SUM(AC16:AC19) -> 10.015085 | AD15: =IFERROR(AC15/$P15,0) -> 1.0840045 | AE15: =$U15-AC15 -> 0.011323914 | AF15: =IFERROR($U15/AC15-1,0) -> 0.0011306857 | AG15: =AF15 -> 0.0011306857 | AI15: =SUM(AI16:AI19) -> 5.373218 | AJ15: =IFERROR(AI15/$P15,0) -> 0.58158192 | AK15: =$U15-AI15 -> 4.653191 | AL15: =IFERROR($U15/AI15-1,0) -> 0.86599706 | AM15: =AL15 -> 0.86599706 | AO15: =SUM(AO16:AO19) -> -2.8967663 | AP15: =IFERROR(AO15/$E15,0) -> -0.23298532 | AQ15: =SUM(AQ16:AQ19) -> -0.003 | AR15: =IFERROR(AQ15/$F15,0) -> -0.00026563062 | AS15: =$AO15-AQ15 -> -2.8937663 | AT15: =IFERROR($AO15/AQ15-1,0) -> 964.58876 | AU15: =AT15 -> 964.58876 | AW15: =SUM(AW16:AW19) -> -2.7485476 | AX15: =IFERROR(AW15/$P15,0) -> -0.29749502 | AY15: =$AO15-AW15 -> -0.14821868 | AZ15: =IFERROR($AO15/AW15-1,0) -> 0.053926184 | BA15: =AZ15 -> 0.053926184 | BC15: =SUM(BC16:BC19) -> -0.5087855 | BD15: =IFERROR(BC15/$P15,0) -> -0.055069503 | BE15: =$AO15-BC15 -> -2.3879808 | BF15: =IFERROR($AO15/BC15-1,0) -> 4.6934922 | BG15: =BF15 -> 4.6934922 | BI15: =SUM(BI16:BI19) -> 7.1296428 | BJ15: =IFERROR(BI15/$E15,0) -> 0.57343326 | BK15: =SUM(BK16:BK19) -> 6.5033722 | BL15: =IFERROR(BK15/$F15,0) -> 0.5758316 | BM15: =$BI15-BK15 -> 0.62627062 | BN15: =BM15/ABS(BK15) -> 0.096299367 | BO15: =BN15 -> 0.096299367 | BQ15: =SUM(BQ16:BQ19) -> 7.2665376 | BR15: =IFERROR(BQ15/$P15,0) -> 0.78650947 | BS15: =$BI15-BQ15 -> -0.13689477 | BT15: =IFERROR(BS15/ABS(BQ15),"") -> -0.018839064 | BU15: =BT15 -> -0.018839064 | BW15: =SUM(BW16:BW19) -> 4.8644325 | BX15: =IFERROR(BW15/$P15,0) -> 0.52651242 | BY15: =$BI15-BW15 -> 2.2652103 | BZ15: =IFERROR(BY15/ABS(BW15),"") -> 0.46566793 | CA15: =BZ15 -> 0.46566793 | CC15: =SUM(CC16:CC19) -> 12.433257 | CD15: =$E15-CC15 -> 0
B16: 1.1.1.1 | C16: Bsoft | E16: 8.6385421 | F16: 8.1078386 | G16: =$E16-F16 -> 0.53070347 | H16: =IFERROR($E16/F16-1,0) -> 0.065455604 | I16: =H16 -> 0.065455604 | K16: 9.1908735 | L16: =$E16-K16 -> -0.55233143 | M16: =IFERROR($E16/K16-1,0) -> -0.06009564 | N16: =M16 -> -0.06009564 | P16: 6.3430565 | Q16: =$E16-P16 -> 2.2954856 | R16: =IFERROR($E16/P16-1,0) -> 0.36188951 | S16: =R16 -> 0.36188951 | U16: 7.4176796 | V16: =IFERROR(U16/$E16,0) -> 0.85867262 | W16: 5.1551641 | X16: =IFERROR(W16/$F16,0) -> 0.6358247 | Y16: =$U16-W16 -> 2.2625155 | Z16: =IFERROR($U16/W16-1,0) -> 0.43888332 | AA16: =Z16 -> 0.43888332 | AC16: 8.1323104 | AD16: =IFERROR(AC16/$P16,0) -> 1.2820807 | AE16: =$U16-AC16 -> -0.71463082 | AF16: =IFERROR($U16/AC16-1,0) -> -0.087875497 | AG16: =AF16 -> -0.087875497 | AI16: 4.0242262 | AJ16: =IFERROR(AI16/$P16,0) -> 0.63443014 | AK16: =$U16-AI16 -> 3.3934533 | AL16: =IFERROR($U16/AI16-1,0) -> 0.84325611 | AM16: =AL16 -> 0.84325611 | AO16: -2.0709912 | AP16: =IFERROR(AO16/$E16,0) -> -0.2397385 | AQ16: 0 | AR16: =IFERROR(AQ16/$F16,0) -> 0 | AS16: =$AO16-AQ16 -> -2.0709912 | AT16: =IFERROR($AO16/AQ16-1,0) -> 0 | AU16: =AT16 -> 0 | AW16: -2.0768442 | AX16: =IFERROR(AW16/$P16,0) -> -0.32742009 | AY16: =$AO16-AW16 -> 0.005853005 | AZ16: =IFERROR($AO16/AW16-1,0) -> -0.0028182206 | BA16: =AZ16 -> -0.0028182206 | BC16: -0.3488736 | BD16: =IFERROR(BC16/$P16,0) -> -0.055000866 | BE16: =$AO16-BC16 -> -1.7221176 | BF16: =IFERROR($AO16/BC16-1,0) -> 4.936222 | BG16: =BF16 -> 4.936222 | BI16: =SUM(U16,AO16) -> 5.3466884 | BJ16: =IFERROR(BI16/$E16,0) -> 0.61893412 | BK16: =SUM(W16,AQ16) -> 5.1551641 | BL16: =IFERROR(BK16/$F16,0) -> 0.6358247 | BM16: =$BI16-BK16 -> 0.19152436 | BN16: =BM16/ABS(BK16) -> 0.037151942 | BO16: =BN16 -> 0.037151942 | BQ16: =SUM(AC16,AW16) -> 6.0554662 | BR16: =IFERROR(BQ16/$P16,0) -> 0.95466062 | BS16: =$BI16-BQ16 -> -0.70877781 | BT16: =IFERROR(BS16/ABS(BQ16),"") -> -0.1170476 | BU16: =BT16 -> -0.1170476 | BW16: =SUM(AI16,BC16) -> 3.6753526 | BX16: =IFERROR(BW16/$P16,0) -> 0.57942928 | BY16: =$BI16-BW16 -> 1.6713358 | BZ16: =IFERROR(BY16/ABS(BW16),"") -> 0.45474162 | CA16: =BZ16 -> 0.45474162 | CC16: 8.6385421 | CD16: =$E16-CC16 -> 0
B17: 1.1.1.2 | C17: Datamex | E17: 1.5535898 | F17: 0.9962509 | G17: =$E17-F17 -> 0.55733888 | H17: =IFERROR($E17/F17-1,0) -> 0.55943627 | I17: =H17 -> 0.55943627 | K17: 0.9962509 | L17: =$E17-K17 -> 0.55733888 | M17: =IFERROR($E17/K17-1,0) -> 0.55943627 | N17: =M17 -> 0.55943627 | P17: 1.2616618 | Q17: =$E17-P17 -> 0.291928 | R17: =IFERROR($E17/P17-1,0) -> 0.23138372 | S17: =R17 -> 0.23138372 | U17: 0.72179059 | V17: =IFERROR(U17/$E17,0) -> 0.46459535 | W17: 0.197022 | X17: =IFERROR(W17/$F17,0) -> 0.19776343 | Y17: =$U17-W17 -> 0.52476859 | Z17: =IFERROR($U17/W17-1,0) -> 2.6635025 | AA17: =Z17 -> 2.6635025 | AC17: 0.34860848 | AD17: =IFERROR(AC17/$P17,0) -> 0.27630898 | AE17: =$U17-AC17 -> 0.37318211 | AF17: =IFERROR($U17/AC17-1,0) -> 1.0704906 | AG17: =AF17 -> 1.0704906 | AI17: 0.49049678 | AJ17: =IFERROR(AI17/$P17,0) -> 0.38877042 | AK17: =$U17-AI17 -> 0.23129381 | AL17: =IFERROR($U17/AI17-1,0) -> 0.47155011 | AM17: =AL17 -> 0.47155011 | AO17: -0.25273944 | AP17: =IFERROR(AO17/$E17,0) -> -0.16268094 | AQ17: 0 | AR17: =IFERROR(AQ17/$F17,0) -> 0 | AS17: =$AO17-AQ17 -> -0.25273944 | AT17: =IFERROR($AO17/AQ17-1,0) -> 0 | AU17: =AT17 -> 0 | AW17: -0.15158648 | AX17: =IFERROR(AW17/$P17,0) -> -0.12014827 | AY17: =$AO17-AW17 -> -0.10115296 | AZ17: =IFERROR($AO17/AW17-1,0) -> 0.66729541 | BA17: =AZ17 -> 0.66729541 | BC17: -0.1599119 | BD17: =IFERROR(BC17/$P17,0) -> -0.12674704 | BE17: =$AO17-BC17 -> -0.09282754 | BF17: =IFERROR($AO17/BC17-1,0) -> 0.58049176 | BG17: =BF17 -> 0.58049176 | BI17: =SUM(U17,AO17) -> 0.46905115 | BJ17: =IFERROR(BI17/$E17,0) -> 0.30191442 | BK17: =SUM(W17,AQ17) -> 0.197022 | BL17: =IFERROR(BK17/$F17,0) -> 0.19776343 | BM17: =$BI17-BK17 -> 0.27202915 | BN17: =BM17/ABS(BK17) -> 1.3807044 | BO17: =BN17 -> 1.3807044 | BQ17: =SUM(AC17,AW17) -> 0.197022 | BR17: =IFERROR(BQ17/$P17,0) -> 0.15616071 | BS17: =$BI17-BQ17 -> 0.27202915 | BT17: =IFERROR(BS17/ABS(BQ17),"") -> 1.3807044 | BU17: =BT17 -> 1.3807044 | BW17: =SUM(AI17,BC17) -> 0.33058488 | BX17: =IFERROR(BW17/$P17,0) -> 0.26202338 | BY17: =$BI17-BW17 -> 0.13846627 | BZ17: =IFERROR(BY17/ABS(BW17),"") -> 0.4188524 | CA17: =BZ17 -> 0.4188524 | CC17: 1.5535898 | CD17: =$E17-CC17 -> 0
B18: 1.1.1.3 | C18: Hivecloud | E18: 1.9911229 | F18: 1.8918697 | G18: =$E18-F18 -> 0.099253227 | H18: =IFERROR($E18/F18-1,0) -> 0.052463036 | I18: =H18 -> 0.052463036 | K18: 1.819628 | L18: =$E18-K18 -> 0.17149488 | M18: =IFERROR($E18/K18-1,0) -> 0.094247221 | N18: =M18 -> 0.094247221 | P18: 1.3780193 | Q18: =$E18-P18 -> 0.61310357 | R18: =IFERROR($E18/P18-1,0) -> 0.44491652 | S18: =R18 -> 0.44491652 | U18: 1.8310186 | V18: =IFERROR(U18/$E18,0) -> 0.91959097 | W18: 1.061893 | X18: =IFERROR(W18/$F18,0) -> 0.5612929 | Y18: =$U18-W18 -> 0.76912561 | Z18: =IFERROR($U18/W18-1,0) -> 0.7242967 | AA18: =Z18 -> 0.7242967 | AC18: 1.5067683 | AD18: =IFERROR(AC18/$P18,0) -> 1.0934305 | AE18: =$U18-AC18 -> 0.3242503 | AF18: =IFERROR($U18/AC18-1,0) -> 0.21519586 | AG18: =AF18 -> 0.21519586 | AI18: 0.7901449 | AJ18: =IFERROR(AI18/$P18,0) -> 0.57339174 | AK18: =$U18-AI18 -> 1.0408737 | AL18: =IFERROR($U18/AI18-1,0) -> 1.31732 | AM18: =AL18 -> 1.31732 | AO18: -0.57303569 | AP18: =IFERROR(AO18/$E18,0) -> -0.28779524 | AQ18: -0.003 | AR18: =IFERROR(AQ18/$F18,0) -> -0.0015857329 | AS18: =$AO18-AQ18 -> -0.57003569 | AT18: =IFERROR($AO18/AQ18-1,0) -> 190.0119 | AU18: =AT18 -> 190.0119 | AW18: -0.52011696 | AX18: =IFERROR(AW18/$P18,0) -> -0.37743808 | AY18: =$AO18-AW18 -> -0.052918727 | AZ18: =IFERROR($AO18/AW18-1,0) -> 0.1017439 | BA18: =AZ18 -> 0.1017439 | BC18: 0 | BD18: =IFERROR(BC18/$P18,0) -> 0 | BE18: =$AO18-BC18 -> -0.57303569 | BF18: =IFERROR($AO18/BC18-1,0) -> 0 | BG18: =BF18 -> 0 | BI18: =SUM(U18,AO18) -> 1.2579829 | BJ18: =IFERROR(BI18/$E18,0) -> 0.63179572 | BK18: =SUM(W18,AQ18) -> 1.058893 | BL18: =IFERROR(BK18/$F18,0) -> 0.55970717 | BM18: =$BI18-BK18 -> 0.19908992 | BN18: =BM18/ABS(BK18) -> 0.18801703 | BO18: =BN18 -> 0.18801703 | BQ18: =SUM(AC18,AW18) -> 0.98665135 | BR18: =IFERROR(BQ18/$P18,0) -> 0.7159924 | BS18: =$BI18-BQ18 -> 0.27133157 | BT18: =IFERROR(BS18/ABS(BQ18),"") -> 0.27500248 | BU18: =BT18 -> 0.27500248 | BW18: =SUM(AI18,BC18) -> 0.7901449 | BX18: =IFERROR(BW18/$P18,0) -> 0.57339174 | BY18: =$BI18-BW18 -> 0.46783803 | BZ18: =IFERROR(BY18/ABS(BW18),"") -> 0.59209143 | CA18: =BZ18 -> 0.59209143 | CC18: 1.9911229 | CD18: =$E18-CC18 -> 0
B19: 1.1.1.4 | C19: Otimizy | E19: 0.25000182 | F19: 0.29791931 | G19: =$E19-F19 -> -0.047917493 | H19: =IFERROR($E19/F19-1,0) -> -0.1608405 | I19: =H19 -> -0.1608405 | K19: 0.23302419 | L19: =$E19-K19 -> 0.016977627 | M19: =IFERROR($E19/K19-1,0) -> 0.072857788 | N19: =M19 -> 0.072857788 | P19: 0.25623264 | Q19: =$E19-P19 -> -0.00623082 | R19: =IFERROR($E19/P19-1,0) -> -0.024317043 | S19: =R19 -> -0.024317043 | U19: 0.055920294 | V19: =IFERROR(U19/$E19,0) -> 0.22367955 | W19: 0.092293095 | X19: =IFERROR(W19/$F19,0) -> 0.30979225 | Y19: =$U19-W19 -> -0.036372801 | Z19: =IFERROR($U19/W19-1,0) -> -0.394101 | AA19: =Z19 -> -0.394101 | AC19: 0.027397975 | AD19: =IFERROR(AC19/$P19,0) -> 0.10692617 | AE19: =$U19-AC19 -> 0.028522319 | AF19: =IFERROR($U19/AC19-1,0) -> 1.0410375 | AG19: =AF19 -> 1.0410375 | AI19: 0.06835014 | AJ19: =IFERROR(AI19/$P19,0) -> 0.26675033 | AK19: =$U19-AI19 -> -0.012429846 | AL19: =IFERROR($U19/AI19-1,0) -> -0.18185546 | AM19: =AL19 -> -0.18185546 | AO19: 0 | AP19: =IFERROR(AO19/$E19,0) -> 0 | AQ19: 0 | AR19: =IFERROR(AQ19/$F19,0) -> 0 | AS19: =$AO19-AQ19 -> 0 | AT19: =IFERROR($AO19/AQ19-1,0) -> 0 | AU19: =AT19 -> 0 | AW19: 0 | AX19: =IFERROR(AW19/$P19,0) -> 0 | AY19: =$AO19-AW19 -> 0 | AZ19: =IFERROR($AO19/AW19-1,0) -> 0 | BA19: =AZ19 -> 0 | BC19: 0 | BD19: =IFERROR(BC19/$P19,0) -> 0 | BE19: =$AO19-BC19 -> 0 | BF19: =IFERROR($AO19/BC19-1,0) -> 0 | BG19: =BF19 -> 0 | BI19: =SUM(U19,AO19) -> 0.055920294 | BJ19: =IFERROR(BI19/$E19,0) -> 0.22367955 | BK19: =SUM(W19,AQ19) -> 0.092293095 | BL19: =IFERROR(BK19/$F19,0) -> 0.30979225 | BM19: =$BI19-BK19 -> -0.036372801 | BN19: =BM19/ABS(BK19) -> -0.394101 | BO19: =BN19 -> -0.394101 | BQ19: =SUM(AC19,AW19) -> 0.027397975 | BR19: =IFERROR(BQ19/$P19,0) -> 0.10692617 | BS19: =$BI19-BQ19 -> 0.028522319 | BT19: =IFERROR(BS19/ABS(BQ19),"") -> 1.0410375 | BU19: =BT19 -> 1.0410375 | BW19: =SUM(AI19,BC19) -> 0.06835014 | BX19: =IFERROR(BW19/$P19,0) -> 0.26675033 | BY19: =$BI19-BW19 -> -0.012429846 | BZ19: =IFERROR(BY19/ABS(BW19),"") -> -0.18185546 | CA19: =BZ19 -> -0.18185546 | CC19: 0.25000182 | CD19: =$E19-CC19 -> 0
B20: 1.1.2 | C20: Torre ICP Médio e Grande | E20: =SUM(E21,E26:E28) -> 10.877396 | F20: =SUM(F21,F26:F28) -> 11.688608 | G20: =$E20-F20 -> -0.81121215 | H20: =IFERROR($E20/F20-1,0) -> -0.069401944 | I20: =H20 -> -0.069401944 | K20: =SUM(K21,K26:K28) -> 10.888323 | L20: =$E20-K20 -> -0.010926389 | M20: =IFERROR($E20/K20-1,0) -> -0.0010034961 | N20: =M20 -> -0.0010034961 | P20: =SUM(P21,P26:P28) -> 9.5936247 | Q20: =$E20-P20 -> 1.2837716 | R20: =IFERROR($E20/P20-1,0) -> 0.13381507 | S20: =R20 -> 0.13381507 | U20: =SUM(U21,U26:U28) -> 3.9666922 | V20: =IFERROR(U20/$E20,0) -> 0.36467295 | W20: =SUM(W21,W26:W28) -> 2.9552578 | X20: =IFERROR(W20/$F20,0) -> 0.2528323 | Y20: =$U20-W20 -> 1.0114343 | Z20: =IFERROR($U20/W20-1,0) -> 0.34224911 | AA20: =Z20 -> 0.34224911 | AC20: =SUM(AC21,AC26:AC28) -> 4.470146 | AD20: =IFERROR(AC20/$P20,0) -> 0.46594964 | AE20: =$U20-AC20 -> -0.50345382 | AF20: =IFERROR($U20/AC20-1,0) -> -0.11262581 | AG20: =AF20 -> -0.11262581 | AI20: =SUM(AI21,AI26:AI28) -> 2.945548 | AJ20: =IFERROR(AI20/$P20,0) -> 0.30703181 | AK20: =$U20-AI20 -> 1.0211442 | AL20: =IFERROR($U20/AI20-1,0) -> 0.34667375 | AM20: =AL20 -> 0.34667375 | AO20: =SUM(AO21,AO26:AO28) -> -2.8066252 | AP20: =IFERROR(AO20/$E20,0) -> -0.25802362 | AQ20: =SUM(AQ21,AQ26:AQ28) -> 0 | AR20: =IFERROR(AQ20/$F20,0) -> 0 | AS20: =$AO20-AQ20 -> -2.8066252 | AT20: =IFERROR($AO20/AQ20-1,0) -> 0 | AU20: =AT20 -> 0 | AW20: =SUM(AW21,AW26:AW28) -> -2.8348305 | AX20: =IFERROR(AW20/$P20,0) -> -0.29549108 | AY20: =$AO20-AW20 -> 0.028205301 | AZ20: =IFERROR($AO20/AW20-1,0) -> -0.0099495547 | BA20: =AZ20 -> -0.0099495547 | BC20: =SUM(BC21,BC26:BC28) -> -0.64985169 | BD20: =IFERROR(BC20/$P20,0) -> -0.067737868 | BE20: =$AO20-BC20 -> -2.1567735 | BF20: =IFERROR($AO20/BC20-1,0) -> 3.3188704 | BG20: =BF20 -> 3.3188704 | BI20: =SUM(BI21,BI26:BI28) -> 1.160067 | BJ20: =IFERROR(BI20/$E20,0) -> 0.10664932 | BK20: =SUM(BK21,BK26:BK28) -> 2.9552578 | BL20: =IFERROR(BK20/$F20,0) -> 0.2528323 | BM20: =$BI20-BK20 -> -1.7951909 | BN20: =BM20/ABS(BK20) -> -0.6074566 | BO20: =BN20 -> -0.6074566 | BQ20: =SUM(BQ21,BQ26:BQ28) -> 1.6353155 | BR20: =IFERROR(BQ20/$P20,0) -> 0.17045856 | BS20: =$BI20-BQ20 -> -0.47524852 | BT20: =IFERROR(BS20/ABS(BQ20),"") -> -0.2906158 | BU20: =BT20 -> -0.2906158 | BW20: =SUM(BW21,BW26:BW28) -> 2.2956963 | BX20: =IFERROR(BW20/$P20,0) -> 0.23929394 | BY20: =$BI20-BW20 -> -1.1356294 | BZ20: =IFERROR(BY20/ABS(BW20),"") -> -0.49467752 | CA20: =BZ20 -> -0.49467752 | CC20: =SUM(CC21,CC26:CC28) -> 10.852732 | CD20: =$E20-CC20 -> 0.024664012
B21: 1.1.2.1 | C21: TMS MG | E21: =SUM(E22:E25) -> 5.1639922 | F21: =SUM(F22:F25) -> 5.6337033 | G21: =$E21-F21 -> -0.46971112 | H21: =IFERROR($E21/F21-1,0) -> -0.083375197 | I21: =H21 -> -0.083375197 | K21: =SUM(K22:K25) -> 5.1763958 | L21: =$E21-K21 -> -0.012403629 | M21: =IFERROR($E21/K21-1,0) -> -0.0023961903 | N21: =M21 -> -0.0023961903 | P21: =SUM(P22:P25) -> 5.0638424 | Q21: =$E21-P21 -> 0.10014978 | R21: =IFERROR($E21/P21-1,0) -> 0.019777428 | S21: =R21 -> 0.019777428 | U21: =SUM(U22:U25) -> 0.74574553 | V21: =IFERROR(U21/$E21,0) -> 0.1444126 | W21: =SUM(W22:W25) -> -0.5796333 | X21: =IFERROR(W21/$F21,0) -> -0.10288673 | Y21: =$U21-W21 -> 1.3253788 | Z21: =IFERROR($U21/W21-1,0) -> -2.2865816 | AA21: =Z21 -> -2.2865816 | AC21: =SUM(AC22:AC25) -> 1.0144256 | AD21: =IFERROR(AC21/$P21,0) -> 0.20032724 | AE21: =$U21-AC21 -> -0.26868006 | AF21: =IFERROR($U21/AC21-1,0) -> -0.2648593 | AG21: =AF21 -> -0.2648593 | AI21: =SUM(AI22:AI25) -> 0.33389956 | AJ21: =IFERROR(AI21/$P21,0) -> 0.065937984 | AK21: =$U21-AI21 -> 0.41184597 | AL21: =IFERROR($U21/AI21-1,0) -> 1.2334427 | AM21: =AL21 -> 1.2334427 | AO21: =SUM(AO22:AO25) -> -2.5025257 | AP21: =IFERROR(AO21/$E21,0) -> -0.48461067 | AQ21: =SUM(AQ22:AQ25) -> 0 | AR21: =IFERROR(AQ21/$F21,0) -> 0 | AS21: =$AO21-AQ21 -> -2.5025257 | AT21: =IFERROR($AO21/AQ21-1,0) -> 0 | AU21: =AT21 -> 0 | AW21: =SUM(AW22:AW25) -> -2.571023 | AX21: =IFERROR(AW21/$P21,0) -> -0.50772176 | AY21: =$AO21-AW21 -> 0.068497255 | AZ21: =IFERROR($AO21/AW21-1,0) -> -0.026642024 | BA21: =AZ21 -> -0.026642024 | BC21: =SUM(BC22:BC25) -> -0.43206322 | BD21: =IFERROR(BC21/$P21,0) -> -0.085323196 | BE21: =$AO21-BC21 -> -2.0704625 | BF21: =IFERROR($AO21/BC21-1,0) -> 4.792036 | BG21: =BF21 -> 4.792036 | BI21: =SUM(BI22:BI25) -> -1.7567802 | BJ21: =IFERROR(BI21/$E21,0) -> -0.34019807 | BK21: =SUM(BK22:BK25) -> -0.5796333 | BL21: =IFERROR(BK21/$F21,0) -> -0.10288673 | BM21: =$BI21-BK21 -> -1.1771469 | BN21: =BM21/ABS(BK21) -> -2.0308476 | BO21: =BN21 -> -2.0308476 | BQ21: =SUM(BQ22:BQ25) -> -1.5565974 | BR21: =IFERROR(BQ21/$P21,0) -> -0.30739452 | BS21: =$BI21-BQ21 -> -0.2001828 | BT21: =IFERROR(BS21/ABS(BQ21),"") -> -0.12860281 | BU21: =BT21 -> -0.12860281 | BW21: =SUM(BW22:BW25) -> -0.098163658 | BX21: =IFERROR(BW21/$P21,0) -> -0.019385212 | BY21: =$BI21-BW21 -> -1.6586165 | BZ21: =IFERROR(BY21/ABS(BW21),"") -> -16.896442 | CA21: =BZ21 -> -16.896442 | CC21: =SUM(CC22:CC25) -> 5.1639927 | CD21: =$E21-CC21 -> -4.9815336e-07
B22: 1.1.2.1.1 | C22: KMM MG | E22: 3.6143312 | F22: 3.868069 | G22: =$E22-F22 -> -0.25373774 | H22: =IFERROR($E22/F22-1,0) -> -0.06559804 | I22: =H22 -> -0.06559804 | K22: 3.6109241 | L22: =$E22-K22 -> 0.0034070951 | M22: =IFERROR($E22/K22-1,0) -> 0.00094355212 | N22: =M22 -> 0.00094355212 | P22: 3.3344302 | Q22: =$E22-P22 -> 0.279901 | R22: =IFERROR($E22/P22-1,0) -> 0.083942675 | S22: =R22 -> 0.083942675 | U22: 0.45272734 | V22: =IFERROR(U22/$E22,0) -> 0.12525895 | W22: -1.2447401 | X22: =IFERROR(W22/$F22,0) -> -0.32179885 | Y22: =$U22-W22 -> 1.6974675 | Z22: =IFERROR($U22/W22-1,0) -> -1.3637123 | AA22: =Z22 -> -1.3637123 | AC22: 0.54948141 | AD22: =IFERROR(AC22/$P22,0) -> 0.16479019 | AE22: =$U22-AC22 -> -0.096754069 | AF22: =IFERROR($U22/AC22-1,0) -> -0.17608252 | AG22: =AF22 -> -0.17608252 | AI22: -0.22413884 | AJ22: =IFERROR(AI22/$P22,0) -> -0.067219532 | AK22: =$U22-AI22 -> 0.67686618 | AL22: =IFERROR($U22/AI22-1,0) -> -3.0198522 | AM22: =AL22 -> -3.0198522 | AO22: -2.5025257 | AP22: =IFERROR(AO22/$E22,0) -> -0.6923897 | AQ22: 0 | AR22: =IFERROR(AQ22/$F22,0) -> 0 | AS22: =$AO22-AQ22 -> -2.5025257 | AT22: =IFERROR($AO22/AQ22-1,0) -> 0 | AU22: =AT22 -> 0 | AW22: -2.571023 | AX22: =IFERROR(AW22/$P22,0) -> -0.77105316 | AY22: =$AO22-AW22 -> 0.068497255 | AZ22: =IFERROR($AO22/AW22-1,0) -> -0.026642024 | BA22: =AZ22 -> -0.026642024 | BC22: -0.43206322 | BD22: =IFERROR(BC22/$P22,0) -> -0.12957633 | BE22: =$AO22-BC22 -> -2.0704625 | BF22: =IFERROR($AO22/BC22-1,0) -> 4.792036 | BG22: =BF22 -> 4.792036 | BI22: =SUM(U22,AO22) -> -2.0497984 | BJ22: =IFERROR(BI22/$E22,0) -> -0.56713075 | BK22: =SUM(W22,AQ22) -> -1.2447401 | BL22: =IFERROR(BK22/$F22,0) -> -0.32179885 | BM22: =$BI22-BK22 -> -0.80505824 | BN22: =BM22/ABS(BK22) -> -0.64676812 | BO22: =BN22 -> -0.64676812 | BQ22: =SUM(AC22,AW22) -> -2.0215416 | BR22: =IFERROR(BQ22/$P22,0) -> -0.60626297 | BS22: =$BI22-BQ22 -> -0.028256814 | BT22: =IFERROR(BS22/ABS(BQ22),"") -> -0.013977855 | BU22: =BT22 -> -0.013977855 | BW22: =SUM(AI22,BC22) -> -0.65620206 | BX22: =IFERROR(BW22/$P22,0) -> -0.19679586 | BY22: =$BI22-BW22 -> -1.3935963 | BZ22: =IFERROR(BY22/ABS(BW22),"") -> -2.1237305 | CA22: =BZ22 -> -2.1237305 | CC22: 3.6143317 | CD22: =$E22-CC22 -> -4.9815336e-07
B23: 1.1.2.1.2 | C23: ATSLog Outros | E23: 0.37492862 | F23: 0.2914862 | G23: =$E23-F23 -> 0.083442422 | H23: =IFERROR($E23/F23-1,0) -> 0.28626543 | I23: =H23 -> 0.28626543 | K23: 0.46506517 | L23: =$E23-K23 -> -0.090136556 | M23: =IFERROR($E23/K23-1,0) -> -0.19381489 | N23: =M23 -> -0.19381489 | P23: 0.31884301 | Q23: =$E23-P23 -> 0.056085607 | R23: =IFERROR($E23/P23-1,0) -> 0.17590352 | S23: =R23 -> 0.17590352 | U23: 0.19805047 | V23: =IFERROR(U23/$E23,0) -> 0.52823515 | W23: 0.13719869 | X23: =IFERROR(W23/$F23,0) -> 0.47068674 | Y23: =$U23-W23 -> 0.060851789 | Z23: =IFERROR($U23/W23-1,0) -> 0.44353041 | AA23: =Z23 -> 0.44353041 | AC23: 0.31077766 | AD23: =IFERROR(AC23/$P23,0) -> 0.97470433 | AE23: =$U23-AC23 -> -0.11272719 | AF23: =IFERROR($U23/AC23-1,0) -> -0.36272616 | AG23: =AF23 -> -0.36272616 | AI23: 0.12445425 | AJ23: =IFERROR(AI23/$P23,0) -> 0.39033081 | AK23: =$U23-AI23 -> 0.073596223 | AL23: =IFERROR($U23/AI23-1,0) -> 0.59135162 | AM23: =AL23 -> 0.59135162 | AO23: 0 | AP23: =IFERROR(AO23/$E23,0) -> 0 | AQ23: 0 | AR23: =IFERROR(AQ23/$F23,0) -> 0 | AS23: =$AO23-AQ23 -> 0 | AT23: =IFERROR($AO23/AQ23-1,0) -> 0 | AU23: =AT23 -> 0 | AW23: 0 | AX23: =IFERROR(AW23/$P23,0) -> 0 | AY23: =$AO23-AW23 -> 0 | AZ23: =IFERROR($AO23/AW23-1,0) -> 0 | BA23: =AZ23 -> 0 | BC23: 0 | BD23: =IFERROR(BC23/$P23,0) -> 0 | BE23: =$AO23-BC23 -> 0 | BF23: =IFERROR($AO23/BC23-1,0) -> 0 | BG23: =BF23 -> 0 | BI23: =SUM(U23,AO23) -> 0.19805047 | BJ23: =IFERROR(BI23/$E23,0) -> 0.52823515 | BK23: =SUM(W23,AQ23) -> 0.13719869 | BL23: =IFERROR(BK23/$F23,0) -> 0.47068674 | BM23: =$BI23-BK23 -> 0.060851789 | BN23: =BM23/ABS(BK23) -> 0.44353041 | BO23: =BN23 -> 0.44353041 | BQ23: =SUM(AC23,AW23) -> 0.31077766 | BR23: =IFERROR(BQ23/$P23,0) -> 0.97470433 | BS23: =$BI23-BQ23 -> -0.11272719 | BT23: =IFERROR(BS23/ABS(BQ23),"") -> -0.36272616 | BU23: =BT23 -> -0.36272616 | BW23: =SUM(AI23,BC23) -> 0.12445425 | BX23: =IFERROR(BW23/$P23,0) -> 0.39033081 | BY23: =$BI23-BW23 -> 0.073596223 | BZ23: =IFERROR(BY23/ABS(BW23),"") -> 0.59135162 | CA23: =BZ23 -> 0.59135162 | CC23: 0.37492862 | CD23: =$E23-CC23 -> 1.2767565e-15
B24: 1.1.2.1.3 | C24: Praxio - Avacorp | E24: 0.68215782 | F24: 0.88464758 | G24: =$E24-F24 -> -0.20248976 | H24: =IFERROR($E24/F24-1,0) -> -0.22889314 | I24: =H24 -> -0.22889314 | K24: 0.66550108 | L24: =$E24-K24 -> 0.016656743 | M24: =IFERROR($E24/K24-1,0) -> 0.025028874 | N24: =M24 -> 0.025028874 | P24: 0.83961217 | Q24: =$E24-P24 -> -0.15745435 | R24: =IFERROR($E24/P24-1,0) -> -0.18753224 | S24: =R24 -> -0.18753224 | U24: -0.080853175 | V24: =IFERROR(U24/$E24,0) -> -0.11852562 | W24: 0.23757642 | X24: =IFERROR(W24/$F24,0) -> 0.26855488 | Y24: =$U24-W24 -> -0.3184296 | Z24: =IFERROR($U24/W24-1,0) -> -1.3403249 | AA24: =Z24 -> -1.3403249 | AC24: 0.018429921 | AD24: =IFERROR(AC24/$P24,0) -> 0.021950517 | AE24: =$U24-AC24 -> -0.099283096 | AF24: =IFERROR($U24/AC24-1,0) -> -5.3870603 | AG24: =AF24 -> -5.3870603 | AI24: 0.15289327 | AJ24: =IFERROR(AI24/$P24,0) -> 0.18209987 | AK24: =$U24-AI24 -> -0.23374645 | AL24: =IFERROR($U24/AI24-1,0) -> -1.528821 | AM24: =AL24 -> -1.528821 | AO24: 0 | AP24: =IFERROR(AO24/$E24,0) -> 0 | AQ24: 0 | AR24: =IFERROR(AQ24/$F24,0) -> 0 | AS24: =$AO24-AQ24 -> 0 | AT24: =IFERROR($AO24/AQ24-1,0) -> 0 | AU24: =AT24 -> 0 | AW24: 0 | AX24: =IFERROR(AW24/$P24,0) -> 0 | AY24: =$AO24-AW24 -> 0 | AZ24: =IFERROR($AO24/AW24-1,0) -> 0 | BA24: =AZ24 -> 0 | BC24: 0 | BD24: =IFERROR(BC24/$P24,0) -> 0 | BE24: =$AO24-BC24 -> 0 | BF24: =IFERROR($AO24/BC24-1,0) -> 0 | BG24: =BF24 -> 0 | BI24: =SUM(U24,AO24) -> -0.080853175 | BJ24: =IFERROR(BI24/$E24,0) -> -0.11852562 | BK24: =SUM(W24,AQ24) -> 0.23757642 | BL24: =IFERROR(BK24/$F24,0) -> 0.26855488 | BM24: =$BI24-BK24 -> -0.3184296 | BN24: =BM24/ABS(BK24) -> -1.3403249 | BO24: =BN24 -> -1.3403249 | BQ24: =SUM(AC24,AW24) -> 0.018429921 | BR24: =IFERROR(BQ24/$P24,0) -> 0.021950517 | BS24: =$BI24-BQ24 -> -0.099283096 | BT24: =IFERROR(BS24/ABS(BQ24),"") -> -5.3870603 | BU24: =BT24 -> -5.3870603 | BW24: =SUM(AI24,BC24) -> 0.15289327 | BX24: =IFERROR(BW24/$P24,0) -> 0.18209987 | BY24: =$BI24-BW24 -> -0.23374645 | BZ24: =IFERROR(BY24/ABS(BW24),"") -> -1.528821 | CA24: =BZ24 -> -1.528821 | CC24: 0.68215782 | CD24: =$E24-CC24 -> 0
B25: 1.1.2.1.4 | C25: Praxio - Globus | E25: 0.49257452 | F25: 0.58950056 | G25: =$E25-F25 -> -0.096926041 | H25: =IFERROR($E25/F25-1,0) -> -0.16442061 | I25: =H25 -> -0.16442061 | K25: 0.43490543 | L25: =$E25-K25 -> 0.057669089 | M25: =IFERROR($E25/K25-1,0) -> 0.13260145 | N25: =M25 -> 0.13260145 | P25: 0.57095699 | Q25: =$E25-P25 -> -0.078382473 | R25: =IFERROR($E25/P25-1,0) -> -0.13728262 | S25: =R25 -> -0.13728262 | U25: 0.1758209 | V25: =IFERROR(U25/$E25,0) -> 0.35694274 | W25: 0.29033173 | X25: =IFERROR(W25/$F25,0) -> 0.49250459 | Y25: =$U25-W25 -> -0.11451083 | Z25: =IFERROR($U25/W25-1,0) -> -0.39441377 | AA25: =Z25 -> -0.39441377 | AC25: 0.1357366 | AD25: =IFERROR(AC25/$P25,0) -> 0.23773524 | AE25: =$U25-AC25 -> 0.040084297 | AF25: =IFERROR($U25/AC25-1,0) -> 0.29530943 | AG25: =AF25 -> 0.29530943 | AI25: 0.28069088 | AJ25: =IFERROR(AI25/$P25,0) -> 0.49161475 | AK25: =$U25-AI25 -> -0.10486998 | AL25: =IFERROR($U25/AI25-1,0) -> -0.37361379 | AM25: =AL25 -> -0.37361379 | AO25: 0 | AP25: =IFERROR(AO25/$E25,0) -> 0 | AQ25: 0 | AR25: =IFERROR(AQ25/$F25,0) -> 0 | AS25: =$AO25-AQ25 -> 0 | AT25: =IFERROR($AO25/AQ25-1,0) -> 0 | AU25: =AT25 -> 0 | AW25: 0 | AX25: =IFERROR(AW25/$P25,0) -> 0 | AY25: =$AO25-AW25 -> 0 | AZ25: =IFERROR($AO25/AW25-1,0) -> 0 | BA25: =AZ25 -> 0 | BC25: 0 | BD25: =IFERROR(BC25/$P25,0) -> 0 | BE25: =$AO25-BC25 -> 0 | BF25: =IFERROR($AO25/BC25-1,0) -> 0 | BG25: =BF25 -> 0 | BI25: =SUM(U25,AO25) -> 0.1758209 | BJ25: =IFERROR(BI25/$E25,0) -> 0.35694274 | BK25: =SUM(W25,AQ25) -> 0.29033173 | BL25: =IFERROR(BK25/$F25,0) -> 0.49250459 | BM25: =$BI25-BK25 -> -0.11451083 | BN25: =BM25/ABS(BK25) -> -0.39441377 | BO25: =BN25 -> -0.39441377 | BQ25: =SUM(AC25,AW25) -> 0.1357366 | BR25: =IFERROR(BQ25/$P25,0) -> 0.23773524 | BS25: =$BI25-BQ25 -> 0.040084297 | BT25: =IFERROR(BS25/ABS(BQ25),"") -> 0.29530943 | BU25: =BT25 -> 0.29530943 | BW25: =SUM(AI25,BC25) -> 0.28069088 | BX25: =IFERROR(BW25/$P25,0) -> 0.49161475 | BY25: =$BI25-BW25 -> -0.10486998 | BZ25: =IFERROR(BY25/ABS(BW25),"") -> -0.37361379 | CA25: =BZ25 -> -0.37361379 | CC25: 0.49257452 | CD25: =$E25-CC25 -> 6.6613381e-16
B26: 1.1.2.2 | C26: Atua | E26: 3.8871673 | F26: 4.0400673 | G26: =$E26-F26 -> -0.15289996 | H26: =IFERROR($E26/F26-1,0) -> -0.037845895 | I26: =H26 -> -0.037845895 | K26: 3.8615994 | L26: =$E26-K26 -> 0.025567862 | M26: =IFERROR($E26/K26-1,0) -> 0.0066210548 | N26: =M26 -> 0.0066210548 | P26: 3.0472195 | Q26: =$E26-P26 -> 0.83994776 | R26: =IFERROR($E26/P26-1,0) -> 0.27564399 | S26: =R26 -> 0.27564399 | U26: 2.667846 | V26: =IFERROR(U26/$E26,0) -> 0.68632137 | W26: 2.6645002 | X26: =IFERROR(W26/$F26,0) -> 0.65951878 | Y26: =$U26-W26 -> 0.0033457497 | Z26: =IFERROR($U26/W26-1,0) -> 0.0012556763 | AA26: =Z26 -> 0.0012556763 | AC26: 2.74984 | AD26: =IFERROR(AC26/$P26,0) -> 0.90240954 | AE26: =$U26-AC26 -> -0.081993965 | AF26: =IFERROR($U26/AC26-1,0) -> -0.029817723 | AG26: =AF26 -> -0.029817723 | AI26: 2.2085648 | AJ26: =IFERROR(AI26/$P26,0) -> 0.72478033 | AK26: =$U26-AI26 -> 0.4592812 | AL26: =IFERROR($U26/AI26-1,0) -> 0.2079546 | AM26: =AL26 -> 0.2079546 | AO26: -0.3022006 | AP26: =IFERROR(AO26/$E26,0) -> -0.077743142 | AQ26: 0 | AR26: =IFERROR(AQ26/$F26,0) -> 0 | AS26: =$AO26-AQ26 -> -0.3022006 | AT26: =IFERROR($AO26/AQ26-1,0) -> 0 | AU26: =AT26 -> 0 | AW26: -0.26380754 | AX26: =IFERROR(AW26/$P26,0) -> -0.086573197 | AY26: =$AO26-AW26 -> -0.038393063 | AZ26: =IFERROR($AO26/AW26-1,0) -> 0.14553437 | BA26: =AZ26 -> 0.14553437 | BC26: -0.21778847 | BD26: =IFERROR(BC26/$P26,0) -> -0.071471211 | BE26: =$AO26-BC26 -> -0.08441213 | BF26: =IFERROR($AO26/BC26-1,0) -> 0.38758769 | BG26: =BF26 -> 0.38758769 | BI26: =SUM(U26,AO26) -> 2.3656454 | BJ26: =IFERROR(BI26/$E26,0) -> 0.60857823 | BK26: =SUM(W26,AQ26) -> 2.6645002 | BL26: =IFERROR(BK26/$F26,0) -> 0.65951878 | BM26: =$BI26-BK26 -> -0.29885485 | BN26: =BM26/ABS(BK26) -> -0.11216169 | BO26: =BN26 -> -0.11216169 | BQ26: =SUM(AC26,AW26) -> 2.4860324 | BR26: =IFERROR(BQ26/$P26,0) -> 0.81583634 | BS26: =$BI26-BQ26 -> -0.12038703 | BT26: =IFERROR(BS26/ABS(BQ26),"") -> -0.048425366 | BU26: =BT26 -> -0.048425366 | BW26: =SUM(AI26,BC26) -> 1.9907763 | BX26: =IFERROR(BW26/$P26,0) -> 0.65330912 | BY26: =$BI26-BW26 -> 0.37486907 | BZ26: =IFERROR(BY26/ABS(BW26),"") -> 0.18830296 | CA26: =BZ26 -> 0.18830296 | CC26: 3.8871673 | CD26: =$E26-CC26 -> 7.5495166e-15
B27: 1.1.2.3 | C27: ATSLog Jornada | E27: 1.3923553 | F27: 1.5623738 | G27: =$E27-F27 -> -0.17001844 | H27: =IFERROR($E27/F27-1,0) -> -0.10882059 | I27: =H27 -> -0.10882059 | K27: 1.4076663 | L27: =$E27-K27 -> -0.015310925 | M27: =IFERROR($E27/K27-1,0) -> -0.010876815 | N27: =M27 -> -0.010876815 | P27: 1.1003274 | Q27: =$E27-P27 -> 0.29202793 | R27: =IFERROR($E27/P27-1,0) -> 0.26540093 | S27: =R27 -> 0.26540093 | U27: 0.40930214 | V27: =IFERROR(U27/$E27,0) -> 0.29396385 | W27: 0.6668569 | X27: =IFERROR(W27/$F27,0) -> 0.42682289 | Y27: =$U27-W27 -> -0.25755475 | Z27: =IFERROR($U27/W27-1,0) -> -0.38622193 | AA27: =Z27 -> -0.38622193 | AC27: 0.51214938 | AD27: =IFERROR(AC27/$P27,0) -> 0.4654518 | AE27: =$U27-AC27 -> -0.10284724 | AF27: =IFERROR($U27/AC27-1,0) -> -0.20081493 | AG27: =AF27 -> -0.20081493 | AI27: 0.26870433 | AJ27: =IFERROR(AI27/$P27,0) -> 0.24420398 | AK27: =$U27-AI27 -> 0.14059781 | AL27: =IFERROR($U27/AI27-1,0) -> 0.52324355 | AM27: =AL27 -> 0.52324355 | AO27: -0.00189889 | AP27: =IFERROR(AO27/$E27,0) -> -0.001363797 | AQ27: 0 | AR27: =IFERROR(AQ27/$F27,0) -> 0 | AS27: =$AO27-AQ27 -> -0.00189889 | AT27: =IFERROR($AO27/AQ27-1,0) -> 0 | AU27: =AT27 -> 0 | AW27: 0 | AX27: =IFERROR(AW27/$P27,0) -> 0 | AY27: =$AO27-AW27 -> -0.00189889 | AZ27: =IFERROR($AO27/AW27-1,0) -> 0 | BA27: =AZ27 -> 0 | BC27: 0 | BD27: =IFERROR(BC27/$P27,0) -> 0 | BE27: =$AO27-BC27 -> -0.00189889 | BF27: =IFERROR($AO27/BC27-1,0) -> 0 | BG27: =BF27 -> 0 | BI27: =SUM(U27,AO27) -> 0.40740325 | BJ27: =IFERROR(BI27/$E27,0) -> 0.29260005 | BK27: =SUM(W27,AQ27) -> 0.6668569 | BL27: =IFERROR(BK27/$F27,0) -> 0.42682289 | BM27: =$BI27-BK27 -> -0.25945364 | BN27: =BM27/ABS(BK27) -> -0.38906945 | BO27: =BN27 -> -0.38906945 | BQ27: =SUM(AC27,AW27) -> 0.51214938 | BR27: =IFERROR(BQ27/$P27,0) -> 0.4654518 | BS27: =$BI27-BQ27 -> -0.10474613 | BT27: =IFERROR(BS27/ABS(BQ27),"") -> -0.20452262 | BU27: =BT27 -> -0.20452262 | BW27: =SUM(AI27,BC27) -> 0.26870433 | BX27: =IFERROR(BW27/$P27,0) -> 0.24420398 | BY27: =$BI27-BW27 -> 0.13869892 | BZ27: =IFERROR(BY27/ABS(BW27),"") -> 0.51617671 | CA27: =BZ27 -> 0.51617671 | CC27: 1.3676908 | CD27: =$E27-CC27 -> 0.02466451
B28: 1.1.2.4 | C28: NSKote | E28: 0.43388151 | F28: 0.45246414 | G28: =$E28-F28 -> -0.018582629 | H28: =IFERROR($E28/F28-1,0) -> -0.041069838 | I28: =H28 -> -0.041069838 | K28: 0.44266121 | L28: =$E28-K28 -> -0.0087796961 | M28: =IFERROR($E28/K28-1,0) -> -0.019833896 | N28: =M28 -> -0.019833896 | P28: 0.38223537 | Q28: =$E28-P28 -> 0.05164614 | R28: =IFERROR($E28/P28-1,0) -> 0.13511607 | S28: =R28 -> 0.13511607 | U28: 0.14379849 | V28: =IFERROR(U28/$E28,0) -> 0.33142342 | W28: 0.20353398 | X28: =IFERROR(W28/$F28,0) -> 0.4498345 | Y28: =$U28-W28 -> -0.059735487 | Z28: =IFERROR($U28/W28-1,0) -> -0.29349147 | AA28: =Z28 -> -0.29349147 | AC28: 0.19373105 | AD28: =IFERROR(AC28/$P28,0) -> 0.50683705 | AE28: =$U28-AC28 -> -0.049932554 | AF28: =IFERROR($U28/AC28-1,0) -> -0.25774162 | AG28: =AF28 -> -0.25774162 | AI28: 0.13437931 | AJ28: =IFERROR(AI28/$P28,0) -> 0.35156168 | AK28: =$U28-AI28 -> 0.0094191833 | AL28: =IFERROR($U28/AI28-1,0) -> 0.070094 | AM28: =AL28 -> 0.070094 | AO28: 0 | AP28: =IFERROR(AO28/$E28,0) -> 0 | AQ28: 0 | AR28: =IFERROR(AQ28/$F28,0) -> 0 | AS28: =$AO28-AQ28 -> 0 | AT28: =IFERROR($AO28/AQ28-1,0) -> 0 | AU28: =AT28 -> 0 | AW28: 0 | AX28: =IFERROR(AW28/$P28,0) -> 0 | AY28: =$AO28-AW28 -> 0 | AZ28: =IFERROR($AO28/AW28-1,0) -> 0 | BA28: =AZ28 -> 0 | BC28: 0 | BD28: =IFERROR(BC28/$P28,0) -> 0 | BE28: =$AO28-BC28 -> 0 | BF28: =IFERROR($AO28/BC28-1,0) -> 0 | BG28: =BF28 -> 0 | BI28: =SUM(U28,AO28) -> 0.14379849 | BJ28: =IFERROR(BI28/$E28,0) -> 0.33142342 | BK28: =SUM(W28,AQ28) -> 0.20353398 | BL28: =IFERROR(BK28/$F28,0) -> 0.4498345 | BM28: =$BI28-BK28 -> -0.059735487 | BN28: =BM28/ABS(BK28) -> -0.29349147 | BO28: =BN28 -> -0.29349147 | BQ28: =SUM(AC28,AW28) -> 0.19373105 | BR28: =IFERROR(BQ28/$P28,0) -> 0.50683705 | BS28: =$BI28-BQ28 -> -0.049932554 | BT28: =IFERROR(BS28/ABS(BQ28),"") -> -0.25774162 | BU28: =BT28 -> -0.25774162 | BW28: =SUM(AI28,BC28) -> 0.13437931 | BX28: =IFERROR(BW28/$P28,0) -> 0.35156168 | BY28: =$BI28-BW28 -> 0.0094191833 | BZ28: =IFERROR(BY28/ABS(BW28),"") -> 0.070094 | CA28: =BZ28 -> 0.070094 | CC28: 0.43388151 | CD28: =$E28-CC28 -> 0
B29: 1.1.3 | C29: Signa | E29: 2.3404616 | F29: 2.324363 | G29: =$E29-F29 -> 0.016098559 | H29: =IFERROR($E29/F29-1,0) -> 0.006926009 | I29: =H29 -> 0.006926009 | K29: 2.3187285 | L29: =$E29-K29 -> 0.02173301 | M29: =IFERROR($E29/K29-1,0) -> 0.0093728133 | N29: =M29 -> 0.0093728133 | P29: 1.785789 | Q29: =$E29-P29 -> 0.5546726 | R29: =IFERROR($E29/P29-1,0) -> 0.31060366 | S29: =R29 -> 0.31060366 | U29: 0.73508178 | V29: =IFERROR(U29/$E29,0) -> 0.31407556 | W29: 0.57302046 | X29: =IFERROR(W29/$F29,0) -> 0.24652795 | Y29: =$U29-W29 -> 0.16206133 | Z29: =IFERROR($U29/W29-1,0) -> 0.28281945 | AA29: =Z29 -> 0.28281945 | AC29: 0.6088209 | AD29: =IFERROR(AC29/$P29,0) -> 0.34092545 | AE29: =$U29-AC29 -> 0.12626089 | AF29: =IFERROR($U29/AC29-1,0) -> 0.20738593 | AG29: =AF29 -> 0.20738593 | AI29: 0.66697228 | AJ29: =IFERROR(AI29/$P29,0) -> 0.37348886 | AK29: =$U29-AI29 -> 0.068109505 | AL29: =IFERROR($U29/AI29-1,0) -> 0.10211744 | AM29: =AL29 -> 0.10211744 | AO29: 0 | AP29: =IFERROR(AO29/$E29,0) -> 0 | AQ29: 0 | AR29: =IFERROR(AQ29/$F29,0) -> 0 | AS29: =$AO29-AQ29 -> 0 | AT29: =IFERROR($AO29/AQ29-1,0) -> 0 | AU29: =AT29 -> 0 | AW29: 0 | AX29: =IFERROR(AW29/$P29,0) -> 0 | AY29: =$AO29-AW29 -> 0 | AZ29: =IFERROR($AO29/AW29-1,0) -> 0 | BA29: =AZ29 -> 0 | BC29: 0.000789 | BD29: =IFERROR(BC29/$P29,0) -> 0.00044182152 | BE29: =$AO29-BC29 -> -0.000789 | BF29: =IFERROR($AO29/BC29-1,0) -> -1 | BG29: =BF29 -> -1 | BI29: =SUM(U29,AO29) -> 0.73508178 | BJ29: =IFERROR(BI29/$E29,0) -> 0.31407556 | BK29: =SUM(W29,AQ29) -> 0.57302046 | BL29: =IFERROR(BK29/$F29,0) -> 0.24652795 | BM29: =$BI29-BK29 -> 0.16206133 | BN29: =BM29/ABS(BK29) -> 0.28281945 | BO29: =BN29 -> 0.28281945 | BQ29: =SUM(AC29,AW29) -> 0.6088209 | BR29: =IFERROR(BQ29/$P29,0) -> 0.34092545 | BS29: =$BI29-BQ29 -> 0.12626089 | BT29: =IFERROR(BS29/ABS(BQ29),"") -> 0.20738593 | BU29: =BT29 -> 0.20738593 | BW29: =SUM(AI29,BC29) -> 0.66776128 | BX29: =IFERROR(BW29/$P29,0) -> 0.37393068 | BY29: =$BI29-BW29 -> 0.067320505 | BZ29: =IFERROR(BY29/ABS(BW29),"") -> 0.10081523 | CA29: =BZ29 -> 0.10081523 | CC29: 2.3404616 | CD29: =$E29-CC29 -> 0
B30: 1.2 | C30: Fintech | E30: =SUM(E31,E35,E36) -> 5.5477029 | F30: =SUM(F31,F35,F36) -> 4.2772429 | G30: =$E30-F30 -> 1.2704601 | H30: =IFERROR($E30/F30-1,0) -> 0.29702781 | I30: =H30 -> 0.29702781 | K30: =SUM(K31,K35,K36) -> 5.2688322 | L30: =$E30-K30 -> 0.27887071 | M30: =IFERROR($E30/K30-1,0) -> 0.052928372 | N30: =M30 -> 0.052928372 | P30: =SUM(P31,P35,P36) -> 2.4459342 | Q30: =$E30-P30 -> 3.1017687 | R30: =IFERROR($E30/P30-1,0) -> 1.2681325 | S30: =R30 -> 1.2681325 | U30: =SUM(U31,U35,U36) -> 3.0729319 | V30: =IFERROR(U30/$E30,0) -> 0.55391069 | W30: =SUM(W31,W35,W36) -> 1.6160157 | X30: =IFERROR(W30/$F30,0) -> 0.37781715 | Y30: =$U30-W30 -> 1.4569162 | Z30: =IFERROR($U30/W30-1,0) -> 0.90154833 | AA30: =Z30 -> 0.90154833 | AC30: =SUM(AC31,AC35,AC36) -> 2.590605 | AD30: =IFERROR(AC30/$P30,0) -> 1.0591475 | AE30: =$U30-AC30 -> 0.48232689 | AF30: =IFERROR($U30/AC30-1,0) -> 0.18618311 | AG30: =AF30 -> 0.18618311 | AI30: =SUM(AI31,AI35,AI36) -> 1.1495372 | AJ30: =IFERROR(AI30/$P30,0) -> 0.46997877 | AK30: =$U30-AI30 -> 1.9233947 | AL30: =IFERROR($U30/AI30-1,0) -> 1.6731905 | AM30: =AL30 -> 1.6731905 | AO30: =SUM(AO31,AO35,AO36) -> -0.135936 | AP30: =IFERROR(AO30/$E30,0) -> -0.024503115 | AQ30: =SUM(AQ31,AQ35,AQ36) -> -0.0821 | AR30: =IFERROR(AQ30/$F30,0) -> -0.019194608 | AS30: =$AO30-AQ30 -> -0.053836 | AT30: =IFERROR($AO30/AQ30-1,0) -> 0.65573691 | AU30: =AT30 -> 0.65573691 | AW30: =SUM(AW31,AW35,AW36) -> -0.0821 | AX30: =IFERROR(AW30/$P30,0) -> -0.033565906 | AY30: =$AO30-AW30 -> -0.053836 | AZ30: =IFERROR($AO30/AW30-1,0) -> 0.65573691 | BA30: =AZ30 -> 0.65573691 | BC30: =SUM(BC31,BC35,BC36) -> 0 | BD30: =IFERROR(BC30/$P30,0) -> 0 | BE30: =$AO30-BC30 -> -0.135936 | BF30: =IFERROR($AO30/BC30-1,0) -> 0 | BG30: =BF30 -> 0 | BI30: =SUM(BI31,BI35,BI36) -> 2.9369959 | BJ30: =IFERROR(BI30/$E30,0) -> 0.52940757 | BK30: =SUM(BK31,BK35,BK36) -> 1.5339157 | BL30: =IFERROR(BK30/$F30,0) -> 0.35862254 | BM30: =$BI30-BK30 -> 1.4030802 | BN30: =BM30/ABS(BK30) -> 0.91470493 | BO30: =BN30 -> 0.91470493 | BQ30: =SUM(BQ31,BQ35,BQ36) -> 2.508505 | BR30: =IFERROR(BQ30/$P30,0) -> 1.0255815 | BS30: =$BI30-BQ30 -> 0.42849089 | BT30: =IFERROR(BS30/ABS(BQ30),"") -> 0.17081524 | BU30: =BT30 -> 0.17081524 | BW30: =SUM(BW31,BW35,BW36) -> 1.1495372 | BX30: =IFERROR(BW30/$P30,0) -> 0.46997877 | BY30: =$BI30-BW30 -> 1.7874587 | BZ30: =IFERROR(BY30/ABS(BW30),"") -> 1.5549377 | CA30: =BZ30 -> 1.5549377 | CC30: =SUM(CC31,CC35,CC36) -> 5.5480476 | CD30: =$E30-CC30 -> -0.00034474144
B31: 1.2.1 | C31: e-frete | E31: =SUM(E32:E34) -> 2.3072107 | F31: =SUM(F32:F34) -> 1.3345512 | G31: =$E31-F31 -> 0.97265949 | H31: =IFERROR($E31/F31-1,0) -> 0.72882891 | I31: =H31 -> 0.72882891 | K31: =SUM(K32:K34) -> 2.0174375 | L31: =$E31-K31 -> 0.28977318 | M31: =IFERROR($E31/K31-1,0) -> 0.14363428 | N31: =M31 -> 0.14363428 | P31: =SUM(P32:P34) -> 1.0490779 | Q31: =$E31-P31 -> 1.2581327 | R31: =IFERROR($E31/P31-1,0) -> 1.1992748 | S31: =R31 -> 1.1992748 | U31: =SUM(U32:U34) -> 1.4424687 | V31: =IFERROR(U31/$E31,0) -> 0.62520026 | W31: =SUM(W32:W34) -> 0.52575402 | X31: =IFERROR(W31/$F31,0) -> 0.39395568 | Y31: =$U31-W31 -> 0.91671469 | Z31: =IFERROR($U31/W31-1,0) -> 1.743619 | AA31: =Z31 -> 1.743619 | AC31: =SUM(AC32:AC34) -> 1.1916403 | AD31: =IFERROR(AC31/$P31,0) -> 1.1358931 | AE31: =$U31-AC31 -> 0.25082838 | AF31: =IFERROR($U31/AC31-1,0) -> 0.21049 | AG31: =AF31 -> 0.21049 | AI31: =SUM(AI32:AI34) -> 0.14251153 | AJ31: =IFERROR(AI31/$P31,0) -> 0.13584456 | AK31: =$U31-AI31 -> 1.2999572 | AL31: =IFERROR($U31/AI31-1,0) -> 9.1217688 | AM31: =AL31 -> 9.1217688 | AO31: =SUM(AO32:AO34) -> -0.134415 | AP31: =IFERROR(AO31/$E31,0) -> -0.058258659 | AQ31: =SUM(AQ32:AQ34) -> -0.08 | AR31: =IFERROR(AQ31/$F31,0) -> -0.059945247 | AS31: =$AO31-AQ31 -> -0.054415 | AT31: =IFERROR($AO31/AQ31-1,0) -> 0.6801875 | AU31: =AT31 -> 0.6801875 | AW31: =SUM(AW32:AW34) -> -0.08 | AX31: =IFERROR(AW31/$P31,0) -> -0.076257442 | AY31: =$AO31-AW31 -> -0.054415 | AZ31: =IFERROR($AO31/AW31-1,0) -> 0.6801875 | BA31: =AZ31 -> 0.6801875 | BC31: =SUM(BC32:BC34) -> 0 | BD31: =IFERROR(BC31/$P31,0) -> 0 | BE31: =$AO31-BC31 -> -0.134415 | BF31: =IFERROR($AO31/BC31-1,0) -> 0 | BG31: =BF31 -> 0 | BI31: =SUM(BI32:BI34) -> 1.3080537 | BJ31: =IFERROR(BI31/$E31,0) -> 0.5669416 | BK31: =SUM(BK32:BK34) -> 0.44575402 | BL31: =IFERROR(BK31/$F31,0) -> 0.33401043 | BM31: =$BI31-BK31 -> 0.86229969 | BN31: =BM31/ABS(BK31) -> 1.9344743 | BO31: =BN31 -> 1.9344743 | BQ31: =SUM(BQ32:BQ34) -> 1.1116403 | BR31: =IFERROR(BQ31/$P31,0) -> 1.0596356 | BS31: =$BI31-BQ31 -> 0.19641338 | BT31: =IFERROR(BS31/ABS(BQ31),"") -> 0.17668788 | BU31: =BT31 -> 0.17668788 | BW31: =SUM(BW32:BW34) -> 0.14251153 | BX31: =IFERROR(BW31/$P31,0) -> 0.13584456 | BY31: =$BI31-BW31 -> 1.1655422 | BZ31: =IFERROR(BY31/ABS(BW31),"") -> 8.1785819 | CA31: =BZ31 -> 8.1785819 | CC31: =SUM(CC32:CC34) -> 2.3072107 | CD31: =$E31-CC31 -> -2.3750344e-09
B32: 1.2.1.1 | C32: e-frete Meio Pagamento | E32: 2.3072107 | F32: 1.3345512 | G32: =$E32-F32 -> 0.97265949 | H32: =IFERROR($E32/F32-1,0) -> 0.72882891 | I32: =H32 -> 0.72882891 | K32: 2.0174375 | L32: =$E32-K32 -> 0.28977318 | M32: =IFERROR($E32/K32-1,0) -> 0.14363428 | N32: =M32 -> 0.14363428 | P32: 1.0490779 | Q32: =$E32-P32 -> 1.2581327 | R32: =IFERROR($E32/P32-1,0) -> 1.1992748 | S32: =R32 -> 1.1992748 | U32: 1.5065336 | V32: =IFERROR(U32/$E32,0) -> 0.6529675 | W32: 0.67535822 | X32: =IFERROR(W32/$F32,0) -> 0.50605644 | Y32: =$U32-W32 -> 0.83117537 | Z32: =IFERROR($U32/W32-1,0) -> 1.2307178 | AA32: =Z32 -> 1.2307178 | AC32: 1.3412445 | AD32: =IFERROR(AC32/$P32,0) -> 1.2784985 | AE32: =$U32-AC32 -> 0.16528906 | AF32: =IFERROR($U32/AC32-1,0) -> 0.12323559 | AG32: =AF32 -> 0.12323559 | AI32: 0.32660147 | AJ32: =IFERROR(AI32/$P32,0) -> 0.31132241 | AK32: =$U32-AI32 -> 1.1799321 | AL32: =IFERROR($U32/AI32-1,0) -> 3.6127582 | AM32: =AL32 -> 3.6127582 | AO32: -0.134415 | AP32: =IFERROR(AO32/$E32,0) -> -0.058258659 | AQ32: -0.08 | AR32: =IFERROR(AQ32/$F32,0) -> -0.059945247 | AS32: =$AO32-AQ32 -> -0.054415 | AT32: =IFERROR($AO32/AQ32-1,0) -> 0.6801875 | AU32: =AT32 -> 0.6801875 | AW32: -0.08 | AX32: =IFERROR(AW32/$P32,0) -> -0.076257442 | AY32: =$AO32-AW32 -> -0.054415 | AZ32: =IFERROR($AO32/AW32-1,0) -> 0.6801875 | BA32: =AZ32 -> 0.6801875 | BC32: 0 | BD32: =IFERROR(BC32/$P32,0) -> 0 | BE32: =$AO32-BC32 -> -0.134415 | BF32: =IFERROR($AO32/BC32-1,0) -> 0 | BG32: =BF32 -> 0 | BI32: =SUM(U32,AO32) -> 1.3721186 | BJ32: =IFERROR(BI32/$E32,0) -> 0.59470884 | BK32: =SUM(W32,AQ32) -> 0.59535822 | BL32: =IFERROR(BK32/$F32,0) -> 0.44611119 | BM32: =$BI32-BK32 -> 0.77676037 | BN32: =BM32/ABS(BK32) -> 1.3046941 | BO32: =BN32 -> 1.3046941 | BQ32: =SUM(AC32,AW32) -> 1.2612445 | BR32: =IFERROR(BQ32/$P32,0) -> 1.202241 | BS32: =$BI32-BQ32 -> 0.11087406 | BT32: =IFERROR(BS32/ABS(BQ32),"") -> 0.087908455 | BU32: =BT32 -> 0.087908455 | BW32: =SUM(AI32,BC32) -> 0.32660147 | BX32: =IFERROR(BW32/$P32,0) -> 0.31132241 | BY32: =$BI32-BW32 -> 1.0455171 | BZ32: =IFERROR(BY32/ABS(BW32),"") -> 3.2012015 | CA32: =BZ32 -> 3.2012015 | CC32: 2.3072107 | CD32: =$E32-CC32 -> -2.3750344e-09
